Workbook

Sheet Instructions
A1: DATA AGENT EVALUATION TEMPLATE
A3: Sheet | B3: Purpose | C3: Who fills
A4: Gold_Dataset | B4: Test questions + ground truth SQL + expected results | C4: DA Team
A5: Agent_A_Results | B5: Output from Agent A (existing agent) | C5: Auto / Evaluator
A6: Agent_B_Results | B6: Output from Agent B (new agent) | C6: Auto / Evaluator
A7: Evaluation_Scores | B7: Per-question scoring for both agents | C7: Evaluator + Formulas
A8: Head_to_Head | B8: Pairwise comparison & statistical summary | C8: Formulas
A9: Error_Analysis | B9: Failure categorization & root cause | C9: Evaluator
A10: Summary_Dashboard | B10: Aggregated metrics & final report | C10: Formulas
A12: COLOR LEGEND
A13: Yellow cells | B13: Input required — fill these in
A14: Green cells | B14: Auto-calculated by formulas
A15: Gray cells | B15: Reference / locked — do not edit
A17: WORKFLOW
A18: Step 1 | B18: Fill Gold_Dataset with real questions + gold SQL from DA team
A19: Step 2 | B19: Run both agents, paste outputs into Agent_A/B_Results sheets
A20: Step 3 | B20: Fill Evaluation_Scores (some auto, some manual judgment)
A21: Step 4 | B21: Review Head_to_Head and Summary_Dashboard for results
A22: Step 5 | B22: Fill Error_Analysis for failures to guide improvements

Sheet README FIRST
A1: Giải thích từng cột, từng sheet Sheet 1: Gold_Dataset Đây là foundation — mọi sheet khác đều reference ngược về đây. Chất lượng eval phụ thuộc hoàn toàn vào chất lượng sheet này. ID — mã định danh duy nhất cho mỗi test case (Q001, Q002...). Convention nào cũng được, miễn unique. Tất cả sheets khác dùng ID này để cross-reference. Question (NL) — câu hỏi bằng ngôn ngữ tự nhiên, đúng như cách user/stakeholder thực sự hỏi. Không được "clean up" hay rephrase cho rõ ràng hơn, vì bạn đang test khả năng agent hiểu ngôn ngữ thực tế. Ví dụ: "cho t biết GMV tháng rồi chia theo category" chứ không phải "Tính tổng GMV tháng 1/2025 group by category_name từ bảng orders". Category — phân loại pattern SQL mà câu hỏi yêu cầu. Mục đích là sau này breakdown performance theo từng pattern để biết agent yếu ở đâu. Các giá trị: Aggregation: SUM, COUNT, AVG, GROUP BY Ranking + Filter: TOP N, HAVING, ORDER BY + LIMIT JOIN: multi-table queries Window + Complex: window functions (ROW_NUMBER, LAG, LEAD), CTEs Subquery: nested SELECT Date/Time: date ranges, date math, timezone handling Conditional Logic: CASE WHEN, IF Multi-step: cần nhiều bước logic, kết hợp nhiều pattern trên Ambiguous: câu hỏi cố tình mơ hồ, test khả năng agent hỏi lại Một question có thể thuộc nhiều category — chọn category dominant nhất. Difficulty — độ khó, dùng để stratify kết quả. Tiêu chí phân loại: Simple: 1 table, basic WHERE/GROUP BY, không JOIN Moderate: 2-3 JOINs, hoặc có subquery/HAVING Complex: CTEs, window functions, nested aggregations, business logic phức tạp Ambiguous: câu hỏi không đủ thông tin để viết SQL duy nhất — agent đúng khi hỏi lại thay vì đoán Target Tables — danh sách tables mà gold SQL cần dùng. Đây là ground truth cho metric Schema Linking — nếu agent dùng đúng tables này thì schema linking đúng. Liệt kê comma-separated. Target Columns — tương tự, các columns quan trọng trong gold SQL. Không cần liệt kê hết mọi column, chỉ cần các columns mang semantic meaning (columns trong SELECT, WHERE, JOIN conditions). Business Rules / Notes — các implicit rules mà agent cần biết để viết SQL đúng. Đây là phần hay bị miss nhất. Ví dụ: "GMV chỉ tính orders có status='completed'", "active user = có ít nhất 1 transaction trong 30 ngày", "soft delete dùng cột is_deleted". Nếu gold SQL phụ thuộc vào business rule mà không có trong schema, ghi ở đây. Gold SQL — SQL chuẩn do DA team viết. Đây là reference answer, không phải unique answer. Hai SQL khác nhau hoàn toàn nhưng ra cùng result đều đúng. Gold SQL dùng cho 2 mục đích: so sánh result set (primary) và so sánh efficiency/readability (secondary). Gold Result (summary) — mô tả tóm tắt kết quả khi chạy gold SQL. Không cần paste full result set, chỉ cần đủ để verify nhanh: "5 rows, total GMV = 12.5B", "empty result set", "1 row, value = 42.3%". Nếu result lớn, ghi pattern thay vì data cụ thể. Expected Row Count — số rows trả về. Dùng làm quick sanity check — nếu agent trả 1000 rows mà expected là 10, chắc chắn sai mà không cần so sánh chi tiết. Dataset Split — quan trọng nhất về mặt methodology: dev: dùng trong quá trình develop, iterate, debug agent. Được phép nhìn đi nhìn lại, tune prompt dựa trên kết quả eval: held-out set, chỉ chạy khi muốn đo chính thức. Không bao giờ dùng để guide development decisions ambiguous: subset riêng cho câu hỏi mơ hồ, đánh giá khả năng clarification Sheet 2 & 3: Agent_A_Results / Agent_B_Results Cấu trúc giống nhau, mỗi sheet chứa output của một agent. A = agent hiện tại (baseline), B = agent mới. ID — auto-link từ Gold_Dataset. Không sửa. Question (ref) — auto-link câu hỏi từ Gold_Dataset. Để tiện đọc mà không phải switch sheet. Generated SQL — SQL mà agent sinh ra. Paste nguyên văn, kể cả nếu sai syntax. Đây là raw output, không chỉnh sửa. Execution Status — kết quả khi chạy generated SQL trên DB: SUCCESS: parse + execute thành công, có result SYNTAX_ERROR: SQL không parse được (thiếu comma, sai keyword...) RUNTIME_ERROR: parse OK nhưng execute fail (column not found, type mismatch...) TIMEOUT: query chạy quá lâu, bị kill EMPTY_RESULT: execute OK nhưng 0 rows — có thể đúng (nếu gold cũng 0) hoặc sai HALLUCINATION: reference table hoặc column không tồn tại trong schema. Đây là failure mode nghiêm trọng nhất vì agent "bịa" ra thứ không có Query Result (summary) — tóm tắt result tương tự cột Gold Result. Dùng để eyeball comparison nhanh. Result Row Count — số rows trả về. So với Expected Row Count ở Gold_Dataset. Execution Time (ms) — thời gian execute query, tính bằng milliseconds. Dùng cho latency comparison và efficiency evaluation. Nếu agent A trả đúng trong 200ms nhưng agent B cần 15 giây, đó là signal quan trọng. Tables Used — liệt kê tables mà generated SQL thực sự dùng. So với Target Tables ở Gold_Dataset → tính Schema Linking accuracy. Nếu agent dùng đúng tables nhưng sai columns, vấn đề ở level khác vs dùng sai tables hoàn toàn. Columns Used — tương tự cho columns. Agent Confidence Score — nếu agent có output confidence/probability thì ghi ở đây. Dùng để phân tích calibration: agent nói 95% confident nhưng sai 40% thì calibration tệ. Nếu agent không output confidence thì để trống. Retries / Self-corrections — số lần agent tự retry khi gặp lỗi. Ví dụ: SQL đầu tiên syntax error → agent tự sửa → lần 2 chạy OK. Ghi "1 retry, fixed syntax". Metric này đo agentic loop quality — agent tốt phải biết self-correct. Error Message (if any) — error message từ DB khi execute fail. Paste nguyên văn. Ví dụ: ERROR: column "user_name" does not exist. Did you mean "username"?. Giúp phân loại error pattern ở sheet Error_Analysis. Notes — ghi chú tự do. Ví dụ: "SQL đúng nhưng dùng full table scan", "agent hỏi lại 1 lần trước khi generate", "result đúng nhưng column order khác gold". Sheet 4: Evaluation_Scores Đây là sheet scoring chính, nơi mọi metric được tính cho từng question. ID, Difficulty, Category — auto-link từ Gold_Dataset. Context để breakdown sau này. A/B: Valid SQL (formula, auto) — binary 1/0. Tự tính từ Execution Status ở Agent Results: SUCCESS → 1, mọi thứ khác → 0. Đây là prerequisite metric — nếu SQL không valid thì các metric khác không applicable. A/B: Exact Result Match (manual) — binary 1/0. Bạn so sánh result set của agent với gold result. 1 = result sets identical (order-insensitive), 0 = khác. Đây là metric quan trọng nhất trong toàn bộ eval. Lưu ý: 2 SQL hoàn toàn khác nhau có thể cho cùng result → cả hai đều score 1. A/B: Partial Credit (manual) — số từ 0.0 đến 1.0. Dùng khi result không exact match nhưng "gần đúng". Cách tính: bao nhiêu % columns trong SELECT đúng × bao nhiêu % rows đúng. Ví dụ: gold trả 5 columns 10 rows, agent trả đúng 4 columns 10 rows → partial credit ≈ 0.8. Metric này tránh binary harsh judgment — agent sai 1 column nhưng đúng 90% vẫn nên được credit. A/B: Schema Linking (manual) — số từ 0.0 đến 1.0. So sánh tables + columns mà agent dùng vs Target Tables/Columns ở Gold_Dataset. Tính bằng F1 score: precision (bao nhiêu % tables agent dùng là đúng) × recall (bao nhiêu % tables cần dùng mà agent dùng). Diagnostic metric — nếu cái này thấp, vấn đề nằm ở schema retrieval/understanding, không phải SQL generation. A/B: Efficiency Score (manual) — số từ 0.0 đến 1.0. Đánh giá chất lượng SQL khi cả 2 đều ra đúng result. Criteria: có dùng index không, có unnecessary full table scan không, có redundant subquery không, execution time so với gold SQL. Scoring guide: 1.0 = ngang hoặc tốt hơn gold, 0.7 = acceptable nhưng suboptimal, 0.3 = chạy được nhưng sẽ có vấn đề trên production data, 0.0 = timeout hoặc resource-intensive đến mức không dùng được. Winner (EX) (formula, auto) — so sánh Exact Result Match giữa A và B cho question đó. A nếu A đúng B sai, B nếu ngược lại, Tie nếu cả hai cùng đúng hoặc cùng sai. Winner (Overall) (manual) — đánh giá tổng hợp khi xét tất cả metrics. Có thể khác Winner (EX) — ví dụ cả 2 đều exact match nhưng B hiệu quả hơn nhiều → Overall winner = B. LLM Judge Score (manual) — điểm từ LLM-as-Judge nếu bạn dùng. Paste score hoặc verdict (A/B/Tie) từ judge model. Optional nhưng hữu ích cho cases mà cả 2 đều "đúng" nhưng quality khác nhau. Notes — ghi chú cho scoring decisions không rõ ràng. Ví dụ: "Cả 2 result gần giống, A thiếu 1 row do filter condition khác". Sheet 5: Head_to_Head Tự động tính toàn bộ từ Evaluation_Scores. Không cần điền gì. McNemar's Contingency Table — bảng 2×2 đếm 4 trường hợp: Both Correct (a): cả A và B đều exact match. Không cho biết agent nào tốt hơn A Correct, B Wrong (b): cases mà A thắng. Đây là competitive advantage của A A Wrong, B Correct (c): cases mà B thắng. Đây là improvement của B so với A Both Wrong (d): cả 2 đều fail. Hardest cases, cần fundamentally different approach McNemar Statistic (χ²) — (b - c)² / (b + c). Chỉ xét ô b và c (disagreement cells), bỏ qua a và d. Logic: nếu 2 agents thực sự ngang nhau, b và c nên gần bằng nhau. Nếu χ² lớn → khác biệt có ý nghĩa thống kê. Critical value — 3.841 (chi-square, df=1, α=0.05). Nếu χ² > 3.841 thì p < 0.05, reject null hypothesis rằng 2 agents ngang nhau. Significant? — YES/NO dựa trên so sánh χ² với critical value. Nếu NO thì khác biệt có thể chỉ là noise, cần thêm data hoặc chấp nhận 2 agents ngang nhau. Breakdown by Difficulty — với mỗi level (Simple/Moderate/Complex/Ambiguous): N: số questions thuộc level đó Agent A/B EX Acc: % exact match cho level đó Δ (B - A): chênh lệch. Dương = B tốt hơn Winner: agent nào win ở level này Ý nghĩa: agent B có thể overall tốt hơn 5% nhưng thực ra chỉ win ở Simple queries (+10%) và thua ở Complex (-8%). Breakdown cho bạn thấy điều này. Breakdown by Category — logic tương tự nhưng chia theo query pattern thay vì difficulty. Cho biết agent mạnh/yếu ở pattern SQL nào cụ thể. Sheet 6: Error_Analysis Sheet quan trọng nhất cho actionable improvements. Mỗi row là một failure case. ID — link về question nào. Agent — failure này của agent nào (A, B, hoặc Both). Error Category — phân loại gốc rễ lỗi: Schema Linking: chọn sai table hoặc column SQL Syntax: SQL không parse được Logic Error: syntax OK, chạy được, nhưng logic sai (sai JOIN condition, sai aggregation, thiếu filter) Hallucination: reference thứ không tồn tại Timeout: query quá chậm Ambiguity Handling: câu hỏi mơ hồ mà agent không hỏi lại, đoán sai Efficiency: result đúng nhưng SQL quá chậm / resource-intensive Other: không thuộc category trên Error Subcategory — chi tiết hơn. Ví dụ trong Schema Linking: "wrong table" vs "right table wrong column" vs "missing JOIN table". Trong Logic Error: "wrong aggregation function" vs "missing WHERE condition" vs "wrong JOIN type". Bạn tự define subcategories dựa trên patterns bạn thấy. Description — mô tả cụ thể lỗi gì xảy ra. Ví dụ: "Agent dùng LEFT JOIN thay vì INNER JOIN, khiến result chứa NULL rows từ merchants không có orders". Root Cause — tại sao agent mắc lỗi này. Đây là phần cần suy nghĩ sâu. Ví dụ: "Schema context không chứa thông tin về relationship cardinality giữa orders và merchants", "Business rule 'chỉ tính completed orders' không có trong prompt", "Agent không xử lý được câu hỏi có 2 ý nghĩa". Severity — mức độ nghiêm trọng: Critical: result hoàn toàn sai hoặc misleading, có thể gây quyết định sai High: result sai đáng kể nhưng user có thể nhận ra Medium: result gần đúng, thiếu một phần nhỏ Low: result đúng nhưng SQL suboptimal Reproducible? — chạy lại cùng input có ra cùng lỗi không. Yes = deterministic bug, fix được chắc chắn. Sometimes = non-deterministic (do temperature, randomness) — cần nhiều runs để confirm. No = flaky, có thể do external factors. Fix Priority — P0 đến P3: P0: fix ngay, blocking. Ví dụ: hallucination rate > 10% P1: fix trong sprint này. Ví dụ: systematic schema linking failure trên 1 table cluster P2: fix khi có bandwidth. Ví dụ: efficiency issues trên complex queries P3: nice to have. Ví dụ: formatting khác gold nhưng result đúng Suggested Fix — đề xuất cụ thể. Ví dụ: "Thêm foreign key descriptions vào schema context", "Thêm few-shot example cho window function pattern", "Thêm business rule X vào system prompt". Sheet 7: Summary_Dashboard Tổng hợp mọi thứ, tự tính hoàn toàn bằng formulas. Overall Metrics table — mỗi row là một metric, so sánh A vs B: Total Questions: tổng số questions đã eval Valid SQL Rate: % queries không bị syntax/runtime error. Nếu dưới 90% thì agent có fundamental problem Execution Accuracy (EX): % exact result match — metric số 1 Avg Partial Credit: trung bình partial credit score, cho nuanced view hơn binary EX Schema Linking Acc: trung bình schema linking, diagnostic Avg Efficiency: trung bình efficiency score Hallucination Rate: % queries hallucinate. Nên dưới 3%. Trên 5% là red flag Avg Latency: trung bình execution time Δ (B - A) — chênh lệch. Dương = B tốt hơn. Cột Winner cho biết ai win metric đó. Statistical Significance — reference McNemar result từ Head_to_Head. Nhắc bạn rằng delta có thể chỉ là noise nếu không significant. Head-to-Head Win/Loss — 4 con số từ contingency table. Cho bạn bức tranh nhanh nhất: nếu "B wins" >> "A wins" → B tốt hơn rõ ràng.

Sheet Gold_Dataset
A1: ID | B1: Question (NL) | C1: Category | D1: Difficulty | E1: Target Tables | F1: Target Columns | G1: Business Rules / Notes | H1: Gold SQL | I1: Gold Result (summary) | J1: Expected Row Count | K1: Dataset Split | L1: Created By | M1: Created Date | N1: DOMAIN
A2: Q1 | B2: Trong 30 ngay truoc giai ngan, user thuong access bao nhieu lan? Phan bo theo bucket. | C2: Subquery | D2: Moderate | E2: momovn-prod.BU_FI.BAOTU_VAYNHANH_LOAN_INFO, momovn-prod.BU_FI.BAOTU_VAYNHANH_ENTRY_POINT | F2: AGENT_ID, LOAN_ID, DISBURSED_TIME, DISBURSED_DATE, LOAN_AMOUNT, FINAL_SEGMENT_USER, EVENT_TIME | G2: Join ENTRY_POINT within 30 days before DISBURSED_TIME using TIMESTAMP_SUB. Count accesses and distinct access days per LOAN_ID. Bucket into 1/2/3/4-5/6-10/11-20/21-50/50+. | H2: WITH disbursed_feb AS (SELECT AGENT_ID, LOAN_ID, DISBURSED_TIME, LOAN_AMOUNT, FINAL_SEGMENT_USER FROM `momovn-prod.BU_FI.BAOTU_VAYNHANH_LOAN_INFO` WHERE DISBURSED_DATE BETWEEN '2026-02-01' AND '2026-02-28' AND DISBURSED_DATE IS NOT NULL), access_counts AS (SELECT d.LOAN_ID, d.AGENT_ID, d.FINAL_SEGMENT_USER, d.LOAN_AMOUNT, COUNT(*) AS access_count, COUNT(DISTINCT DATE(e.EVENT_TIME)) AS access_days FROM disbursed_feb d JOIN `momovn-prod.BU_FI.BAOTU_VAYNHANH_ENTRY_POINT` e ON d.AGENT_ID=e.AGENT_ID AND e.EVENT_TIME<d.DISBURSED_TIME AND e.EVENT_TIME>=TIMESTAMP_SUB(d.DISBURSED_TIME, INTERVAL 30 DAY) GROUP BY d.LOAN_ID, d.AGENT_ID, d.FINAL_SEGMENT_USER, d.LOAN_AMOUNT) SELECT CASE WHEN access_count=1 THEN '01_1 lan' WHEN access_count=2 THEN '02_2 lan' WHEN access_count=3 THEN '03_3 lan' WHEN access_count BETWEEN 4 AND 5 THEN '04_4-5 lan' WHEN access_count BETWEEN 6 AND 10 THEN '05_6-10 lan' WHEN access_count BETWEEN 11 AND 20 THEN '06_11-20 lan' WHEN access_count BETWEEN 21 AND 50 THEN '07_21-50 lan' ELSE '08_50+ lan' END AS access_bucket, COUNT(*) AS loans, ROUND(100.0*COUNT(*)/SUM(COUNT(*)) OVER(),1) AS pct, ROUND(AVG(access_count),1) AS avg_accesses, ROUND(AVG(access_days),1) AS avg_days, ROUND(AVG(LOAN_AMOUNT)/1e6,1) AS avg_loan_mm FROM access_counts GROUP BY access_bucket ORDER BY access_bucket | I2: 88.4% user access >=2 lan. Top bucket: 6-10 lan (19.6%), 11-20 lan (18.0%). Avg loan tang tu 15.7M (1 lan) den 19.4M (50+ lan). Chi 11.6% quyet dinh ngay lan dau. | J2: 8 | K2: eval | L2: DA-SQL Agent | M2: 2026-03-11 | N2: VAYNHANH
A3: Q2 | B3: Tính last touchpoint user giải ngân tháng 2 | C3: Window + Complex | D3: Complex | E3: momovn-prod.BU_FI.BAOTU_VAYNHANH_LOAN_INFO, momovn-prod.BU_FI.BAOTU_VAYNHANH_ENTRY_POINT | F3: AGENT_ID, LOAN_ID, DISBURSED_TIME, DISBURSED_DATE, LOAN_AMOUNT, ACCESSED_SOURCE, EVENT_TIME, ETL_DATE | G3: Giải ngân = DISBURSED_DATE IS NOT NULL (cả STATUS DISBURSED và LIQUIDATED). Last touchpoint = ENTRY_POINT row có EVENT_TIME lớn nhất trước DISBURSED_TIME, match bằng AGENT_ID. ETL_DATE >= 2026-01-01 để giới hạn scan. | H3: WITH disbursed_feb AS ( SELECT AGENT_ID, LOAN_ID, DISBURSED_TIME, DISBURSED_DATE, LENDER_ID, LOAN_AMOUNT, FINAL_SEGMENT_USER FROM `momovn-prod.BU_FI.BAOTU_VAYNHANH_LOAN_INFO` WHERE DISBURSED_DATE BETWEEN '2026-02-01' AND '2026-02-28' AND DISBURSED_DATE IS NOT NULL ), entry_ranked AS ( SELECT e.AGENT_ID, e.EVENT_TIME, e.ACCESSED_SOURCE, d.LOAN_ID, d.DISBURSED_TIME, d.LENDER_ID, d.LOAN_AMOUNT, d.FINAL_SEGMENT_USER, ROW_NUMBER() OVER (PARTITION BY d.LOAN_ID ORDER BY e.EVENT_TIME DESC) AS rn FROM disbursed_feb d JOIN `momovn-prod.BU_FI.BAOTU_VAYNHANH_ENTRY_POINT` e ON d.AGENT_ID = e.AGENT_ID AND e.EVENT_TIME < d.DISBURSED_TIME AND e.ETL_DATE >= '2026-01-01' ) SELECT ACCESSED_SOURCE, COUNT(*) AS loan_count, COUNT(DISTINCT AGENT_ID) AS unique_users, ROUND(SUM(LOAN_AMOUNT)/1e9,1) AS total_amount_bn, ROUND(AVG(LOAN_AMOUNT)/1e6,1) AS avg_loan_mm, ROUND(100.0*COUNT(*)/SUM(COUNT(*)) OVER(),1) AS pct FROM entry_ranked WHERE rn=1 GROUP BY ACCESSED_SOURCE ORDER BY loan_count DESC | I3: Top 3: tabbar_home 66.6% (79,780 loans), app_all_service_top 12.8% (15,374), financial_hub 5.8% (6,999). Top 4 sources = 90.4% total disbursements. | J3: 80 | K3: eval | L3: DA-SQL Agent | N3: VAYNHANH
A4: Q3 | B4: Tinh last touchpoint ma user giai ngan Vay Nhanh thang 2 chia theo final segment user | C4: Window + Complex | D4: Complex | E4: momovn-prod.BU_FI.BAOTU_VAYNHANH_LOAN_INFO, momovn-prod.BU_FI.BAOTU_VAYNHANH_ENTRY_POINT | F4: AGENT_ID, LOAN_ID, DISBURSED_TIME, DISBURSED_DATE, LOAN_AMOUNT, FINAL_SEGMENT_USER, ACCESSED_SOURCE, EVENT_TIME, ETL_DATE | G4: Last touchpoint = ENTRY_POINT row with max EVENT_TIME before DISBURSED_TIME, matched by AGENT_ID. Breakdown by FINAL_SEGMENT_USER (NEWLOAN, RELOAN, REPEATED, FM_MERCHANT_NEW, FM_MERCHANT_REPEATED, FM_STUDENT_NEW). ETL_DATE >= 2026-01-01 to limit scan. HAVING COUNT(*) >= 10 to filter noise. | H4: WITH disbursed_feb AS (SELECT AGENT_ID, LOAN_ID, DISBURSED_TIME, LOAN_AMOUNT, FINAL_SEGMENT_USER FROM `momovn-prod.BU_FI.BAOTU_VAYNHANH_LOAN_INFO` WHERE DISBURSED_DATE BETWEEN '2026-02-01' AND '2026-02-28' AND DISBURSED_DATE IS NOT NULL), entry_ranked AS (SELECT e.AGENT_ID, e.ACCESSED_SOURCE, d.LOAN_ID, d.LOAN_AMOUNT, d.FINAL_SEGMENT_USER, ROW_NUMBER() OVER (PARTITION BY d.LOAN_ID ORDER BY e.EVENT_TIME DESC) AS rn FROM disbursed_feb d JOIN `momovn-prod.BU_FI.BAOTU_VAYNHANH_ENTRY_POINT` e ON d.AGENT_ID = e.AGENT_ID AND e.EVENT_TIME < d.DISBURSED_TIME AND e.ETL_DATE >= '2026-01-01') SELECT FINAL_SEGMENT_USER, ACCESSED_SOURCE, COUNT(*) AS loans, COUNT(DISTINCT AGENT_ID) AS users, ROUND(SUM(LOAN_AMOUNT)/1e9,2) AS amount_bn, ROUND(AVG(LOAN_AMOUNT)/1e6,1) AS avg_mm, ROUND(100.0*COUNT(*)/SUM(COUNT(*)) OVER(PARTITION BY FINAL_SEGMENT_USER),1) AS pct_within_segment FROM entry_ranked WHERE rn=1 GROUP BY FINAL_SEGMENT_USER, ACCESSED_SOURCE HAVING COUNT(*)>=10 ORDER BY FINAL_SEGMENT_USER, loans DESC | I4: RELOAN: tabbar_home 69.7%, app_all_service 11.6%, search 5.1%. NEWLOAN: tabbar_home 61.6%, app_all_service 16.0%, financial_hub 10.6%. REPEATED: tabbar_home 64.3%, collection channels 5.9%. RELOAN depends more on Home; NEWLOAN explores via Financial Hub; Collection channels almost exclusively RELOAN+REPEATED. | J4: 80 | K4: eval | L4: DA-SQL Agent | M4: 2026-03-11 | N4: VAYNHANH
A5: Q4 | B5: So sanh so lan access va so ngay access truoc giai ngan giua NEWLOAN, RELOAN, REPEATED? | C5: JOIN | D5: Moderate | E5: momovn-prod.BU_FI.BAOTU_VAYNHANH_LOAN_INFO, momovn-prod.BU_FI.BAOTU_VAYNHANH_ENTRY_POINT | F5: AGENT_ID, LOAN_ID, DISBURSED_TIME, DISBURSED_DATE, FINAL_SEGMENT_USER, EVENT_TIME | G5: Count accesses + distinct days within 30d before disbursement per loan. Use APPROX_QUANTILES for median. Filter FINAL_SEGMENT_USER IN (NEWLOAN, RELOAN, REPEATED). | H5: WITH disbursed_feb AS (SELECT AGENT_ID, LOAN_ID, DISBURSED_TIME, FINAL_SEGMENT_USER FROM `momovn-prod.BU_FI.BAOTU_VAYNHANH_LOAN_INFO` WHERE DISBURSED_DATE BETWEEN '2026-02-01' AND '2026-02-28' AND DISBURSED_DATE IS NOT NULL AND FINAL_SEGMENT_USER IN ('NEWLOAN','RELOAN','REPEATED')), access_counts AS (SELECT d.LOAN_ID, d.FINAL_SEGMENT_USER, COUNT(*) AS access_count, COUNT(DISTINCT DATE(e.EVENT_TIME)) AS access_days FROM disbursed_feb d JOIN `momovn-prod.BU_FI.BAOTU_VAYNHANH_ENTRY_POINT` e ON d.AGENT_ID=e.AGENT_ID AND e.EVENT_TIME<d.DISBURSED_TIME AND e.EVENT_TIME>=TIMESTAMP_SUB(d.DISBURSED_TIME, INTERVAL 30 DAY) GROUP BY d.LOAN_ID, d.FINAL_SEGMENT_USER) SELECT FINAL_SEGMENT_USER, COUNT(*) AS loans, ROUND(AVG(access_count),1) AS avg_accesses, ROUND(APPROX_QUANTILES(access_count,100)[OFFSET(50)],0) AS median_accesses, ROUND(AVG(access_days),1) AS avg_distinct_days, ROUND(APPROX_QUANTILES(access_days,100)[OFFSET(50)],0) AS median_days FROM access_counts GROUP BY FINAL_SEGMENT_USER ORDER BY loans DESC | I5: RELOAN: median 10 accesses / 5 days. NEWLOAN: median 4 accesses / 2 days. REPEATED: median 9 / 4 days. New users decide fast (2 days), reloan users browse more (5 days). | J5: 3 | K5: eval | L5: DA-SQL Agent | M5: 2026-03-11 | N5: VAYNHANH
A6: Q5 | B6: Cohort liquidation theo thang: ty le reloan trong 30/60/90 ngay sau khi tat toan? | C6: Multi-step | D6: Moderate | E6: momovn-prod.BU_FI.BAOTU_VAYNHANH_LOAN_INFO | F6: AGENT_ID, LOAN_ID, LIQUIDATED_DATE, DISBURSED_DATE, LOAN_AMOUNT | G6: Liquidated = LIQUIDATED_DATE IS NOT NULL (NEVER use STATUS). Self-join: find next DISBURSED_DATE > LIQUIDATED_DATE within 90 days. ROW_NUMBER to get first reloan only. LEFT JOIN to keep non-reloans. Jan/Feb 2026 cohorts immature (not enough time for 60d/90d window). | H6: WITH liquidations AS (SELECT AGENT_ID, LOAN_ID AS liq_loan_id, LIQUIDATED_DATE, LENDER_ID AS liq_lender, LOAN_AMOUNT AS liq_amount, FORMAT_DATE('%Y-%m', LIQUIDATED_DATE) AS liq_month FROM `momovn-prod.BU_FI.BAOTU_VAYNHANH_LOAN_INFO` WHERE LIQUIDATED_DATE IS NOT NULL AND LIQUIDATED_DATE BETWEEN '2025-07-01' AND '2026-02-28'), next_loan AS (SELECT l.*, n.LOAN_ID AS reloan_id, n.DISBURSED_DATE AS reloan_date, n.LOAN_AMOUNT AS reloan_amount, DATE_DIFF(n.DISBURSED_DATE, l.LIQUIDATED_DATE, DAY) AS days_to_reloan, ROW_NUMBER() OVER (PARTITION BY l.AGENT_ID, l.liq_loan_id ORDER BY n.DISBURSED_DATE) AS rn FROM liquidations l LEFT JOIN `momovn-prod.BU_FI.BAOTU_VAYNHANH_LOAN_INFO` n ON l.AGENT_ID=n.AGENT_ID AND n.DISBURSED_DATE>l.LIQUIDATED_DATE AND n.DISBURSED_DATE<=DATE_ADD(l.LIQUIDATED_DATE, INTERVAL 90 DAY) AND n.DISBURSED_DATE IS NOT NULL) SELECT liq_month, COUNT(DISTINCT CONCAT(AGENT_ID, liq_loan_id)) AS total_liquidations, COUNTIF(rn=1 AND days_to_reloan<=30) AS reloan_30d, COUNTIF(rn=1 AND days_to_reloan<=60) AS reloan_60d, COUNTIF(rn=1 AND days_to_reloan<=90) AS reloan_90d, ROUND(100.0*COUNTIF(rn=1 AND days_to_reloan<=30)/COUNT(DISTINCT CONCAT(AGENT_ID, liq_loan_id)),1) AS rate_30d, ROUND(100.0*COUNTIF(rn=1 AND days_to_reloan<=60)/COUNT(DISTINCT CONCAT(AGENT_ID, liq_loan_id)),1) AS rate_60d, ROUND(100.0*COUNTIF(rn=1 AND days_to_reloan<=90)/COUNT(DISTINCT CONCAT(AGENT_ID, liq_loan_id)),1) AS rate_90d FROM next_loan WHERE rn=1 OR rn IS NULL GROUP BY liq_month ORDER BY liq_month | I6: Mature cohorts (Jul-Nov 2025): 90d reloan rate stable 58.7-62.1%. 30d rate peaked Oct at 47.9%. Feb 2026 immature at 39.3% (30d only). ~60% users reloan within 90 days of paying off. | J6: 8 | K6: eval | L6: DA-SQL Agent | M6: 2026-03-11 | N6: VAYNHANH
A7: Q6 | B7: Ti le duoc duyet (disburse/submit) chia theo segment, lender, credit score range, thang (Jul 2025 - Feb 2026)? | C7: Subquery | D7: Moderate | E7: momovn-prod.BU_FI.BAOTU_VAYNHANH_LOAN_INFO | F7: SUBMITTED_DATE, DISBURSED_DATE, FINAL_SEGMENT_USER, LENDER_ID, MOMO_CREDIT_SCORE | G7: Submitted = SUBMITTED_DATE IS NOT NULL. Disbursed = DISBURSED_DATE IS NOT NULL. Credit score buckets: <606, 606-665, 666-690, 691-715, 716-740, 741-765, 766+. NEVER use STATUS column. | H7: WITH base AS (SELECT FORMAT_DATE('%Y-%m', SUBMITTED_DATE) AS submit_month, FINAL_SEGMENT_USER, LENDER_ID, CASE WHEN MOMO_CREDIT_SCORE < 606 THEN '01 <606' WHEN MOMO_CREDIT_SCORE BETWEEN 606 AND 665 THEN '02 606-665' WHEN MOMO_CREDIT_SCORE BETWEEN 666 AND 690 THEN '03 666-690' WHEN MOMO_CREDIT_SCORE BETWEEN 691 AND 715 THEN '04 691-715' WHEN MOMO_CREDIT_SCORE BETWEEN 716 AND 740 THEN '05 716-740' WHEN MOMO_CREDIT_SCORE BETWEEN 741 AND 765 THEN '06 741-765' WHEN MOMO_CREDIT_SCORE >= 766 THEN '07 766+' ELSE '99 NULL' END AS score_range, CASE WHEN DISBURSED_DATE IS NOT NULL THEN 1 ELSE 0 END AS is_disbursed FROM `momovn-prod.BU_FI.BAOTU_VAYNHANH_LOAN_INFO` WHERE SUBMITTED_DATE IS NOT NULL AND SUBMITTED_DATE BETWEEN '2025-07-01' AND '2026-02-28') SELECT submit_month, FINAL_SEGMENT_USER AS segment, LENDER_ID AS lender, score_range, COUNT(*) AS submitted, SUM(is_disbursed) AS disbursed, ROUND(100.0*SUM(is_disbursed)/COUNT(*),1) AS approval_pct FROM base GROUP BY submit_month, FINAL_SEGMENT_USER, LENDER_ID, score_range ORDER BY submit_month, FINAL_SEGMENT_USER, LENDER_ID, score_range | I7: Overall 65-73% by month (peak Oct 73.1%, low Feb 65.3%). RELOAN 78.4% vs NEWLOAN 58.2%. MBV 76.1% > VIET_CREDIT 71.2% > AMBER 67% > MCREDIT 64.5%. Score <606: 38.9%, 666+: 78-84%. Approval rate declining as submit volume grows. | J7: 20 | K7: eval | L7: DA-SQL Agent | M7: 2026-03-11 | N7: VAYNHANH
A8: Q7 | B8: Tong gia tri giai ngan va gia tri trung binh moi khoan Vay Nhanh thang 2/2026? | C8: Aggregation | D8: Simple | E8: momovn-prod.BU_FI.BAOTU_VAYNHANH_LOAN_INFO | F8: DISBURSED_DATE, DISBURSED_AMOUNT | G8: DISBURSED_AMOUNT = LOAN_AMOUNT in this table. Use DISBURSED_DATE for time filter. | H8: SELECT ROUND(SUM(DISBURSED_AMOUNT)/1e9,1) AS total_bn, ROUND(AVG(DISBURSED_AMOUNT)/1e6,1) AS avg_mm FROM `momovn-prod.BU_FI.BAOTU_VAYNHANH_LOAN_INFO` WHERE DISBURSED_DATE BETWEEN '2026-02-01' AND '2026-02-28' AND DISBURSED_DATE IS NOT NULL | I8: Total 2,515.2 bn VND, avg 17.6M per loan | J8: 1 | K8: eval | L8: DA-SQL Agent | M8: 2026-03-10 | N8: VAYNHANH
A9: Q8 | B9: So sanh giai ngan Vay Nhanh thang 1 va thang 2/2026? | C9: Aggregation | D9: Simple | E9: momovn-prod.BU_FI.BAOTU_VAYNHANH_LOAN_INFO | F9: DISBURSED_DATE, AGENT_ID, DISBURSED_AMOUNT | G9: Feb has fewer days + Tet holiday. MoM comparison expected to show decline. | H9: SELECT FORMAT_DATE('%Y-%m', DISBURSED_DATE) AS month, COUNT(*) AS loans, COUNT(DISTINCT AGENT_ID) AS users, ROUND(SUM(DISBURSED_AMOUNT)/1e9,1) AS amount_bn, ROUND(AVG(DISBURSED_AMOUNT)/1e6,1) AS avg_mm FROM `momovn-prod.BU_FI.BAOTU_VAYNHANH_LOAN_INFO` WHERE DISBURSED_DATE BETWEEN '2026-01-01' AND '2026-02-28' AND DISBURSED_DATE IS NOT NULL GROUP BY month ORDER BY month | I9: Jan 171,573 loans / 3,108.4bn -> Feb 143,176 loans / 2,515.2bn (-16.5% loans, -19.1% amount) | J9: 2 | K9: eval | L9: DA-SQL Agent | M9: 2026-03-10 | N9: VAYNHANH
A10: Q9 | B10: Phan bo so lan giai ngan cua user Vay Nhanh thang 2/2026? | C10: Aggregation | D10: Simple | E10: momovn-prod.BU_FI.BAOTU_VAYNHANH_LOAN_INFO | F10: DISBURSED_COUNT_TIME, DISBURSED_AMOUNT, DISBURSED_DATE | G10: DISBURSED_COUNT_TIME = ordinal loan number per user. Higher count = more experienced borrower. | H10: SELECT CASE WHEN DISBURSED_COUNT_TIME=1 THEN '1st loan' WHEN DISBURSED_COUNT_TIME=2 THEN '2nd loan' WHEN DISBURSED_COUNT_TIME=3 THEN '3rd loan' WHEN DISBURSED_COUNT_TIME BETWEEN 4 AND 5 THEN '4-5th loan' WHEN DISBURSED_COUNT_TIME BETWEEN 6 AND 10 THEN '6-10th loan' ELSE '11+ loan' END AS loan_sequence, MIN(DISBURSED_COUNT_TIME) AS sort_key, COUNT(*) AS loans, ROUND(AVG(DISBURSED_AMOUNT)/1e6,1) AS avg_mm, ROUND(100.0*COUNT(*)/SUM(COUNT(*)) OVER(),1) AS pct FROM `momovn-prod.BU_FI.BAOTU_VAYNHANH_LOAN_INFO` WHERE DISBURSED_DATE BETWEEN '2026-02-01' AND '2026-02-28' AND DISBURSED_DATE IS NOT NULL GROUP BY loan_sequence ORDER BY sort_key | I10: 1st loan 34.5% (avg 13.5M), 2nd 21.7% (avg 17.8M), 3rd 14.3% (avg 21.3M). Avg increases with sequence. | J10: 1 | K10: eval | L10: DA-SQL Agent | M10: 2026-03-10 | N10: VAYNHANH
A11: Q10 | B11: Top 10 ly do tu choi don vay Vay Nhanh thang 2/2026? | C11: Aggregation | D11: Simple | E11: momovn-prod.BU_FI.BAOTU_VAYNHANH_LOAN_INFO | F11: REJECTED_REASON, CREATED_DATE | G11: REJECTED_REASON populated regardless of STATUS. Filter by CREATED_DATE. Top reasons: RJ_DEDUP, blacklist, bad debt. | H11: SELECT REJECTED_REASON, COUNT(*) AS cnt FROM `momovn-prod.BU_FI.BAOTU_VAYNHANH_LOAN_INFO` WHERE CREATED_DATE BETWEEN '2026-02-01' AND '2026-02-28' AND REJECTED_REASON IS NOT NULL AND REJECTED_REASON != '' GROUP BY REJECTED_REASON ORDER BY cnt DESC LIMIT 10 | I11: Top 3: RJ_DEDUP (10,135), FASTMONEY_REF_BLACKLIST (9,170), RJ_BAD_DEBT (6,893) | J11: 10 | K11: eval | L11: DA-SQL Agent | M11: 2026-03-10 | N11: VAYNHANH
A12: Q11 | B12: So luong user duy nhat giai ngan Vay Nhanh thang 2/2026 va trung binh moi user vay bao nhieu khoan? | C12: Aggregation | D12: Simple | E12: momovn-prod.BU_FI.BAOTU_VAYNHANH_LOAN_INFO | F12: AGENT_ID, DISBURSED_DATE | G12: User = AGENT_ID (not BORROWER_ID). Loans per user = total_loans / unique_users. | H12: SELECT COUNT(DISTINCT AGENT_ID) AS unique_borrowers, COUNT(*) AS total_loans, ROUND(COUNT(*)*1.0/COUNT(DISTINCT AGENT_ID),2) AS loans_per_user FROM `momovn-prod.BU_FI.BAOTU_VAYNHANH_LOAN_INFO` WHERE DISBURSED_DATE BETWEEN '2026-02-01' AND '2026-02-28' AND DISBURSED_DATE IS NOT NULL | I12: 126,248 unique users, 143,176 loans, 1.13 loans/user | J12: 1 | K12: eval | L12: DA-SQL Agent | M12: 2026-03-10 | N12: VAYNHANH
A13: Q12 | B13: Phan bo ky han (tenor) cac khoan vay Vay Nhanh thang 2/2026? | C13: Aggregation | D13: Simple | E13: momovn-prod.BU_FI.BAOTU_VAYNHANH_LOAN_INFO | F13: TENOR, DISBURSED_AMOUNT, DISBURSED_DATE | G13: Tenor in months. Short-term (1-6 months) dominates. Longer tenor = higher avg loan. | H13: SELECT CAST(TENOR AS INT64) AS tenor_months, COUNT(*) AS loans, ROUND(AVG(DISBURSED_AMOUNT)/1e6,1) AS avg_mm, ROUND(100.0*COUNT(*)/SUM(COUNT(*)) OVER(),1) AS pct FROM `momovn-prod.BU_FI.BAOTU_VAYNHANH_LOAN_INFO` WHERE DISBURSED_DATE BETWEEN '2026-02-01' AND '2026-02-28' AND DISBURSED_DATE IS NOT NULL GROUP BY tenor_months ORDER BY loans DESC | I13: 6-month tenor dominates (28.7%, avg 7.2M), then 9-month (15.5%), 12-month (13.5%). 36-month avg 62M. | J13: 1 | K13: eval | L13: DA-SQL Agent | M13: 2026-03-10 | N13: VAYNHANH
A14: Q13 | B14: Giai ngan Vay Nhanh theo ngay trong tuan thang 2/2026? | C14: Aggregation | D14: Simple | E14: momovn-prod.BU_FI.BAOTU_VAYNHANH_LOAN_INFO | F14: DISBURSED_DATE, DISBURSED_AMOUNT | G14: Use EXTRACT(DAYOFWEEK) or FORMAT_DATE('%A'). Weekend typically lower. | H14: SELECT FORMAT_DATE('%A', DISBURSED_DATE) AS day_of_week, EXTRACT(DAYOFWEEK FROM DISBURSED_DATE) AS dow_num, COUNT(*) AS loans, ROUND(SUM(DISBURSED_AMOUNT)/1e9,2) AS amount_bn, ROUND(AVG(DISBURSED_AMOUNT)/1e6,1) AS avg_mm FROM `momovn-prod.BU_FI.BAOTU_VAYNHANH_LOAN_INFO` WHERE DISBURSED_DATE BETWEEN '2026-02-01' AND '2026-02-28' AND DISBURSED_DATE IS NOT NULL GROUP BY day_of_week, dow_num ORDER BY dow_num | I14: 7 rows. Need to run to get exact numbers. | J14: 1 | K14: eval | L14: DA-SQL Agent | M14: 2026-03-10 | N14: VAYNHANH
A15: Q14 | B15: Thoi gian trung binh tu submit den giai ngan Vay Nhanh thang 2/2026 theo lender? | C15: Aggregation | D15: Moderate | E15: momovn-prod.BU_FI.BAOTU_VAYNHANH_LOAN_INFO | F15: LENDER_ID, SUBMITTED_TIME, DISBURSED_TIME, DISBURSED_DATE | G15: Use TIMESTAMP_DIFF(DISBURSED_TIME, SUBMITTED_TIME, MINUTE). SUBMITTED_TIME must not be null. | H15: SELECT LENDER_ID, COUNT(*) AS loans, ROUND(AVG(TIMESTAMP_DIFF(DISBURSED_TIME, SUBMITTED_TIME, MINUTE)),1) AS avg_minutes, ROUND(APPROX_QUANTILES(TIMESTAMP_DIFF(DISBURSED_TIME, SUBMITTED_TIME, MINUTE),100)[OFFSET(50)],1) AS median_minutes FROM `momovn-prod.BU_FI.BAOTU_VAYNHANH_LOAN_INFO` WHERE DISBURSED_DATE BETWEEN '2026-02-01' AND '2026-02-28' AND DISBURSED_DATE IS NOT NULL AND SUBMITTED_TIME IS NOT NULL GROUP BY LENDER_ID ORDER BY loans DESC | I15: VIET_CREDIT avg 2.1min (median 2), MCREDIT avg 6.3min (median 0), MBV avg 2.3min (median 1), AMBER avg 2.4min (median 2) | J15: 1 | K15: eval | L15: DA-SQL Agent | M15: 2026-03-10 | N15: VAYNHANH
A16: Q15 | B16: Tan suat truy cap theo ngay truoc giai ngan (day 0 den day -30) cua user Vay Nhanh thang 2? | C16: JOIN | D16: Moderate | E16: momovn-prod.BU_FI.BAOTU_VAYNHANH_LOAN_INFO, momovn-prod.BU_FI.BAOTU_VAYNHANH_ENTRY_POINT | F16: AGENT_ID, LOAN_ID, DISBURSED_TIME, DISBURSED_DATE, EVENT_TIME | G16: TIMESTAMP_DIFF(DISBURSED_TIME, EVENT_TIME, DAY) = days before disbursement. Day 0 = same day as disbursement. Join within 30-day window. | H16: WITH disbursed_feb AS (SELECT AGENT_ID, LOAN_ID, DISBURSED_TIME FROM `momovn-prod.BU_FI.BAOTU_VAYNHANH_LOAN_INFO` WHERE DISBURSED_DATE BETWEEN '2026-02-01' AND '2026-02-28' AND DISBURSED_DATE IS NOT NULL) SELECT TIMESTAMP_DIFF(d.DISBURSED_TIME, e.EVENT_TIME, DAY) AS days_before_disbursement, COUNT(*) AS total_accesses, COUNT(DISTINCT d.LOAN_ID) AS unique_loans FROM disbursed_feb d JOIN `momovn-prod.BU_FI.BAOTU_VAYNHANH_ENTRY_POINT` e ON d.AGENT_ID=e.AGENT_ID AND e.EVENT_TIME<d.DISBURSED_TIME AND e.EVENT_TIME>=TIMESTAMP_SUB(d.DISBURSED_TIME, INTERVAL 30 DAY) GROUP BY days_before_disbursement ORDER BY days_before_disbursement | I16: Day 0 spike: 205K accesses (49,707 loans = 43%). Day 1: 103K (-50%). Day 7-28: plateau ~40-56K accesses/day. Pattern: sharp spike day 0-1, then long flat tail. | J16: 30 | K16: eval | L16: DA-SQL Agent | M16: 2026-03-11 | N16: VAYNHANH
A17: Q16 | B17: So sanh so lan access va so ngay access truoc giai ngan giua NEWLOAN, RELOAN, REPEATED? | C17: Subquery | D17: Complex | E17: momovn-prod.BU_FI.BAOTU_VAYNHANH_LOAN_INFO, momovn-prod.BU_FI.BAOTU_VAYNHANH_ENTRY_POINT | F17: AGENT_ID, LOAN_ID, DISBURSED_TIME, DISBURSED_DATE, FINAL_SEGMENT_USER, EVENT_TIME | G17: Count accesses + distinct days within 30d before disbursement per loan. Use APPROX_QUANTILES for median. Filter FINAL_SEGMENT_USER IN (NEWLOAN, RELOAN, REPEATED). | H17: WITH disbursed_feb AS (SELECT AGENT_ID, LOAN_ID, DISBURSED_TIME, FINAL_SEGMENT_USER FROM `momovn-prod.BU_FI.BAOTU_VAYNHANH_LOAN_INFO` WHERE DISBURSED_DATE BETWEEN '2026-02-01' AND '2026-02-28' AND DISBURSED_DATE IS NOT NULL AND FINAL_SEGMENT_USER IN ('NEWLOAN','RELOAN','REPEATED')), access_counts AS (SELECT d.LOAN_ID, d.FINAL_SEGMENT_USER, COUNT(*) AS access_count, COUNT(DISTINCT DATE(e.EVENT_TIME)) AS access_days FROM disbursed_feb d JOIN `momovn-prod.BU_FI.BAOTU_VAYNHANH_ENTRY_POINT` e ON d.AGENT_ID=e.AGENT_ID AND e.EVENT_TIME<d.DISBURSED_TIME AND e.EVENT_TIME>=TIMESTAMP_SUB(d.DISBURSED_TIME, INTERVAL 30 DAY) GROUP BY d.LOAN_ID, d.FINAL_SEGMENT_USER) SELECT FINAL_SEGMENT_USER, COUNT(*) AS loans, ROUND(AVG(access_count),1) AS avg_accesses, ROUND(APPROX_QUANTILES(access_count,100)[OFFSET(50)],0) AS median_accesses, ROUND(AVG(access_days),1) AS avg_distinct_days, ROUND(APPROX_QUANTILES(access_days,100)[OFFSET(50)],0) AS median_days FROM access_counts GROUP BY FINAL_SEGMENT_USER ORDER BY loans DESC | I17: RELOAN: median 10 accesses / 5 days. NEWLOAN: median 4 accesses / 2 days. REPEATED: median 9 / 4 days. New users decide fast (2 days), reloan users browse more (5 days). | J17: 3 | K17: eval | L17: DA-SQL Agent | M17: 2026-03-11 | N17: VAYNHANH
A18: Q17 | B18: Thoi gian trung binh tu tat toan den reloan theo thang | C18: Subquery | D18: Complex | E18: momovn-prod.BU_FI.BAOTU_VAYNHANH_LOAN_INFO | F18: AGENT_ID, LOAN_ID, LIQUIDATED_DATE, DISBURSED_DATE | G18: Self-join to find first reloan after liquidation (no time cap). Use APPROX_QUANTILES for percentiles. Recent cohorts appear faster because only near-term reloans observed (right-censoring). | H18: WITH liquidations AS (SELECT AGENT_ID, LOAN_ID AS liq_loan_id, LIQUIDATED_DATE, FORMAT_DATE('%Y-%m', LIQUIDATED_DATE) AS liq_month FROM `momovn-prod.BU_FI.BAOTU_VAYNHANH_LOAN_INFO` WHERE LIQUIDATED_DATE IS NOT NULL AND LIQUIDATED_DATE BETWEEN '2025-07-01' AND '2026-02-28'), next_loan AS (SELECT l.*, n.DISBURSED_DATE AS reloan_date, DATE_DIFF(n.DISBURSED_DATE, l.LIQUIDATED_DATE, DAY) AS days_to_reloan, ROW_NUMBER() OVER (PARTITION BY l.AGENT_ID, l.liq_loan_id ORDER BY n.DISBURSED_DATE) AS rn FROM liquidations l JOIN `momovn-prod.BU_FI.BAOTU_VAYNHANH_LOAN_INFO` n ON l.AGENT_ID=n.AGENT_ID AND n.DISBURSED_DATE>l.LIQUIDATED_DATE AND n.DISBURSED_DATE IS NOT NULL) SELECT liq_month, COUNT(*) AS reloans, ROUND(AVG(days_to_reloan),1) AS avg_days, ROUND(APPROX_QUANTILES(days_to_reloan,100)[OFFSET(25)],0) AS p25_days, ROUND(APPROX_QUANTILES(days_to_reloan,100)[OFFSET(50)],0) AS median_days, ROUND(APPROX_QUANTILES(days_to_reloan,100)[OFFSET(75)],0) AS p75_days FROM next_loan WHERE rn=1 GROUP BY liq_month ORDER BY liq_month | I18: Mature cohorts: median 9-17 days to reloan. P25 = 3-4 days (instant reloans). Oct 2025 median 10d, Dec median 9d. Users pay off and reborrow within 2 weeks typically. | J18: 8 | K18: eval | L18: DA-SQL Agent | M18: 2026-03-11 | N18: VAYNHANH
A19: Q18 | B19: So sanh traffic user khong co khoan vay giua thang 3/2026 va thang 1/2026 cung ky (1-11)? | C19: Subquery | D19: Complex | E19: momovn-prod.BU_FI.BAOTU_VAYNHANH_LOAN_INFO, momovn-prod.BU_FI.BAOTU_VAYNHANH_ENTRY_POINT | F19: AGENT_ID, DISBURSED_DATE, LIQUIDATED_DATE, ETL_DATE, ACCESSED_SOURCE | G19: No-loan users = LEFT JOIN loan_info WHERE active loan IS NULL. Compare same period (1-11) for fairness. Active loan at time = disbursed before period end AND (not liquidated OR liquidated after period start). | H19: WITH active_loans_jan AS (SELECT DISTINCT AGENT_ID FROM `momovn-prod.BU_FI.BAOTU_VAYNHANH_LOAN_INFO` WHERE DISBURSED_DATE IS NOT NULL AND (LIQUIDATED_DATE IS NULL OR LIQUIDATED_DATE>='2026-01-01') AND DISBURSED_DATE<'2026-01-12'), active_loans_mar AS (SELECT DISTINCT AGENT_ID FROM `momovn-prod.BU_FI.BAOTU_VAYNHANH_LOAN_INFO` WHERE DISBURSED_DATE IS NOT NULL AND (LIQUIDATED_DATE IS NULL OR LIQUIDATED_DATE>='2026-03-01') AND DISBURSED_DATE<'2026-03-12'), jan_traffic AS (SELECT e.ACCESSED_SOURCE, COUNT(*) AS sessions, COUNT(DISTINCT e.AGENT_ID) AS users FROM `momovn-prod.BU_FI.BAOTU_VAYNHANH_ENTRY_POINT` e LEFT JOIN active_loans_jan a ON e.AGENT_ID=a.AGENT_ID WHERE e.ETL_DATE BETWEEN '2026-01-01' AND '2026-01-11' AND a.AGENT_ID IS NULL GROUP BY e.ACCESSED_SOURCE), mar_traffic AS (SELECT e.ACCESSED_SOURCE, COUNT(*) AS sessions, COUNT(DISTINCT e.AGENT_ID) AS users FROM `momovn-prod.BU_FI.BAOTU_VAYNHANH_ENTRY_POINT` e LEFT JOIN active_loans_mar a ON e.AGENT_ID=a.AGENT_ID WHERE e.ETL_DATE BETWEEN '2026-03-01' AND '2026-03-11' AND a.AGENT_ID IS NULL GROUP BY e.ACCESSED_SOURCE) SELECT COALESCE(m.ACCESSED_SOURCE,j.ACCESSED_SOURCE) AS source, IFNULL(j.users,0) AS jan_users, IFNULL(j.sessions,0) AS jan_sessions, IFNULL(m.users,0) AS mar_users, IFNULL(m.sessions,0) AS mar_sessions, IFNULL(m.users,0)-IFNULL(j.users,0) AS user_diff, ROUND(100.0*SAFE_DIVIDE(IFNULL(m.users,0)-IFNULL(j.users,0),IFNULL(j.users,0)),1) AS user_growth_pct FROM mar_traffic m FULL OUTER JOIN jan_traffic j ON m.ACCESSED_SOURCE=j.ACCESSED_SOURCE ORDER BY IFNULL(m.users,0)+IFNULL(j.users,0) DESC | I19: Mar vs Jan (1-11): 550K vs 615K users (-10.5%). Sessions 1.53M vs 1.97M (-22.4%). Sessions/user 2.8 vs 3.2. tabbar_home -56K (-16%), financial_hub -44K (-27%), momo_passport -28K (-68%). Only app_all_service_top grew +15K (+11%). | J19: 50 | K19: eval | L19: DA-SQL Agent | M19: 2026-03-11 | N19: VAYNHANH
A20: Q19 | B20: DPD30 cac khoan vay theo vintage va lender (chi dung LOAN_INFO, khong dung bang vintage)? | C20: Ambiguous | D20: Ambiguous | E20: momovn-prod.BU_FI.BAOTU_VAYNHANH_LOAN_INFO | F20: DISBURSED_DATE, LIQUIDATED_DATE, FIRST_DUE_DATE, TENOR, LENDER_ID, LOAN_AMOUNT | G20: LOAN_INFO khong co du lieu thanh toan tung ky. Chi biet loan da liquidated hay chua | J20: 1 | K20: eval | L20: DA-SQL Agent | M20: 2026-03-11 | N20: VAYNHANH
A22: TTT001 | B22: AUM tháng 1 bao nhiêu? | C22: Aggregation | D22: Simple | E22: mart_ttt_daily_user_record | F22: BALANCE, GRASS_DATE | G22: AUM = SUM(BALANCE) tại ngày cuối tháng (snapshot), KHÔNG phải SUM across all days. Nếu SUM cả tháng → inflate ~30x. Không filter MAU/MFU vì churn accounts vẫn có balance. Câu hỏi không nói rõ năm nào → LLM phải infer 2026. Không nói rõ breakdown Individual vs Money Pool → LLM có thể miss hoặc tự ý breakdown. | H22: SELECT SUM(BALANCE) AS total_aum FROM `momovn-prod.BU_FI.mart_ttt_daily_user_record` WHERE GRASS_DATE = '2026-01-31' | I22: 1 row, total_aum ~11.57T VND | J22: 1 | K22: eval | L22: DA Team (AI-assisted) | M22: 46091 | N22: TTT
A23: TTT002 | B23: Có bao nhiêu người đang dùng TTT vậy? | C23: Ambiguous | D23: Ambiguous | E23: mart_ttt_daily_user_record | F23: USER_ID, MAU_TYPE, GRASS_DATE | G23: Đang dùng = MAU hay MFU? Không nói tháng nào. Agent tốt nên hỏi lại: "Ý anh/chị là người mở app (MAU ~3.5M) hay người thực sự có tiền (MFU ~1.7M)?". USER_ID cần REGEXP_EXTRACT vì mp_ prefix gây double-count. Nếu agent tự đoán mà không clarify → penalty. | H23: -- Agent nên hỏi lại. Nếu buộc phải trả lời, MAU là default hợp lý: SELECT COUNT(DISTINCT CAST(REGEXP_EXTRACT(USER_ID, r'\d+') AS STRING)) AS total_mau FROM `momovn-prod.BU_FI.mart_ttt_daily_user_record` WHERE GRASS_DATE BETWEEN '2026-02-01' AND '2026-02-28' AND MAU_TYPE != '0.Churn' | I23: 1 row, ~3.4-3.5M (nếu MAU) hoặc ~1.67M (nếu MFU) | J23: 1 | K23: eval | L23: DA Team (AI-assisted) | M23: 46091 | N23: TTT
A24: TTT003 | B24: Tháng rồi người ta gửi vô TTT tổng bao nhiêu tiền? | C24: Aggregation | D24: Moderate | E24: mart_ttt_daily_user_record | F24: cashin_gmv, cashin_p2p_gmv, cashin_va_gmv, cashin_ai_gmv, cashin_stock_gmv, cashin_payout_gmv, cashin_mp_gmv, GRASS_DATE | G24: Tháng rồi = tháng trước (agent phải infer). Total cashin = SUM tất cả 7 sub-channels, không chỉ cashin_gmv (~50% total). COALESCE(col, 0) vì NULL. "Gửi vô" = cashin, không phải balance. LLM yếu thường chỉ dùng cashin_gmv. | H24: SELECT SUM( COALESCE(cashin_gmv, 0) + COALESCE(cashin_p2p_gmv, 0) + COALESCE(cashin_va_gmv, 0) + COALESCE(cashin_ai_gmv, 0) + COALESCE(cashin_stock_gmv, 0) + COALESCE(cashin_payout_gmv, 0) + COALESCE(cashin_mp_gmv, 0) ) AS total_cashin FROM `momovn-prod.BU_FI.mart_ttt_daily_user_record` WHERE GRASS_DATE BETWEEN '2026-02-01' AND '2026-02-28' | I24: 1 row, total cashin cả tháng | J24: 1 | K24: eval | L24: DA Team (AI-assisted) | M24: 46091 | N24: TTT
A25: TTT004 | B25: MoMo đang trả lãi cho TTT mỗi tháng bao nhiêu vậy? Có đáng lo không? | C25: Aggregation | D25: Simple | E25: mart_ttt_daily_user_record | F25: INTEREST, GRASS_DATE | G25: Column tên `INTEREST` (KHÔNG phải `interest_gmv` — column name sai phổ biến nhất). Interest = chi phí MoMo trả cho user/ngày, SUM across tháng. "Có đáng lo không" = phần business interpretation, agent không cần SQL cho phần này. LLM có thể dùng sai column name → query fail. | H25: SELECT SUM(INTEREST) AS total_interest_paid FROM `momovn-prod.BU_FI.mart_ttt_daily_user_record` WHERE GRASS_DATE BETWEEN '2026-02-01' AND '2026-02-28' | I25: 1 row, ~37-38B VND/month | J25: 1 | K25: eval | L25: DA Team (AI-assisted) | M25: 46091 | N25: TTT
A26: TTT005 | B26: Tháng 1 so với tháng 2 thì TTT đang lên hay xuống? | C26: Multi-step | D26: Ambiguous | E26: mart_ttt_daily_user_record | F26: BALANCE, USER_ID, MAU_TYPE, INTEREST, cashin sub-channels, GRASS_DATE | G26: Câu hỏi cực kỳ vague — "lên hay xuống" theo metric nào? AUM? MAU? Cashin? Agent tốt nên hỏi lại hoặc decompose thành multiple metrics. Mỗi metric có date logic khác nhau (AUM = snapshot, MAU = full range, cashin = SUM range). Nếu agent chỉ trả 1 metric → incomplete. | H26: -- Cần multiple queries. Minimum viable: AUM + MAU for 2 months WITH jan_stats AS ( SELECT SUM(CASE WHEN GRASS_DATE = '2026-01-31' THEN BALANCE ELSE 0 END) AS aum, COUNT(DISTINCT CASE WHEN MAU_TYPE != '0.Churn' THEN CAST(REGEXP_EXTRACT(USER_ID, r'\d+') AS STRING) END) AS mau FROM `momovn-prod.BU_FI.mart_ttt_daily_user_record` WHERE GRASS_DATE BETWEEN '2026-01-01' AND '2026-01-31' ), feb_stats AS ( SELECT SUM(CASE WHEN GRASS_DATE = '2026-02-28' THEN BALANCE ELSE 0 END) AS aum, COUNT(DISTINCT CASE WHEN MAU_TYPE != '0.Churn' THEN CAST(REGEXP_EXTRACT(USER_ID, r'\d+') AS STRING) END) AS mau FROM `momovn-prod.BU_FI.mart_ttt_daily_user_record` WHERE GRASS_DATE BETWEEN '2026-02-01' AND '2026-02-28' ) SELECT 'Jan' AS month, aum, mau FROM jan_stats UNION ALL SELECT 'Feb', aum, mau FROM feb_stats | I26: 2 rows: Jan vs Feb cho AUM + MAU | J26: 2 | K26: eval | L26: DA Team (AI-assisted) | M26: 46091 | N26: TTT
A27: TTT006 | B27: Vùng nào đang dùng TTT nhiều nhất? Top 5 cho t | C27: Ranking + Filter | D27: Moderate | E27: mart_ttt_daily_user_record | F27: REGION, USER_ID, MAU_TYPE, GRASS_DATE | G27: Dùng nhiều nhất = MAU count. Cần filter MAU_TYPE != '0.Churn'. REGEXP_EXTRACT cho USER_ID dedup. REGION có thể NULL → COALESCE. LIMIT 5. Không nói rõ tháng → agent phải infer tháng gần nhất. | H27: SELECT COALESCE(REGION, 'Unknown') AS region, COUNT(DISTINCT CAST(REGEXP_EXTRACT(USER_ID, r'\d+') AS STRING)) AS active_users FROM `momovn-prod.BU_FI.mart_ttt_daily_user_record` WHERE GRASS_DATE BETWEEN '2026-02-01' AND '2026-02-28' AND MAU_TYPE != '0.Churn' GROUP BY COALESCE(REGION, 'Unknown') ORDER BY active_users DESC LIMIT 5 | I27: 5 rows — top 5 regions | J27: 5 | K27: eval | L27: DA Team (AI-assisted) | M27: 46091 | N27: TTT
A28: TTT007 | B28: Tiền rút ra nhiều hơn tiền gửi vào không? Tháng 2 | C28: Multi-step | D28: Complex | E28: mart_ttt_daily_user_record | F28: Tất cả 7 cashin + 7 cashout sub-channels, GRASS_DATE | G28: Net cash = Total Cashin - Total Cashout. Phải SUM đủ 7+7 sub-channels, mỗi cái COALESCE. Câu hỏi hỏi yes/no nhưng SQL cần tính cả 2 phía. Nếu chỉ dùng cashin_gmv và cashout_gmv → miss ~50% flow, có thể sai direction. | H28: SELECT SUM( COALESCE(cashin_gmv, 0) + COALESCE(cashin_p2p_gmv, 0) + COALESCE(cashin_va_gmv, 0) + COALESCE(cashin_ai_gmv, 0) + COALESCE(cashin_stock_gmv, 0) + COALESCE(cashin_payout_gmv, 0) + COALESCE(cashin_mp_gmv, 0) ) AS total_cashin, SUM( COALESCE(cashout_gmv, 0) + COALESCE(cashout_napas_gmv, 0) + COALESCE(cashout_p2p_gmv, 0) + COALESCE(cashout_payment_gmv, 0) + COALESCE(cashout_stock_gmv, 0) + COALESCE(cashout_mp_gmv, 0) + COALESCE(cashout_payment_mp_gmv, 0) ) AS total_cashout FROM `momovn-prod.BU_FI.mart_ttt_daily_user_record` WHERE GRASS_DATE BETWEEN '2026-02-01' AND '2026-02-28' | I28: 1 row: total_cashin vs total_cashout, net cash = cashin - cashout | J28: 1 | K28: eval | L28: DA Team (AI-assisted) | M28: 46091 | N28: TTT
A29: TTT008 | B29: Nhóm tuổi nào gửi tiết kiệm TTT nhiều nhất? | C29: Aggregation | D29: Moderate | E29: mart_ttt_daily_user_record | F29: AGE_GROUP, BALANCE, GRASS_DATE | G29: Gửi tiết kiệm nhiều nhất có thể hiểu là total AUM hoặc total cashin — ambiguous nhẹ. AGE_GROUP format: '1.Below 22', '2.23-27', '3.28-35', '4.36-50', '5.Above 50'. Nên dùng AUM snapshot cuối tháng (default interpretation). ORDER BY DESC, không cần LIMIT (chỉ ~5-6 groups). | H29: SELECT AGE_GROUP, SUM(BALANCE) AS total_aum, COUNT(DISTINCT CAST(REGEXP_EXTRACT(USER_ID, r'\d+') AS STRING)) AS user_count FROM `momovn-prod.BU_FI.mart_ttt_daily_user_record` WHERE GRASS_DATE = '2026-01-31' AND BALANCE > 0 GROUP BY AGE_GROUP ORDER BY total_aum DESC | I29: ~5-6 rows, sorted by AUM desc | J29: 46148 | K29: eval | L29: DA Team (AI-assisted) | M29: 46091 | N29: TTT
A30: TTT009 | B30: Bao nhiêu % user TTT đang dùng Túi+? | C30: Conditional Logic | D30: Moderate | E30: mart_ttt_daily_user_record | F30: PLUS_TYPE, USER_ID, MAU_TYPE, GRASS_DATE | G30: Túi+ users = PLUS_TYPE NOT IN ('0.Churn', 'None') AND PLUS_TYPE IS NOT NULL. Base = MAU (MAU_TYPE != '0.Churn'). REGEXP_EXTRACT cả tử lẫn mẫu. LLM thường không biết filter logic của PLUS_TYPE — dễ include churn Túi+ hoặc 'None' value. | H30: SELECT COUNT(DISTINCT CASE WHEN PLUS_TYPE NOT IN ('0.Churn', 'None') AND PLUS_TYPE IS NOT NULL THEN CAST(REGEXP_EXTRACT(USER_ID, r'\d+') AS STRING) END) * 100.0 / NULLIF(COUNT(DISTINCT CASE WHEN MAU_TYPE != '0.Churn' THEN CAST(REGEXP_EXTRACT(USER_ID, r'\d+') AS STRING) END), 0) AS tui_plus_pct FROM `momovn-prod.BU_FI.mart_ttt_daily_user_record` WHERE GRASS_DATE BETWEEN '2026-01-01' AND '2026-01-31' | I30: 1 row, tui_plus_pct (%) | J30: 1 | K30: eval | L30: DA Team (AI-assisted) | M30: 46091 | N30: TTT
A31: TTT010 | B31: Người dùng rút tiền từ TTT chủ yếu qua kênh nào? | C31: Ranking + Filter | D31: Moderate | E31: mart_ttt_daily_user_record | F31: cashout_gmv, cashout_napas_gmv, cashout_p2p_gmv, cashout_payment_gmv, cashout_stock_gmv, cashout_mp_gmv, cashout_payment_mp_gmv, GRASS_DATE | G31: Cần breakdown 7 cashout sub-channels để so sánh. "Chủ yếu" = channel có GMV cao nhất. LLM thường chỉ biết cashout_gmv, không biết 6 kênh còn lại. Format output nên UNPIVOT hoặc liệt kê từng kênh. COALESCE. | H31: SELECT 'basic' AS channel, SUM(COALESCE(cashout_gmv, 0)) AS gmv FROM `momovn-prod.BU_FI.mart_ttt_daily_user_record` WHERE GRASS_DATE BETWEEN '2026-02-01' AND '2026-02-28' UNION ALL SELECT 'napas', SUM(COALESCE(cashout_napas_gmv, 0)) FROM `momovn-prod.BU_FI.mart_ttt_daily_user_record` WHERE GRASS_DATE BETWEEN '2026-02-01' AND '2026-02-28' UNION ALL SELECT 'p2p', SUM(COALESCE(cashout_p2p_gmv, 0)) FROM `momovn-prod.BU_FI.mart_ttt_daily_user_record` WHERE GRASS_DATE BETWEEN '2026-02-01' AND '2026-02-28' UNION ALL SELECT 'payment', SUM(COALESCE(cashout_payment_gmv, 0)) FROM `momovn-prod.BU_FI.mart_ttt_daily_user_record` WHERE GRASS_DATE BETWEEN '2026-02-01' AND '2026-02-28' UNION ALL SELECT 'stock', SUM(COALESCE(cashout_stock_gmv, 0)) FROM `momovn-prod.BU_FI.mart_ttt_daily_user_record` WHERE GRASS_DATE BETWEEN '2026-02-01' AND '2026-02-28' UNION ALL SELECT 'money_pool', SUM(COALESCE(cashout_mp_gmv, 0)) FROM `momovn-prod.BU_FI.mart_ttt_daily_user_record` WHERE GRASS_DATE BETWEEN '2026-02-01' AND '2026-02-28' UNION ALL SELECT 'payment_mp', SUM(COALESCE(cashout_payment_mp_gmv, 0)) FROM `momovn-prod.BU_FI.mart_ttt_daily_user_record` WHERE GRASS_DATE BETWEEN '2026-02-01' AND '2026-02-28' ORDER BY gmv DESC | I31: 7 rows, sorted by GMV desc — top channel likely p2p or payment | J31: 7 | K31: eval | L31: DA Team (AI-assisted) | M31: 46091 | N31: TTT
A32: TTT011 | B32: User mới tháng này so tháng trước tăng hay giảm? Giảm bao nhiêu? | C32: Date/Time | D32: Moderate | E32: mart_ttt_daily_user_record | F32: USER_ID, MAU_TYPE, GRASS_DATE | G32: User mới = MAU_TYPE = '1.New' (KHÔNG phải != '0.Churn'). "Tháng này" vs "tháng trước" → agent phải infer relative dates. Cần REGEXP_EXTRACT. Dùng DATE_TRUNC(GRASS_DATE, MONTH) — KHÔNG dùng GRASS_MONTH (không tồn tại). LLM hay nhầm MAU_TYPE != '0.Churn' (= tất cả active, gồm retain + reactive) vs = '1.New' (chỉ new). | H32: WITH monthly_new AS ( SELECT DATE_TRUNC(GRASS_DATE, MONTH) AS month, COUNT(DISTINCT CAST(REGEXP_EXTRACT(USER_ID, r'\d+') AS STRING)) AS new_users FROM `momovn-prod.BU_FI.mart_ttt_daily_user_record` WHERE GRASS_DATE BETWEEN '2026-01-01' AND '2026-02-28' AND MAU_TYPE = '1.New' GROUP BY DATE_TRUNC(GRASS_DATE, MONTH) ) SELECT *, LAG(new_users) OVER (ORDER BY month) AS prev_month, new_users - LAG(new_users) OVER (ORDER BY month) AS diff FROM monthly_new | I32: 2 rows: Jan + Feb new user counts with diff | J32: 2 | K32: eval | L32: DA Team (AI-assisted) | M32: 46091 | N32: TTT
A33: TTT012 | B33: Góp chung (Money Pool) đang chiếm bao nhiêu % tổng AUM? | C33: Aggregation | D33: Simple | E33: mart_ttt_daily_user_record | F33: IS_MP, BALANCE, GRASS_DATE | G33: IS_MP = 'Money Pool' vs 'Individual'. AUM = snapshot cuối tháng. % = Money Pool AUM / Total AUM * 100. LLM có thể không biết column IS_MP tồn tại hoặc dùng sai filter. Nếu SUM across month → sai 30x nhưng tỷ lệ % có thể vẫn gần đúng (trap tinh vi). | H33: SELECT IS_MP, SUM(BALANCE) AS aum, SUM(BALANCE) * 100.0 / SUM(SUM(BALANCE)) OVER () AS pct FROM `momovn-prod.BU_FI.mart_ttt_daily_user_record` WHERE GRASS_DATE = '2026-01-31' GROUP BY IS_MP | I33: 2 rows: Individual ~86%, Money Pool ~14% | J33: 2 | K33: eval | L33: DA Team (AI-assisted) | M33: 46091 | N33: TTT
... A40: TTT019 | B40: Trong tháng 1, ngày nào có nhiều người rút tiền nhất? Rút bao nhiêu? | C40: Ranking + Filter | D40: Moderate | E40: mart_ttt_daily_user_record | F40: GRASS_DATE, USER_ID, cashout sub-channels | G40: Nhiều người rút = COUNT DISTINCT users có cashout > 0 (bất kỳ sub-channel nào). "Rút bao nhiêu" = total cashout GMV ngày đó (SUM tất cả 7 sub-channels). Cần cả 2 metrics: user count + GMV. Chỉ count users có ít nhất 1 cashout sub-channel > 0. REGEXP_EXTRACT. LLM thường chỉ trả GMV hoặc chỉ trả user count, không cả 2. | H40: SELECT GRASS_DATE, COUNT(DISTINCT CAST(REGEXP_EXTRACT(USER_ID, r'\d+') AS STRING)) AS users_withdrawing, SUM( COALESCE(cashout_gmv, 0) + COALESCE(cashout_napas_gmv, 0) + COALESCE(cashout_p2p_gmv, 0) + COALESCE(cashout_payment_gmv, 0) + COALESCE(cashout_stock_gmv, 0) + COALESCE(cashout_mp_gmv, 0) + COALESCE(cashout_payment_mp_gmv, 0) ) AS total_cashout FROM `momovn-prod.BU_FI.mart_ttt_daily_user_record` WHERE GRASS_DATE BETWEEN '2026-01-01' AND '2026-01-31' AND ( COALESCE(cashout_gmv, 0) + COALESCE(cashout_napas_gmv, 0) + COALESCE(cashout_p2p_gmv, 0) + COALESCE(cashout_payment_gmv, 0) + COALESCE(cashout_stock_gmv, 0) + COALESCE(cashout_mp_gmv, 0) + COALESCE(cashout_payment_mp_gmv, 0) ) > 0 GROUP BY GRASS_DATE ORDER BY users_withdrawing DESC LIMIT 1 | I40: 1 row: ngày peak + user count + total cashout GMV | J40: 1 | K40: eval | L40: DA Team (AI-assisted) | M40: 46091 | N40: TTT
A41: TTT020 | B41: TTT tháng vừa rồi ổn không? Brief cho t ngắn gọn | C41: Ambiguous | D41: Ambiguous | E41: mart_ttt_daily_user_record | F41: Potentially ALL | G41: Câu hỏi executive-style cực kỳ vague. "Tháng vừa rồi" = tháng nào? "Ổn không" = theo tiêu chí gì? Agent tốt nên: (1) clarify hoặc (2) decompose thành ≥3 metrics: MAU trend, AUM, net cash flow, churn. Nếu chỉ trả 1 metric → incomplete. Nếu tháng 3/2026 → net cash -416B là critical insight. Agent đúng khi hỏi ngược: "Anh muốn t nhìn vào chỉ số nào? MAU, AUM, hay dòng tiền?". | H41: -- Không có single Gold SQL -- Agent tốt: hỏi lại HOẶC chạy ≥3 queries: -- 1. MAU (with REGEXP_EXTRACT + MAU_TYPE filter) -- 2. AUM (end-of-month snapshot) -- 3. Net cash flow (full cashin - cashout sub-channels) -- 4. Churn rate (optional) | I41: Multi-query needed. Key: nếu Feb thì relatively stable; nếu Mar thì net cash -416B red flag | J41: N/A | K41: eval | L41: DA Team (AI-assisted) | M41: 46091 | N41: TTT
A42: TTT021 | B42: user ttt giu tien bao lau truoc khi rut ra het? | C42: Window + Complex | D42: Complex | E42: mart_ttt_daily_user_record | F42: USER_ID, BALANCE, MFU_TYPE, GRASS_DATE | G42: Câu hỏi hành vi duration — cần tính khoảng cách ngày từ lúc user bắt đầu có balance > 0 đến khi balance = 0. Table là daily snapshot nên phải self-join hoặc window function để tìm "first funded date" vs "last funded date" per user. Rất phức tạp: cần xác định "episode" nạp-rút, không phải chỉ min/max date. LLM sẽ gần như chắc chắn oversimplify hoặc viết sai logic. Có thể cần approximate bằng cách tính avg số ngày MFU_TYPE != '0.Churn' liên tiếp. | H42: -- Approximate: avg number of consecutive funded days per user WITH funded_days AS ( SELECT CAST(REGEXP_EXTRACT(USER_ID, r'\d+') AS STRING) AS uid, GRASS_DATE, MFU_TYPE, LAG(GRASS_DATE) OVER (PARTITION BY CAST(REGEXP_EXTRACT(USER_ID, r'\d+') AS STRING) ORDER BY GRASS_DATE) AS prev_date FROM `momovn-prod.BU_FI.mart_ttt_daily_user_record` WHERE GRASS_DATE BETWEEN '2026-01-01' AND '2026-01-31' AND MFU_TYPE != '0.Churn' ), with_gaps AS ( SELECT uid, GRASS_DATE, CASE WHEN DATE_DIFF(GRASS_DATE, prev_date, DAY) > 1 OR prev_date IS NULL THEN 1 ELSE 0 END AS new_episode FROM funded_days ), episodes AS ( SELECT uid, GRASS_DATE, SUM(new_episode) OVER (PARTITION BY uid ORDER BY GRASS_DATE) AS episode_id FROM with_gaps ), episode_length AS ( SELECT uid, episode_id, DATE_DIFF(MAX(GRASS_DATE), MIN(GRASS_DATE), DAY) + 1 AS days_held FROM episodes GROUP BY uid, episode_id ) SELECT AVG(days_held) AS avg_days_before_withdraw, APPROX_QUANTILES(days_held, 100)[OFFSET(50)] AS median_days FROM episode_length | I42: 1 row: avg + median days users hold money before withdrawing | J42: 1 | K42: eval | L42: DA Team (AI-assisted) | M42: 46091 | N42: TTT
A43: TTT022 | B43: tai sao aum giam thang nay? | C43: Ambiguous | D43: Ambiguous | E43: mart_ttt_daily_user_record | F43: BALANCE, GRASS_DATE, cashin/cashout sub-channels, MAU_TYPE, MFU_TYPE | G43: Câu hỏi causal ("tại sao") — SQL không trả lời được "tại sao", chỉ trả lời "cái gì xảy ra". Agent tốt nên: (1) Xác nhận AUM giảm thật không (snapshot cuối tháng so sánh), (2) Decompose các yếu tố: net cash flow giảm? user churn tăng? cashin giảm? cashout tăng? (3) Trả lời bằng data rồi interpret. "Tháng này" không rõ tháng nào. LLM sẽ fail nếu chỉ gen 1 query đơn giản. | H43: -- Cần multi-query decomposition. Minimum: -- 1. AUM comparison (2 tháng gần nhất, end-of-month snapshot) -- 2. Net cash flow breakdown (cashin vs cashout, all sub-channels) -- 3. MFU churn (người rút hết tiền) -- Không có single SQL answer cho "tại sao" | I43: Multi-query. Agent tốt nhất nên hỏi lại "tháng nào?" rồi decompose | J43: N/A | K43: eval | L43: DA Team (AI-assisted) | M43: 46091 | N43: TTT
A44: TTT023 | B44: moi thang co bao nhieu nguoi nap VA tren 10 giao dich 1 ngay? | C44: Aggregation | D44: Complex | E44: mart_ttt_daily_user_record | F44: USER_ID, CASHIN_VA_TRANS, GRASS_DATE | G44: Nạp VA = Virtual Account cashin. "Trên 10 giao dịch 1 ngày" = CASHIN_VA_TRANS > 10 per row (vì mỗi row = 1 user/1 ngày). Cần GROUP BY tháng, COUNT DISTINCT user có ít nhất 1 ngày CASHIN_VA_TRANS > 10. REGEXP_EXTRACT cho dedup. Câu hỏi cụ thể nhưng dùng column TRANS (không phải GMV) — LLM thường chỉ biết GMV columns. "Mỗi tháng" = cần multi-month, không nói range → agent phải infer. | H44: SELECT DATE_TRUNC(GRASS_DATE, MONTH) AS month, COUNT(DISTINCT CAST(REGEXP_EXTRACT(USER_ID, r'\d+') AS STRING)) AS users_over_10_va_trans FROM `momovn-prod.BU_FI.mart_ttt_daily_user_record` WHERE GRASS_DATE BETWEEN '2025-10-01' AND '2026-02-28' AND CASHIN_VA_TRANS > 10 GROUP BY DATE_TRUNC(GRASS_DATE, MONTH) ORDER BY month | I44: ~5 rows (1 per month), count users with >10 VA transactions in a single day | J44: 5 | K44: eval | L44: DA Team (AI-assisted) | M44: 46091 | N44: TTT
A45: TTT024 | B45: hanh vi nap rut cua tui cong khac gi so voi tui ca nhan 30 ngay qua? | C45: Multi-step | D45: Complex | E45: mart_ttt_daily_user_record | F45: IS_MP, tất cả cashin + cashout sub-channels + TRANS columns, GRASS_DATE | G45: Túi cộng = Money Pool (IS_MP = 'Money Pool'). "Túi cá nhân" = Individual. "30 ngày qua" = relative date. "Hành vi nạp rút" = cần cả GMV lẫn transaction count, breakdown by channel. Cần GROUP BY IS_MP với tất cả sub-channels. LLM sẽ: (1) không biết IS_MP column, (2) thiếu sub-channels, (3) chỉ lấy GMV không lấy TRANS. | H45: SELECT IS_MP, SUM(COALESCE(cashin_gmv,0)+COALESCE(cashin_p2p_gmv,0)+COALESCE(cashin_va_gmv,0)+COALESCE(cashin_ai_gmv,0)+COALESCE(cashin_stock_gmv,0)+COALESCE(cashin_payout_gmv,0)+COALESCE(cashin_mp_gmv,0)) AS total_cashin_gmv, SUM(COALESCE(CASHIN_TRANS,0)+COALESCE(CASHIN_P2P_TRANS,0)+COALESCE(CASHIN_VA_TRANS,0)+COALESCE(CASHIN_AI_TRANS,0)+COALESCE(CASHIN_STOCK_TRANS,0)+COALESCE(CASHIN_PAYOUT_TRANS,0)+COALESCE(CASHIN_MP_TRANS,0)) AS total_cashin_trans, SUM(COALESCE(cashout_gmv,0)+COALESCE(cashout_napas_gmv,0)+COALESCE(cashout_p2p_gmv,0)+COALESCE(cashout_payment_gmv,0)+COALESCE(cashout_stock_gmv,0)+COALESCE(cashout_mp_gmv,0)+COALESCE(cashout_payment_mp_gmv,0)) AS total_cashout_gmv, SUM(COALESCE(CASHOUT_TRANS,0)+COALESCE(CASHOUT_NAPAS_TRANS,0)+COALESCE(CASHOUT_P2P_TRANS,0)+COALESCE(CASHOUT_PAYMENT_TRANS,0)+COALESCE(CASHOUT_STOCK_TRANS,0)+COALESCE(CASHOUT_MP_TRANS,0)+COALESCE(CASHOUT_PAYMENT_MP_TRANS,0)) AS total_cashout_trans FROM `momovn-prod.BU_FI.mart_ttt_daily_user_record` WHERE GRASS_DATE >= DATE_SUB(CURRENT_DATE(), INTERVAL 30 DAY) GROUP BY IS_MP | I45: 2 rows (Individual, Money Pool): cashin/cashout GMV + trans counts | J45: 2 | K45: eval | L45: DA Team (AI-assisted) | M45: 46091 | N45: TTT
A46: TTT025 | B46: nguoi dung mua tui cong thi sau do lam gi? | C46: Ambiguous | D46: Ambiguous | E46: fact_ttt_event_tracking, mart_ttt_daily_user_record | F46: event_name, screen_name, USER_ID, IS_MP, GRASS_DATE | G46: Câu hỏi journey/funnel — "mua túi cộng" = kích hoạt Money Pool, "sau đó làm gì" = cần xem event sequence sau activation. Cần JOIN event tracking table với mart table. Không rõ timeframe. Agent tốt nên hỏi lại: "Anh muốn xem hành vi trong bao lâu sau khi kích hoạt? Và đo bằng metric nào — screen views, transactions, hay balance?". LLM gần chắc không biết cách map "mua túi cộng" → event nào. | H46: -- Cần event tracking data -- Agent nên hỏi lại clarify -- Approximate: xem cashin/cashout pattern của Money Pool users SELECT DATE_TRUNC(GRASS_DATE, MONTH) AS month, COUNT(DISTINCT CAST(REGEXP_EXTRACT(USER_ID, r'\d+') AS STRING)) AS mp_users, SUM(COALESCE(cashin_mp_gmv, 0)) AS mp_cashin, SUM(COALESCE(cashout_mp_gmv, 0)) AS mp_cashout, SUM(COALESCE(cashout_payment_mp_gmv, 0)) AS mp_payment FROM `momovn-prod.BU_FI.mart_ttt_daily_user_record` WHERE IS_MP = 'Money Pool' AND MAU_TYPE = '1.New' AND GRASS_DATE BETWEEN '2025-10-01' AND '2026-02-28' GROUP BY DATE_TRUNC(GRASS_DATE, MONTH) ORDER BY month | I46: Agent nên clarify. Nếu ép trả lời: ~5 rows monthly behavior of new MP users | J46: ~5 | K46: eval | L46: DA Team (AI-assisted) | M46: 46091 | N46: TTT
A47: TTT026 | B47: so du trung binh cua user ttt la bao nhieu? | C47: Aggregation | D47: Simple | E47: mart_ttt_daily_user_record | F47: BALANCE, AVG_BALANCE, USER_ID, GRASS_DATE | G47: Bẫy column: table có cả `BALANCE` (snapshot cuối ngày) và `AVG_BALANCE` (rolling 30-day avg). "Số dư trung bình" có thể hiểu là: (1) AVG(BALANCE) tại 1 ngày = trung bình trên tất cả users, (2) dùng column AVG_BALANCE = rolling avg per user. Cần clarify. Nếu dùng BALANCE, phải chọn 1 ngày (snapshot). Nên filter chỉ funded users (MFU_TYPE != '0.Churn') để avg không bị kéo xuống bởi hàng triệu users balance = 0. Không nói tháng nào. | H47: SELECT AVG(BALANCE) AS avg_balance_per_funded_user, SUM(BALANCE) AS total_aum, COUNT(DISTINCT CAST(REGEXP_EXTRACT(USER_ID, r'\d+') AS STRING)) AS funded_users FROM `momovn-prod.BU_FI.mart_ttt_daily_user_record` WHERE GRASS_DATE = '2026-02-28' AND MFU_TYPE != '0.Churn' | I47: 1 row: avg ~6-7M VND per funded user | J47: 1 | K47: eval | L47: DA Team (AI-assisted) | M47: 46091 | N47: TTT
A48: TTT027 | B48: tui+ dang co bao nhieu nguoi? tang hay giam so thang truoc? | C48: Date/Time | D48: Moderate | E48: mart_ttt_daily_user_record | F48: PLUS_TYPE, USER_ID, GRASS_DATE | G48: Túi+ users = PLUS_TYPE NOT IN ('0.Churn', 'None') AND IS NOT NULL. Cần 2 tháng để compare. REGEXP_EXTRACT. "Tháng trước" = relative. LLM trap: (1) filter PLUS_TYPE sai, (2) thiếu dedup, (3) không biết phải so tháng hiện tại và tháng trước . (4) không biết phải so cùng kì tính theo ngày grass date nếu tháng hiện tại chưa full | I48: 2 rows (Feb, March): Túi+ user counts tính theo đúng số lượng ngày | J48: 2 | K48: eval | L48: DA Team (AI-assisted) | M48: 46091 | N48: TTT
A49: TTT028 | B49: user nao dang giu nhieu tien nhat trong ttt? top 10 | C49: Ranking + Filter | D49: Simple | E49: mart_ttt_daily_user_record | F49: USER_ID, BALANCE, GRASS_DATE | G49: Top 10 users by BALANCE tại ngày gần nhất (snapshot). Cần ORDER BY BALANCE DESC LIMIT 10. Không cần REGEXP_EXTRACT ở đây vì muốn xem account-level. Nhưng nên dùng end-of-month snapshot. Câu đơn giản nhưng LLM có thể: (1) SUM across days, (2) không chọn đúng date. | H49: SELECT USER_ID, IS_MP, BALANCE FROM `momovn-prod.BU_FI.mart_ttt_daily_user_record` WHERE GRASS_DATE = '2026-02-28' ORDER BY BALANCE DESC LIMIT 10 | I49: 10 rows: top 10 users by balance | J49: 10 | K49: eval | L49: DA Team (AI-assisted) | M49: 46091 | N49: TTT
A50: TTT029 | B50: tai sao thang nay user nap nhieu tien hon binh thuong? | C50: Ambiguous | D50: Ambiguous | E50: mart_ttt_daily_user_record | F50: cashin sub-channels, GRASS_DATE, CASHIN_VA_TRANS, AGE_GROUP, REGION | G50: Causal question lần nữa. "Nạp nhiều hơn bình thường" = trước tiên phải xác nhận cashin thực sự tăng (so vs baseline). Sau đó decompose: kênh nào tăng? nhóm user nào nạp nhiều hơn? region nào? Agent không thể trả lời "tại sao" chỉ bằng SQL — chỉ có thể show "cái gì thay đổi". "Tháng này" = không rõ. LLM sẽ fail nếu gen 1 query. | H50: -- Multi-query decomposition needed: -- 1. Confirm: tổng cashin tháng này vs avg 3 tháng trước -- 2. Breakdown by channel: kênh nào spike -- 3. Breakdown by segment: AGE_GROUP, REGION, BAL_GROUP -- Example query 1: cashin trend WITH monthly AS ( SELECT DATE_TRUNC(GRASS_DATE, MONTH) AS month, SUM(COALESCE(cashin_gmv,0)+COALESCE(cashin_p2p_gmv,0)+COALESCE(cashin_va_gmv,0)+COALESCE(cashin_ai_gmv,0)+COALESCE(cashin_stock_gmv,0)+COALESCE(cashin_payout_gmv,0)+COALESCE(cashin_mp_gmv,0)) AS total_cashin FROM `momovn-prod.BU_FI.mart_ttt_daily_user_record` WHERE GRASS_DATE BETWEEN '2025-11-01' AND '2026-02-28' GROUP BY DATE_TRUNC(GRASS_DATE, MONTH) ) SELECT *, LAG(total_cashin) OVER (ORDER BY month) AS prev_month, ROUND((total_cashin - LAG(total_cashin) OVER (ORDER BY month)) / NULLIF(LAG(total_cashin) OVER (ORDER BY month), 0) * 100, 2) AS mom_change_pct FROM monthly ORDER BY month | I50: ~4 rows monthly cashin trend. Agent nên follow up với channel/segment breakdown | J50: 4 | K50: eval | L50: DA Team (AI-assisted) | M50: 46091 | N50: TTT
A51: TTT030 | B51: user tui+ rut tien ve ngan hang (napas) thang roi bao nhieu? co tang khong? | C51: Conditional Logic | D51: Moderate | E51: mart_ttt_daily_user_record | F51: PLUS_TYPE, IS_CASHOUT_NAPAS, CASHOUT_NAPAS_GMV, CASHOUT_NAPAS_TRANS, GRASS_DATE, USER_ID | G51: Túi+ filter: PLUS_TYPE NOT IN ('0.Churn', 'None'). Napas = cashout_napas_gmv. "Có tăng không" = cần so 2 tháng. Có thể dùng IS_CASHOUT_NAPAS = 'Cashout' hoặc trực tiếp filter cashout_napas_gmv > 0. REGEXP_EXTRACT. LLM trap: (1) không biết PLUS_TYPE filter, (2) không biết IS_CASHOUT_NAPAS tag. | H51: SELECT DATE_TRUNC(GRASS_DATE, MONTH) AS month, COUNT(DISTINCT CAST(REGEXP_EXTRACT(USER_ID, r'\d+') AS STRING)) AS napas_users, SUM(COALESCE(CASHOUT_NAPAS_GMV, 0)) AS napas_gmv, SUM(COALESCE(CASHOUT_NAPAS_TRANS, 0)) AS napas_trans FROM `momovn-prod.BU_FI.mart_ttt_daily_user_record` WHERE GRASS_DATE BETWEEN '2026-01-01' AND '2026-02-28' AND PLUS_TYPE NOT IN ('0.Churn', 'None') AND PLUS_TYPE IS NOT NULL GROUP BY DATE_TRUNC(GRASS_DATE, MONTH) ORDER BY month | I51: 2 rows (Jan, Feb): napas users + GMV + trans for Túi+ users | J51: 2 | K51: eval | L51: DA Team (AI-assisted) | M51: 46091 | N51: TTT
A52: TTT031 | B52: tinh hinh kinh doanh ttt 6 thang qua | C52: Ambiguous | D52: Moderate | E52: mart_ttt_daily_user_record | F52: Potentially ALL key metrics | G52: Cực kỳ vague — giống Q020 nhưng timeframe dài hơn. "Tình hình kinh doanh" = executive dashboard gồm: MAU, MFU, AUM, cashin, cashout, net cash, churn, new users, interest cost. Mỗi metric cần date logic khác nhau. 6 tháng = Sep 2025 – Feb 2026. Agent đúng nếu hỏi lại "anh muốn focus vào metric nào?" hoặc tự decompose ≥4 metrics. | H52: -- Minimum viable: monthly trend cho 4 core metrics -- AUM (snapshot) + MAU (range) + cashin + cashout per month -- Mỗi metric cần query riêng do date logic khác nhau -- Ví dụ cho MAU trend: SELECT DATE_TRUNC(GRASS_DATE, MONTH) AS month, COUNT(DISTINCT CAST(REGEXP_EXTRACT(USER_ID, r'\d+') AS STRING)) AS mau FROM `momovn-prod.BU_FI.mart_ttt_daily_user_record` WHERE GRASS_DATE BETWEEN '2025-09-01' AND '2026-02-28' AND MAU_TYPE != '0.Churn' GROUP BY DATE_TRUNC(GRASS_DATE, MONTH) ORDER BY month | I52: Multi-query, 6 rows per metric | J52: N/A | K52: eval | L52: DA Team (AI-assisted) | M52: 46091 | N52: TTT
A53: TTT032 | B53: nhom so du nao dong gop nhieu nhat vao tong AUM? | C53: Aggregation | D53: Moderate | E53: mart_ttt_daily_user_record | F53: BAL_GROUP, BALANCE, GRASS_DATE | G53: BAL_GROUP = balance tier ([0]Churn, [1](0-300k], [2](300k-3TR], [3](3TR-30TR], [4](30TR-50TR], [5](50TR-100TR], [6](100TR-inf]). GROUP BY BAL_GROUP, SUM(BALANCE) at end-of-month. ORDER BY DESC. LLM có thể: (1) không biết BAL_GROUP column tồn tại → cố tạo CASE WHEN tự phân nhóm, (2) SUM across all days. | H53: SELECT BAL_GROUP, SUM(BALANCE) AS total_aum, COUNT(DISTINCT CAST(REGEXP_EXTRACT(USER_ID, r'\d+') AS STRING)) AS user_count, ROUND(SUM(BALANCE) * 100.0 / SUM(SUM(BALANCE)) OVER (), 2) AS pct_of_total FROM `momovn-prod.BU_FI.mart_ttt_daily_user_record` WHERE GRASS_DATE = '2026-01-31' GROUP BY BAL_GROUP ORDER BY total_aum DESC | I53: ~7 rows (1 per BAL_GROUP), top tier likely [6](100TR-inf] | J53: 7 | K53: eval | L53: DA Team (AI-assisted) | M53: 46091 | N53: TTT
A54: TTT033 | B54: user tui+ duoc cashback bao nhieu roi? co dang khong? | C54: Aggregation | D54: Moderate | E54: mart_ttt_daily_user_record | F54: TOTAL_CASHBACK_GMV, TOTAL_CASHBACK_TRANS, IS_CASHBACK, PLUS_TYPE, GRASS_DATE, USER_ID | G54: Cashback = quyền lợi Túi+ hoàn 0.1% khi thanh toán bằng TTT. Column: TOTAL_CASHBACK_GMV, TOTAL_CASHBACK_TRANS. Filter: IS_CASHBACK = 'Cashback' hoặc TOTAL_CASHBACK_GMV > 0. "Có đáng không" = cần tính tổng cashback vs tổng cashout_payment (chi phí cashback / revenue from payment). LLM gần chắc không biết columns TOTAL_CASHBACK_GMV và IS_CASHBACK tồn tại. | H54: SELECT DATE_TRUNC(GRASS_DATE, MONTH) AS month, COUNT(DISTINCT CAST(REGEXP_EXTRACT(USER_ID, r'\d+') AS STRING)) AS cashback_users, SUM(COALESCE(TOTAL_CASHBACK_GMV, 0)) AS total_cashback, SUM(COALESCE(CASHOUT_PAYMENT_GMV, 0)) AS total_payment_gmv, ROUND(SUM(COALESCE(TOTAL_CASHBACK_GMV, 0)) * 100.0 / NULLIF(SUM(COALESCE(CASHOUT_PAYMENT_GMV, 0)), 0), 4) AS cashback_rate_pct FROM `momovn-prod.BU_FI.mart_ttt_daily_user_record` WHERE GRASS_DATE BETWEEN '2026-01-01' AND '2026-02-28' AND PLUS_TYPE NOT IN ('0.Churn', 'None') AND PLUS_TYPE IS NOT NULL GROUP BY DATE_TRUNC(GRASS_DATE, MONTH) ORDER BY month | I54: 2 rows: monthly cashback total + rate vs payment GMV | J54: 2 | K54: eval | L54: DA Team (AI-assisted) | M54: 46091 | N54: TTT
A55: TTT034 | B55: user nap tu dong (auto invest) co bao nhieu nguoi? nap trung binh bao nhieu? | C55: Aggregation | D55: Simple | E55: mart_ttt_daily_user_record | F55: CASHIN_AI_TRANS, CASHIN_AI_GMV, USER_ID, GRASS_DATE | G55: Nạp tự động = Auto Invest = cashin_ai columns. Filter: CASHIN_AI_TRANS > 0 hoặc CASHIN_AI_GMV > 0. Avg = tổng GMV / số unique users. REGEXP_EXTRACT. Không nói tháng nào. LLM trap: (1) không biết cashin_ai_gmv/trans columns, (2) nhầm với cashin_gmv. | H55: SELECT COUNT(DISTINCT CAST(REGEXP_EXTRACT(USER_ID, r'\d+') AS STRING)) AS ai_users, SUM(COALESCE(CASHIN_AI_GMV, 0)) AS total_ai_cashin, ROUND(SUM(COALESCE(CASHIN_AI_GMV, 0)) / NULLIF(COUNT(DISTINCT CAST(REGEXP_EXTRACT(USER_ID, r'\d+') AS STRING)), 0), 0) AS avg_ai_cashin_per_user FROM `momovn-prod.BU_FI.mart_ttt_daily_user_record` WHERE GRASS_DATE BETWEEN '2026-02-01' AND '2026-02-28' AND CASHIN_AI_TRANS > 0 | I55: 1 row: AI users count + total + avg per user | J55: 1 | K55: eval | L55: DA Team (AI-assisted) | M55: 46091 | N55: TTT
A56: TTT035 | B56: user co so du tren 50 trieu chiem bao nhieu % tong? ho la ai? | C56: Conditional Logic | D56: Moderate | E56: mart_ttt_daily_user_record | F56: BALANCE, BAL_GROUP, USER_ID, GRASS_DATE, AGE_GROUP, GENDER, REGION | G56: >50 triệu = BALANCE > 50000000 hoặc BAL_GROUP IN ('[5](50TR-100TR]', '[6](100TR-inf]'). "Chiếm bao nhiêu %" = % of total AUM hoặc % of total users (ambiguous). "Họ là ai" = demographic breakdown (age, gender, region). Cần snapshot cuối tháng. LLM có thể: (1) dùng sai threshold, (2) không biết BAL_GROUP, (3) chỉ trả % mà không trả demographics. | H56: WITH all_users AS ( SELECT SUM(BALANCE) AS total_aum, COUNT(DISTINCT CAST(REGEXP_EXTRACT(USER_ID, r'\d+') AS STRING)) AS total_users FROM `momovn-prod.BU_FI.mart_ttt_daily_user_record` WHERE GRASS_DATE = '2026-01-31' AND BALANCE > 0 ), high_balance AS ( SELECT COUNT(DISTINCT CAST(REGEXP_EXTRACT(USER_ID, r'\d+') AS STRING)) AS hb_users, SUM(BALANCE) AS hb_aum FROM `momovn-prod.BU_FI.mart_ttt_daily_user_record` WHERE GRASS_DATE = '2026-01-31' AND BALANCE > 50000000 ), demographics AS ( SELECT AGE_GROUP, GENDER, COALESCE(REGION, 'Unknown') AS region, COUNT(DISTINCT CAST(REGEXP_EXTRACT(USER_ID, r'\d+') AS STRING)) AS users FROM `momovn-prod.BU_FI.mart_ttt_daily_user_record` WHERE GRASS_DATE = '2026-01-31' AND BALANCE > 50000000 GROUP BY AGE_GROUP, GENDER, COALESCE(REGION, 'Unknown') ORDER BY users DESC LIMIT 10 ) SELECT hb.hb_users, hb.hb_aum, ROUND(hb.hb_users * 100.0 / a.total_users, 2) AS pct_users, ROUND(hb.hb_aum * 100.0 / a.total_aum, 2) AS pct_aum FROM high_balance hb CROSS JOIN all_users a | I56: 1 row: counts + % of users + % of AUM. Plus demographics query | J56: 1 + top 10 demographic segments | K56: eval | L56: DA Team (AI-assisted) | M56: 46091 | N56: TTT
A57: TTT036 | B57: cuoi tuan user co rut tien nhieu hon ngay thuong khong? | C57: Date/Time | D57: Moderate | E57: mart_ttt_daily_user_record | F57: GRASS_DATE, cashout sub-channels | G57: Cần phân loại ngày thành weekday vs weekend (EXTRACT(DAYOFWEEK)). Tính AVG daily cashout cho mỗi nhóm. Cashout = full 7 sub-channels. Known insight: Mar 7-8 (Sat-Sun) có spike +38-46%. LLM trap: (1) BQ DAYOFWEEK: 1=Sunday, 7=Saturday — dễ code sai, (2) thiếu sub-channels. | H57: SELECT CASE WHEN EXTRACT(DAYOFWEEK FROM GRASS_DATE) IN (1, 7) THEN 'Weekend' ELSE 'Weekday' END AS day_type, COUNT(DISTINCT GRASS_DATE) AS num_days, SUM(COALESCE(cashout_gmv,0)+COALESCE(cashout_napas_gmv,0)+COALESCE(cashout_p2p_gmv,0)+COALESCE(cashout_payment_gmv,0)+COALESCE(cashout_stock_gmv,0)+COALESCE(cashout_mp_gmv,0)+COALESCE(cashout_payment_mp_gmv,0)) AS total_cashout, ROUND(SUM(COALESCE(cashout_gmv,0)+COALESCE(cashout_napas_gmv,0)+COALESCE(cashout_p2p_gmv,0)+COALESCE(cashout_payment_gmv,0)+COALESCE(cashout_stock_gmv,0)+COALESCE(cashout_mp_gmv,0)+COALESCE(cashout_payment_mp_gmv,0)) / COUNT(DISTINCT GRASS_DATE), 0) AS avg_daily_cashout FROM `momovn-prod.BU_FI.mart_ttt_daily_user_record` WHERE GRASS_DATE BETWEEN '2026-02-01' AND '2026-02-28' GROUP BY CASE WHEN EXTRACT(DAYOFWEEK FROM GRASS_DATE) IN (1, 7) THEN 'Weekend' ELSE 'Weekday' END | I57: 2 rows: Weekend vs Weekday avg daily cashout | J57: 2 | K57: eval | L57: DA Team (AI-assisted) | M57: 46091 | N57: TTT
A58: TTT037 | B58: user ttt duoc nhan lai bao nhieu 1 ngay? phan bo theo nhom so du ra sao? | C58: Aggregation | D58: Moderate | E58: mart_ttt_daily_user_record | F58: INTEREST, INT_GROUP, BAL_GROUP, GRASS_DATE | G58: Lãi 1 ngày = SUM(INTEREST) for 1 specific day. "Phân bổ theo nhóm số dư" = GROUP BY BAL_GROUP hoặc INT_GROUP. LLM trap: (1) Dùng sai column interest_gmv, (2) Không biết INT_GROUP/BAL_GROUP columns tồn tại → cố tự CASE WHEN, (3) SUM across nhiều ngày thay vì 1 ngày. | H58: SELECT BAL_GROUP, COUNT(DISTINCT CAST(REGEXP_EXTRACT(USER_ID, r'\d+') AS STRING)) AS users, SUM(INTEREST) AS daily_interest, AVG(INTEREST) AS avg_interest_per_user FROM `momovn-prod.BU_FI.mart_ttt_daily_user_record` WHERE GRASS_DATE = '2026-01-31' AND INTEREST > 0 GROUP BY BAL_GROUP ORDER BY daily_interest DESC | I58: ~6-7 rows (BAL_GROUPs), sorted by interest contribution | J58: 46180 | K58: eval | L58: DA Team (AI-assisted) | M58: 46091 | N58: TTT
A59: TTT038 | B59: user reactive thang 2 quay lai voi bao nhieu tien? co giu lai duoc khong? | C59: Subquery | D59: Complex | E59: mart_ttt_daily_user_record | F59: USER_ID, MAU_TYPE, MFU_TYPE, BALANCE, cashin sub-channels, GRASS_DATE | G59: Reactive = MAU_TYPE = '3.Reactive' trong tháng 2. "Quay lại với bao nhiêu tiền" = tổng cashin hoặc balance cuối tháng 2 của nhóm reactive. "Giữ lại được không" = cần check tháng 3 xem họ còn MFU không → subquery/JOIN 2 tháng. LLM trap: (1) Không biết MAU_TYPE = '3.Reactive', (2) Chỉ query 1 tháng mà không check retention. | H59: WITH reactive_feb AS ( SELECT DISTINCT CAST(REGEXP_EXTRACT(USER_ID, r'\d+') AS STRING) AS uid FROM `momovn-prod.BU_FI.mart_ttt_daily_user_record` WHERE GRASS_DATE BETWEEN '2026-02-01' AND '2026-02-28' AND MAU_TYPE = '3.Reactive' ), feb_metrics AS ( SELECT CAST(REGEXP_EXTRACT(USER_ID, r'\d+') AS STRING) AS uid, SUM(COALESCE(cashin_gmv,0)+COALESCE(cashin_p2p_gmv,0)+COALESCE(cashin_va_gmv,0)+COALESCE(cashin_ai_gmv,0)+COALESCE(cashin_stock_gmv,0)+COALESCE(cashin_payout_gmv,0)+COALESCE(cashin_mp_gmv,0)) AS total_cashin FROM `momovn-prod.BU_FI.mart_ttt_daily_user_record` WHERE GRASS_DATE BETWEEN '2026-02-01' AND '2026-02-28' AND CAST(REGEXP_EXTRACT(USER_ID, r'\d+') AS STRING) IN (SELECT uid FROM reactive_feb) GROUP BY CAST(REGEXP_EXTRACT(USER_ID, r'\d+') AS STRING) ), mar_status AS ( SELECT DISTINCT CAST(REGEXP_EXTRACT(USER_ID, r'\d+') AS STRING) AS uid FROM `momovn-prod.BU_FI.mart_ttt_daily_user_record` WHERE GRASS_DATE BETWEEN '2026-03-01' AND '2026-03-08' AND MAU_TYPE != '0.Churn' ) SELECT COUNT(DISTINCT f.uid) AS reactive_users, SUM(f.total_cashin) AS total_reactive_cashin, AVG(f.total_cashin) AS avg_cashin_per_user, COUNT(DISTINCT m.uid) AS retained_in_mar, ROUND(COUNT(DISTINCT m.uid) * 100.0 / NULLIF(COUNT(DISTINCT f.uid), 0), 2) AS retention_pct FROM feb_metrics f LEFT JOIN mar_status m ON f.uid = m.uid | I59: 1 row: reactive count + cashin + retention into March | J59: 1 | K59: eval | L59: DA Team (AI-assisted) | M59: 46091 | N59: TTT
A60: TTT039 | B60: user nap qua p2p vs nap thuong, nhom nao nhieu hon? | C60: Conditional Logic | D60: Simple | E60: mart_ttt_daily_user_record | F60: CASHIN_GMV, CASHIN_P2P_GMV, USER_ID, GRASS_DATE | G60: Nạp qua P2P = cashin_p2p_gmv. "Nạp thường" = cashin_gmv (cashin thuần từ ví MoMo). So sánh 2 channels. Câu đơn giản nhưng LLM có thể: (1) Gộp tất cả sub-channels thay vì chỉ 2, (2) Hiểu "nạp thường" sai (nghĩ là total). Không nói timeframe. | H60: SELECT 'Cashin Thuần' AS channel, COUNT(DISTINCT CASE WHEN CASHIN_TRANS > 0 THEN CAST(REGEXP_EXTRACT(USER_ID, r'\d+') AS STRING) END) AS users, SUM(COALESCE(CASHIN_GMV, 0)) AS gmv FROM `momovn-prod.BU_FI.mart_ttt_daily_user_record` WHERE GRASS_DATE BETWEEN '2026-02-01' AND '2026-02-28' UNION ALL SELECT 'Cashin P2P', COUNT(DISTINCT CASE WHEN CASHIN_P2P_TRANS > 0 THEN CAST(REGEXP_EXTRACT(USER_ID, r'\d+') AS STRING) END), SUM(COALESCE(CASHIN_P2P_GMV, 0)) FROM `momovn-prod.BU_FI.mart_ttt_daily_user_record` WHERE GRASS_DATE BETWEEN '2026-02-01' AND '2026-02-28' | I60: 2 rows: P2P vs Thuần — user count + GMV comparison | J60: 2 | K60: eval | L60: DA Team (AI-assisted) | M60: 46091 | N60: TTT
A61: TTT040 | B61: nguoi dung tui+ duoc quyen loi gi? bao nhieu nguoi su dung tung quyen loi? | C61: Multi-step | D61: Complex | E61: mart_ttt_daily_user_record | F61: PLUS_TYPE, IS_STOCKBACK, IS_WHEEL, IS_TKOL8M, IS_CASHBACK, IS_CASHOUT_NAPAS, TOTAL_CASHBACK_GMV, CASHOUT_NAPAS_GMV, USER_ID, GRASS_DATE | G61: Quyền lợi Túi+ gồm: (1) Cashback 0.1% thanh toán (IS_CASHBACK), (2) Rút napas miễn phí 100tr/tháng (IS_CASHOUT_NAPAS), (3) Stockback cổ phiếu (IS_STOCKBACK), (4) Vòng quay (IS_WHEEL), (5) TKOL 8M ưu đãi (IS_TKOL8M). Cần COUNT DISTINCT users cho mỗi benefit. Filter Túi+ users trước. LLM gần chắc không biết 5 campaign behavior tags này tồn tại — đây là trap rất khó. | H61: SELECT COUNT(DISTINCT CAST(REGEXP_EXTRACT(USER_ID, r'\d+') AS STRING)) AS total_tui_plus, COUNT(DISTINCT CASE WHEN IS_CASHBACK = 'Cashback' THEN CAST(REGEXP_EXTRACT(USER_ID, r'\d+') AS STRING) END) AS used_cashback, COUNT(DISTINCT CASE WHEN IS_CASHOUT_NAPAS = 'Cashout' THEN CAST(REGEXP_EXTRACT(USER_ID, r'\d+') AS STRING) END) AS used_napas, COUNT(DISTINCT CASE WHEN IS_STOCKBACK = 'Claim Stockback' THEN CAST(REGEXP_EXTRACT(USER_ID, r'\d+') AS STRING) END) AS used_stockback, COUNT(DISTINCT CASE WHEN IS_WHEEL = 'Wheel88' THEN CAST(REGEXP_EXTRACT(USER_ID, r'\d+') AS STRING) END) AS used_wheel, COUNT(DISTINCT CASE WHEN IS_TKOL8M = 'TKOL 8M' THEN CAST(REGEXP_EXTRACT(USER_ID, r'\d+') AS STRING) END) AS used_tkol8m FROM `momovn-prod.BU_FI.mart_ttt_daily_user_record` WHERE GRASS_DATE BETWEEN '2026-01-01' AND '2026-01-31' AND PLUS_TYPE NOT IN ('0.Churn', 'None') AND PLUS_TYPE IS NOT NULL | I61: 1 row: total Túi+ users + count per benefit type | J61: 1 | K61: eval | L61: DA Team (AI-assisted) | M61: 46091 | N61: TTT
A62: TTT041 | B62: tui+ bac vang kim cuong moi hang co bao nhieu nguoi? | C62: Aggregation | D62: Simple | E62: mart_ttt_daily_user_record | F62: TIER, USER_ID, GRASS_DATE, PLUS_TYPE | G62: Bạc vàng kim cương = Silver, Gold, Platinum (column TIER). Cần filter PLUS_TYPE NOT IN ('0.Churn', 'None') trước, rồi GROUP BY TIER. REGEXP_EXTRACT cho dedup. Column TIER mới từ 01/2026 — LLM gần chắc không biết column này tồn tại, sẽ cố dùng PLUS_SEGMENT hoặc CASE WHEN từ BALANCE. Không nói tháng nào. | H62: SELECT TIER, COUNT(DISTINCT CAST(REGEXP_EXTRACT(USER_ID, r'\d+') AS STRING)) AS users FROM `momovn-prod.BU_FI.mart_ttt_daily_user_record` WHERE GRASS_DATE BETWEEN '2026-02-01' AND '2026-02-28' AND PLUS_TYPE NOT IN ('0.Churn', 'None') AND PLUS_TYPE IS NOT NULL GROUP BY TIER ORDER BY users DESC | I62: 3 rows: Silver, Gold, Platinum user counts | J62: 3 | K62: eval | L62: DA Team (AI-assisted) | M62: 46091 | N62: TTT
A63: TTT042 | B63: bao nhieu nguoi bo tien mua tui+? ho chi bao nhieu? | C63: Aggregation | D63: Moderate | E63: mart_ttt_daily_user_record | F63: PLUS_SEGMENT, IS_BUY_PACKAGE, PACKAGE_GMV, PACKAGE_TRANS, USER_ID, GRASS_DATE | G63: Bỏ tiền mua = 2 khía cạnh: (1) mua subscription Túi+ (PLUS_SEGMENT chứa '+ Buy' suffix — Silver + Buy = 9K, Gold + Buy = 19K, Platinum + Buy = 49K), (2) mua gói bundle voucher (IS_BUY_PACKAGE). Câu hỏi ambiguous — user hỏi về subscription hay bundle? Agent tốt nên trả cả 2. LLM sẽ fail vì: (1) không biết PLUS_SEGMENT format mới, (2) không biết IS_BUY_PACKAGE, PACKAGE_GMV columns tồn tại. | H63: -- Part 1: Subscription Túi+ (trả tiền mua tier) SELECT PLUS_SEGMENT, COUNT(DISTINCT CAST(REGEXP_EXTRACT(USER_ID, r'\d+') AS STRING)) AS users FROM `momovn-prod.BU_FI.mart_ttt_daily_user_record` WHERE GRASS_DATE BETWEEN '2026-02-01' AND '2026-02-28' AND PLUS_SEGMENT LIKE '%Buy%' GROUP BY PLUS_SEGMENT ORDER BY users DESC; -- Part 2: Bundle voucher SELECT COUNT(DISTINCT CAST(REGEXP_EXTRACT(USER_ID, r'\d+') AS STRING)) AS bundle_buyers, SUM(COALESCE(PACKAGE_GMV, 0)) AS total_package_revenue, SUM(COALESCE(PACKAGE_TRANS, 0)) AS total_package_trans FROM `momovn-prod.BU_FI.mart_ttt_daily_user_record` WHERE GRASS_DATE BETWEEN '2026-02-01' AND '2026-02-28' AND IS_BUY_PACKAGE IS NOT NULL AND IS_BUY_PACKAGE != 'None' | I63: Part 1: rows per Buy segment. Part 2: total buyers + revenue | J63: Multi-query | K63: eval | L63: DA Team (AI-assisted) | M63: 46091 | N63: TTT
A64: TTT043 | B64: user ttt dung tien ttt de thanh toan va chuyen tien chiem bao nhieu % tong momo? | C64: Aggregation | D64: Moderate | E64: mart_ttt_daily_user_record | F64: TTT_P2P_GMV, TTT_PAYMENT_GMV, MOMO_P2P_GMV, MOMO_PAYMENT_GMV, GRASS_DATE | G64: % penetration = ttt_gmv / momo_gmv * 100. Có 2 metrics: P2P penetration (ttt_p2p_gmv / momo_p2p_gmv) và Payment penetration (ttt_payment_gmv / momo_payment_gmv). Columns mới hoàn toàn — LLM không biết tồn tại. Sẽ cố dùng cashout_p2p_gmv hoặc cashout_payment_gmv (sai vì đó chỉ là cashout, không phải cross-platform metric). | H64: SELECT SUM(COALESCE(TTT_P2P_GMV, 0)) AS ttt_p2p, SUM(COALESCE(MOMO_P2P_GMV, 0)) AS momo_p2p, ROUND(SUM(COALESCE(TTT_P2P_GMV, 0)) * 100.0 / NULLIF(SUM(COALESCE(MOMO_P2P_GMV, 0)), 0), 2) AS p2p_penetration_pct, SUM(COALESCE(TTT_PAYMENT_GMV, 0)) AS ttt_payment, SUM(COALESCE(MOMO_PAYMENT_GMV, 0)) AS momo_payment, ROUND(SUM(COALESCE(TTT_PAYMENT_GMV, 0)) * 100.0 / NULLIF(SUM(COALESCE(MOMO_PAYMENT_GMV, 0)), 0), 2) AS payment_penetration_pct FROM `momovn-prod.BU_FI.mart_ttt_daily_user_record` WHERE GRASS_DATE BETWEEN '2026-02-01' AND '2026-02-28' | I64: 1 row: P2P penetration % + Payment penetration % | J64: 1 | K64: eval | L64: DA Team (AI-assisted) | M64: 46091 | N64: TTT
A65: TTT044 | B65: tier platinum co so du trung binh bao nhieu? so voi silver va gold? | C65: Aggregation | D65: Moderate | E65: mart_ttt_daily_user_record | F65: TIER, BALANCE, AVG_BALANCE, USER_ID, GRASS_DATE, PLUS_TYPE | G65: GROUP BY TIER, tính AVG(BALANCE) tại end-of-month snapshot. Filter PLUS_TYPE active. Bẫy: (1) TIER column mới, LLM không biết, (2) Dùng AVG_BALANCE (rolling 30d) thay vì AVG(BALANCE) (snapshot) — 2 con số khác nhau, câu hỏi hỏi "số dư trung bình" có thể map vào cả 2. (3) Platinum = Balance 50M+ nên avg balance phải rất cao. | H65: SELECT TIER, COUNT(DISTINCT CAST(REGEXP_EXTRACT(USER_ID, r'\d+') AS STRING)) AS users, AVG(BALANCE) AS avg_balance, SUM(BALANCE) AS total_aum FROM `momovn-prod.BU_FI.mart_ttt_daily_user_record` WHERE GRASS_DATE = '2026-02-28' AND PLUS_TYPE NOT IN ('0.Churn', 'None') AND PLUS_TYPE IS NOT NULL GROUP BY TIER ORDER BY avg_balance DESC | I65: 3 rows: Platinum (avg very high ~50M+), Gold, Silver — sorted by avg_balance | J65: 3 | K65: eval | L65: DA Team (AI-assisted) | M65: 46091 | N65: TTT
A66: TTT045 | B66: user nhan xu sinh loi co bao nhieu? ho co xu huong giu tien lau hon khong? | C66: Multi-step | D66: Complex | E66: mart_ttt_daily_user_record | F66: IS_COIN_INT, IS_COIN_SPENT, USER_ID, BALANCE, MFU_TYPE, GRASS_DATE | G66: Xu sinh lời = IS_COIN_INT column (scheme collab MoMo Xu, 8%/năm). "Giữ tiền lâu hơn" = so sánh MFU retention hoặc avg balance giữa nhóm IS_COIN_INT active vs non-active. Cần 2 queries: (1) count IS_COIN_INT users, (2) compare balance/retention metrics. LLM gần chắc không biết IS_COIN_INT tồn tại. Câu hỏi cũng liên quan IS_COIN_SPENT (đổi xu → voucher). | H66: -- Part 1: Count coin interest users SELECT IS_COIN_INT, COUNT(DISTINCT CAST(REGEXP_EXTRACT(USER_ID, r'\d+') AS STRING)) AS users, AVG(BALANCE) AS avg_balance FROM `momovn-prod.BU_FI.mart_ttt_daily_user_record` WHERE GRASS_DATE = '2026-02-28' AND MFU_TYPE != '0.Churn' GROUP BY IS_COIN_INT; -- Part 2: Compare retention (MFU retain rate) SELECT CASE WHEN IS_COIN_INT IS NOT NULL AND IS_COIN_INT != 'None' THEN 'Coin Interest User' ELSE 'Regular User' END AS segment, COUNT(DISTINCT CASE WHEN MFU_TYPE = '2.Retain' THEN CAST(REGEXP_EXTRACT(USER_ID, r'\d+') AS STRING) END) AS retained, COUNT(DISTINCT CAST(REGEXP_EXTRACT(USER_ID, r'\d+') AS STRING)) AS total, ROUND(COUNT(DISTINCT CASE WHEN MFU_TYPE = '2.Retain' THEN CAST(REGEXP_EXTRACT(USER_ID, r'\d+') AS STRING) END) * 100.0 / NULLIF(COUNT(DISTINCT CAST(REGEXP_EXTRACT(USER_ID, r'\d+') AS STRING)), 0), 2) AS retain_pct FROM `momovn-prod.BU_FI.mart_ttt_daily_user_record` WHERE GRASS_DATE BETWEEN '2026-02-01' AND '2026-02-28' AND MFU_TYPE != '0.Churn' GROUP BY CASE WHEN IS_COIN_INT IS NOT NULL AND IS_COIN_INT != 'None' THEN 'Coin Interest User' ELSE 'Regular User' END | I66: Part 1: user counts + avg balance by IS_COIN_INT. Part 2: retention comparison | J66: Multi-query | K66: eval | L66: DA Team (AI-assisted) | M66: 46091 | N66: TTT
A67: TTT046 | B67: % nguoi dung ttt dung tien ttt chuyen khoan tang hay giam? tach p2p voi thanh toan | C67: Date/Time | D67: Complex | E67: mart_ttt_daily_user_record | F67: TTT_P2P_GMV, TTT_PAYMENT_GMV, MOMO_P2P_GMV, MOMO_PAYMENT_GMV, GRASS_DATE | G67: Cần tính penetration % theo tháng cho cả P2P và Payment, rồi so trend MoM. Penetration = ttt_gmv / momo_gmv. "Tách P2P với thanh toán" = 2 metrics riêng. Cần ít nhất 2-3 tháng data. LLM sẽ fail vì: (1) Không biết columns mới, (2) Dùng cashout_p2p thay vì ttt_p2p_gmv, (3) Không có mẫu số momo_* để tính %. | H67: SELECT DATE_TRUNC(GRASS_DATE, MONTH) AS month, ROUND(SUM(COALESCE(TTT_P2P_GMV, 0)) * 100.0 / NULLIF(SUM(COALESCE(MOMO_P2P_GMV, 0)), 0), 2) AS p2p_penetration_pct, ROUND(SUM(COALESCE(TTT_PAYMENT_GMV, 0)) * 100.0 / NULLIF(SUM(COALESCE(MOMO_PAYMENT_GMV, 0)), 0), 2) AS payment_penetration_pct FROM `momovn-prod.BU_FI.mart_ttt_daily_user_record` WHERE GRASS_DATE BETWEEN '2025-12-01' AND '2026-02-28' GROUP BY DATE_TRUNC(GRASS_DATE, MONTH) ORDER BY month | I67: 3 rows (Dec, Jan, Feb): P2P penetration % + Payment penetration % monthly trend | J67: 3 | K67: eval | L67: DA Team (AI-assisted) | M67: 46091 | N67: TTT
A68: TTT047 | B68: merchant nap tien payout vao ttt tu khi nao? co bao nhieu merchant dang dung? | C68: Aggregation | D68: Moderate | E68: mart_ttt_daily_user_record | F68: FIRST_PAYOUT_DATE, CASHIN_PAYOUT_GMV, CASHIN_PAYOUT_TRANS, USER_ID, GRASS_DATE | G68: Merchant nạp payout = user có FIRST_PAYOUT_DATE IS NOT NULL hoặc CASHIN_PAYOUT_GMV > 0. "Từ khi nào" = MIN(FIRST_PAYOUT_DATE). "Bao nhiêu merchant" = COUNT DISTINCT users có payout. Column FIRST_PAYOUT_DATE mới — LLM không biết. Sẽ cố filter bằng cashin_payout_gmv > 0 (gần đúng nhưng thiếu FIRST_PAYOUT_DATE insight). | H68: SELECT COUNT(DISTINCT CAST(REGEXP_EXTRACT(USER_ID, r'\d+') AS STRING)) AS active_merchants, MIN(FIRST_PAYOUT_DATE) AS earliest_payout_date, SUM(COALESCE(CASHIN_PAYOUT_GMV, 0)) AS total_payout_gmv, SUM(COALESCE(CASHIN_PAYOUT_TRANS, 0)) AS total_payout_trans FROM `momovn-prod.BU_FI.mart_ttt_daily_user_record` WHERE GRASS_DATE BETWEEN '2026-02-01' AND '2026-02-28' AND FIRST_PAYOUT_DATE IS NOT NULL | I68: 1 row: merchant count + earliest payout date + GMV + trans | J68: 1 | K68: eval | L68: DA Team (AI-assisted) | M68: 46091 | N68: TTT
A69: TTT048 | B69: tier nao dung ttt de thanh toan nhieu nhat? platinum co dung nhieu hon silver khong? | C69: Conditional Logic | D69: Complex | E69: mart_ttt_daily_user_record | F69: TIER, TTT_PAYMENT_GMV, TTT_PAYMENT_TRANS, TTT_P2P_GMV, USER_ID, PLUS_TYPE, GRASS_DATE | G69: Cross 2 dimensions mới: TIER × TTT as SOF. Cần GROUP BY TIER, SUM(ttt_payment_gmv + ttt_p2p_gmv). Filter PLUS_TYPE active. LLM fail vì: (1) TIER column unknown, (2) TTT_PAYMENT_GMV unknown → dùng cashout_payment_gmv (gần nhưng không phải SOF metric), (3) Thiếu cross-analysis tier × SOF. | H69: SELECT TIER, COUNT(DISTINCT CAST(REGEXP_EXTRACT(USER_ID, r'\d+') AS STRING)) AS users, SUM(COALESCE(TTT_PAYMENT_GMV, 0)) AS ttt_payment_gmv, SUM(COALESCE(TTT_P2P_GMV, 0)) AS ttt_p2p_gmv, SUM(COALESCE(TTT_PAYMENT_GMV, 0) + COALESCE(TTT_P2P_GMV, 0)) AS total_sof_gmv, ROUND(SUM(COALESCE(TTT_PAYMENT_GMV, 0) + COALESCE(TTT_P2P_GMV, 0)) / NULLIF(COUNT(DISTINCT CAST(REGEXP_EXTRACT(USER_ID, r'\d+') AS STRING)), 0), 0) AS avg_sof_per_user FROM `momovn-prod.BU_FI.mart_ttt_daily_user_record` WHERE GRASS_DATE BETWEEN '2026-02-01' AND '2026-02-28' AND PLUS_TYPE NOT IN ('0.Churn', 'None') AND PLUS_TYPE IS NOT NULL GROUP BY TIER ORDER BY total_sof_gmv DESC | I69: 3 rows: tier comparison on SOF usage, Platinum likely highest per user | J69: 3 | K69: eval | L69: DA Team (AI-assisted) | M69: 46091 | N69: TTT
A70: TTT049 | B70: user chuyen tien qua ngan hang (e2b) tu ttt so voi toan momo nhu nao? | C70: Aggregation | D70: Moderate | E70: mart_ttt_daily_user_record | F70: TTT_P2P_E2B_GMV, TTT_P2P_E2B_TRANS, MOMO_P2P_E2B_GMV, MOMO_P2P_E2B_TRANS, GRASS_DATE | G70: E2B = E-wallet to Bank transfer. Columns rất mới (chưa có đầy đủ data model note). So sánh TTT E2B vs MoMo E2B để tính penetration. LLM gần chắc không biết E2B columns tồn tại — sẽ cố dùng cashout_napas (liên quan nhưng khác concept: napas = TTT → bank trực tiếp, E2B = ví → bank qua P2P). | H70: SELECT SUM(COALESCE(TTT_P2P_E2B_GMV, 0)) AS ttt_e2b_gmv, SUM(COALESCE(MOMO_P2P_E2B_GMV, 0)) AS momo_e2b_gmv, ROUND(SUM(COALESCE(TTT_P2P_E2B_GMV, 0)) * 100.0 / NULLIF(SUM(COALESCE(MOMO_P2P_E2B_GMV, 0)), 0), 2) AS e2b_penetration_pct, SUM(COALESCE(TTT_P2P_E2B_TRANS, 0)) AS ttt_e2b_trans, SUM(COALESCE(MOMO_P2P_E2B_TRANS, 0)) AS momo_e2b_trans FROM `momovn-prod.BU_FI.mart_ttt_daily_user_record` WHERE GRASS_DATE BETWEEN '2026-02-01' AND '2026-02-28' | I70: 1 row: TTT E2B GMV, MoMo E2B GMV, penetration % | J70: 1 | K70: eval | L70: DA Team (AI-assisted) | M70: 46091 | N70: TTT
A71: TTT050 | B71: so sanh hanh vi su dung ttt lam nguon tien cua 3 tier bac vang kim cuong — ai chuyen tien nhieu, ai thanh toan nhieu? | C71: Multi-step | D71: Complex | E71: mart_ttt_daily_user_record | F71: TIER, TTT_P2P_GMV, TTT_P2P_TRANS, TTT_PAYMENT_GMV, TTT_PAYMENT_TRANS, TTT_P2P_E2B_GMV, MOMO_P2P_GMV, MOMO_PAYMENT_GMV, USER_ID, PLUS_TYPE, GRASS_DATE | G71: Full cross-analysis: TIER × (P2P + Payment + E2B). Cần per-user metrics (avg GMV/user) để so sánh fair vì Platinum ít user hơn nhưng chi nhiều hơn. Also tính penetration per tier = ttt_gmv / momo_gmv. Đây là câu hỏi tổng hợp exploit gần như tất cả columns mới: TIER + ttt_p2p + ttt_payment + momo_p2p + momo_payment + e2b. LLM sẽ fail ở hầu hết mọi khía cạnh. | H71: SELECT TIER, COUNT(DISTINCT CAST(REGEXP_EXTRACT(USER_ID, r'\d+') AS STRING)) AS users, -- P2P SUM(COALESCE(TTT_P2P_GMV, 0)) AS ttt_p2p_gmv, ROUND(SUM(COALESCE(TTT_P2P_GMV, 0)) / NULLIF(COUNT(DISTINCT CAST(REGEXP_EXTRACT(USER_ID, r'\d+') AS STRING)), 0), 0) AS avg_p2p_per_user, ROUND(SUM(COALESCE(TTT_P2P_GMV, 0)) * 100.0 / NULLIF(SUM(COALESCE(MOMO_P2P_GMV, 0)), 0), 2) AS p2p_penetration_pct, -- Payment SUM(COALESCE(TTT_PAYMENT_GMV, 0)) AS ttt_payment_gmv, ROUND(SUM(COALESCE(TTT_PAYMENT_GMV, 0)) / NULLIF(COUNT(DISTINCT CAST(REGEXP_EXTRACT(USER_ID, r'\d+') AS STRING)), 0), 0) AS avg_payment_per_user, ROUND(SUM(COALESCE(TTT_PAYMENT_GMV, 0)) * 100.0 / NULLIF(SUM(COALESCE(MOMO_PAYMENT_GMV, 0)), 0), 2) AS payment_penetration_pct, -- E2B SUM(COALESCE(TTT_P2P_E2B_GMV, 0)) AS ttt_e2b_gmv FROM `momovn-prod.BU_FI.mart_ttt_daily_user_record` WHERE GRASS_DATE BETWEEN '2026-02-01' AND '2026-02-28' AND PLUS_TYPE NOT IN ('0.Churn', 'None') AND PLUS_TYPE IS NOT NULL GROUP BY TIER ORDER BY ttt_p2p_gmv + ttt_payment_gmv DESC | I71: 3 rows: Silver, Gold, Platinum — full SOF breakdown with per-user avg + penetration % | J71: 3 | K71: eval | L71: DA Team (AI-assisted) | M71: 46091 | N71: TTT
A72: TTT051 | B72: so sanh chi phi hoan tien tui cong va doanh thu ban tui cong trung binh moi user trong 6 thang qua | C72: Multi-step | D72: Complex | E72: mart_ttt_daily_user_record | F72: total_cashback_gmv, user_id, grass_date, segment, | G72: - Chi phí: TOTAL_CASHBACK_GMV (0.1% hoàn tiền cho Túi+ users) - Doanh thu: Phí subscription — nhưng không có column trực tiếp, phải ước lượng từ PLUS_SEGMENT (chứa suffix Buy) với data sau 2026-01-01, và chứa ''TTT+ 9k'' với data trước 2026-01-01 - Upgrade: Nếu user đã có tier thấp (kể cả miễn phí) → mua tier cao hơn chỉ trả phần chênh lệch - Detect upgrade: Dùng LAG(TIER) so sánh tier các ngày trước vs hiện tại | H72: WITH monthly_user AS ( -- Gom về 1 row / user / tháng SELECT DATE_TRUNC(GRASS_DATE, MONTH) AS month, CAST(REGEXP_EXTRACT(USER_ID, r'\d+') AS STRING) AS uid, -- Lấy segment + tier cuối tháng (ổn định nhất) ARRAY_AGG(PLUS_SEGMENT ORDER BY GRASS_DATE DESC LIMIT 1)[OFFSET(0)] AS plus_segment, ARRAY_AGG(TIER ORDER BY GRASS_DATE DESC LIMIT 1)[OFFSET(0)] AS tier, -- Cashback = tích lũy hàng ngày → SUM cả tháng SUM(COALESCE(TOTAL_CASHBACK_GMV, 0)) AS cashback_gmv FROM `momovn-prod.BU_FI.mart_ttt_daily_user_record` WHERE GRASS_DATE BETWEEN '2025-09-01' AND '2026-02-28' AND PLUS_TYPE NOT IN ('0.Churn', 'None') AND PLUS_TYPE IS NOT NULL GROUP BY 1, 2 ), with_prev_tier AS ( -- Detect upgrade: so sánh tier tháng trước SELECT *, LAG(tier) OVER (PARTITION BY uid ORDER BY month) AS prev_tier FROM monthly_user ), revenue_calc AS ( SELECT month, uid, cashback_gmv, plus_segment, tier, prev_tier, -- ===== ƯỚC LƯỢNG DOANH THU SUBSCRIPTION ===== CASE -- [Pre-2026] Chỉ có 1 gói TTT+ 9k WHEN month < '2026-01-01' AND plus_segment = 'TTT+ 9k' THEN 9000 -- [Post-2026] Silver + Buy = 9K (không có tier thấp hơn → luôn full) WHEN month >= '2026-01-01' AND plus_segment LIKE '%Silver%Buy%' THEN 9000 -- [Post-2026] Gold + Buy: 19K full, hoặc chênh lệch nếu upgrade WHEN month >= '2026-01-01' AND plus_segment LIKE '%Gold%Buy%' THEN CASE WHEN prev_tier = 'Silver' THEN 19000 - 9000 -- upgrade Silver→Gold: 10K ELSE 19000 -- mua mới: 19K END -- [Post-2026] Platinum + Buy: 49K full, hoặc chênh lệch WHEN month >= '2026-01-01' AND plus_segment LIKE '%Platinum%Buy%' THEN CASE WHEN prev_tier = 'Gold' THEN 49000 - 19000 -- upgrade Gold→Plat: 30K WHEN prev_tier = 'Silver' THEN 49000 - 9000 -- upgrade Silver→Plat: 40K ELSE 49000 -- mua mới: 49K END -- Các segment khác = được Túi+ miễn phí ELSE 0 END AS est_revenue, -- Flag paid user CASE WHEN plus_segment = 'TTT+ 9k' THEN 1 WHEN plus_segment LIKE '%Buy%' THEN 1 ELSE 0 END AS is_paid FROM with_prev_tier ) -- ===== KẾT QUẢ CHÍNH: MONTHLY COMPARISON ===== SELECT month, -- Tổng quan users COUNT(DISTINCT uid) AS total_plus_users, COUNT(DISTINCT CASE WHEN is_paid = 1 THEN uid END) AS paid_users, COUNT(DISTINCT CASE WHEN cashback_gmv > 0 THEN uid END) AS cashback_users, -- CHI PHÍ HOÀN TIỀN (Cashback 0.1%) ROUND(SUM(cashback_gmv), 0) AS total_cashback_cost, ROUND(SUM(cashback_gmv) / NULLIF(COUNT(DISTINCT CASE WHEN cashback_gmv > 0 THEN uid END), 0), 0) AS avg_cashback_per_cb_user, ROUND(SUM(cashback_gmv) / NULLIF(COUNT(DISTINCT uid), 0), 0) AS avg_cashback_per_plus_user, -- DOANH THU BÁN TÚI+ (subscription) ROUND(SUM(est_revenue), 0) AS total_subscription_revenue, ROUND(SUM(est_revenue) / NULLIF(COUNT(DISTINCT CASE WHEN is_paid = 1 THEN uid END), 0), 0) AS avg_revenue_per_paid_user, ROUND(SUM(est_revenue) / NULLIF(COUNT(DISTINCT uid), 0), 0) AS avg_revenue_per_plus_user, -- NET = Revenue - Cost (per Túi+ user) ROUND( (SUM(est_revenue) - SUM(cashback_gmv)) / NULLIF(COUNT(DISTINCT uid), 0), 0 ) AS net_per_plus_user, -- Ratio: doanh thu / chi phí ROUND(SUM(est_revenue) / NULLIF(SUM(cashback_gmv), 0), 4) AS revenue_cost_ratio FROM revenue_calc GROUP BY month ORDER BY month | I72: 6 rows (Sep 2025 → Feb 2026): Tổng tiền MoMo trả lại user (chi phí) , Tổng tiền user trả để mua Túi+ (doanh thu), TB chi phí hoàn / user có nhận cashback,TB doanh thu / user trả tiền mua Túi+, Lãi/lỗ ròng trên mỗi user Túi+ , ROI >1 = lãi, <1 = lỗ | J72: 6 | K72: eval | L72: DA Team (AI-assisted) | M72: 46091 | N72: TTT
A74: VTS001 | B74: tổng GMV VTS ở SME OFFLINE trong tháng 1/2026 là bao nhiêu | C74: Aggregation | D74: Simple | E74: momovn-prod.BU_FI.PAYLATER_ALL_TRANS | F74: amount, created_date, service_category | G74: result_code=0 & pay_pl/pay_ins & service_category = 'SME OFFLINE' | H74: SELECT SUM(amount) FROM momovn-prod.BU_FI.PAYLATER_ALL_TRANS WHERE 1=1 AND created_date BETWEEN '2026-01-01' AND '2026-01-31' AND result_code=0 AND trans_type IN ('pay_pl','pay_ins') and service_category = 'SME OFFLINE' | I74: 1 row, GMV = 225418915314 | J74: 1 | K74: dev | L74: DA_Team | M74: 2025-03-11 | N74: VTS
A75: VTS002 | B75: tháng 12/2025 có bao nhiêu user dùng VTS theo active_type | C75: Aggregation | D75: Simple | E75: momovn-prod.BU_FI.momovn-prod.BU_FI.PAYLATER_MAU_SEGMENT | F75: mau_type, agent_id, month_trans | G75: MAU = distinct users | H75: SELECT mau_type, count(distinct agent_id) FROM `momovn-prod.BU_FI.PAYLATER_MAU_SEGMENT` WHERE month_trans = '2025-12-01' group by 1 order by 1 | I75: 3 row, 1.New 112594 2.Retain 1158626 3.Reactive 165386 | J75: 3 | K75: dev | L75: DA_Team | M75: 2025-03-11 | N75: VTS
A76: VTS003 | B76: Có bao nhiêu user light, medium, hardcore ở tháng 1/2026? | C76: Conditional Logic | D76: Simple | E76: momovn-prod.BU_FI.momovn-prod.BU_FI.PAYLATER_MAU_SEGMENT | F76: agent_id, trans_vts, month_trans | G76: Phân loại theo số transaction (trans_vts): light = 1-3 trans, medium = 4-6 trans, hardcore = 7+ trans. CASE WHEN trans_vts BETWEEN 1 AND 3 → light, 4-6 → medium, >=7 → hardcore | H76: SELECT CASE WHEN trans_vts BETWEEN 1 AND 3 THEN 'light' WHEN trans_vts BETWEEN 4 AND 6 THEN 'medium' WHEN trans_vts >= 7 THEN 'hardcore' END AS user_segment, COUNT(DISTINCT agent_id) AS user_count FROM `momovn-prod.BU_FI.PAYLATER_MAU_SEGMENT` WHERE month_trans = '2026-01-01' GROUP BY 1 ORDER BY 1 | I76: 3 rows, user_segment user_count 1.light 596303 2.medium 286755 3.hardcore 570525 | J76: 3 | K76: eval | L76: DA_Team | M76: 2025-03-11 | N76: VTS
A77: VTS004 | B77: Số lượng user có trả góp ở TikTok thang 1/2026 | C77: Aggregation | D77: Simple | E77: PAYLATER_ALL_TRANS | F77: user_id, trans_type, service_name, result_code | G77: Trả góp: trans_type = 'pay_ins'. Merchant TikTok: service_nameLIKE '%tiktok%' (có thể viết hoa/thường khác nhau). Filter result_code = 0. COUNT DISTINCT user_id | H77: SELECT COUNT(DISTINCT user_id) AS user_count FROM `momovn-prod.BU_FI.PAYLATER_ALL_TRANS` WHERE result_code = 0 AND trans_type = 'pay_ins' AND created_date BETWEEN '2026-01-01' AND '2026-01-31' AND LOWER(service_name) LIKE '%tiktok%' group by all | I77: 1 row, 17466 | J77: 1 | K77: dev | L77: DA_Team | M77: 2025-03-11 | N77: VTS
A78: VTS005 | B78: Số lượng MAU theo từng nhóm tuổi trong tháng 3/2025 | C78: Aggregation | D78: Simple | E78: momovn-prod.BU_FI.PAYLATER_MAU_SEGMENT | F78: agent_id, age_group, month_trans | G78: COUNT DISTINCT agent_id GROUP BY age_group | H78: SELECT age_group, COUNT(DISTINCT agent_id) AS user_count FROM `momovn-prod.BU_FI.PAYLATER_MAU_SEGMENT` WHERE month_trans = '2025-03-01' GROUP BY age_group ORDER BY age_group | I78: 7 rows (7 age groups) age_group user_count [1] Age <=22 332642 [2] Age 23-26 255399 [3] Age 27-30 162575 [4] Age 31-35 152964 [5] Age 36-40 79371 [6] Age > 40 60005 | J78: 7 | K78: dev | L78: DA_Team | M78: 2025-03-11 | N78: VTS
A79: VTS006 | B79: User đang có hạn mức như thế nào? Cho xem phân bổ credit limit theo số user tháng 2/2025 | C79: Aggregation | D79: Simple | E79: momovn-prod.BU_FI.PAYLATER_MAU_SEGMENT | F79: agent_id, credit_limit, month_trans | G79: Phân bổ credit_limit theo khoảng. Có thể chia theo các mức phổ biến: <=1M, 1-3M, 3-5M, 5-10M, 10-20M, >20M. CASE WHEN để bucket rồi COUNT DISTINCT agent_id | H79: SELECT CASE WHEN credit_limit <= 1000000 THEN '01. <=1M' WHEN credit_limit <= 3000000 THEN '02. 1-3M' WHEN credit_limit <= 5000000 THEN '03. 3-5M' WHEN credit_limit <= 10000000 THEN '04. 5-10M' WHEN credit_limit <= 20000000 THEN '05. 10-20M' ELSE '06. >20M' END AS credit_limit_bucket, COUNT(DISTINCT agent_id) AS user_count FROM `momovn-prod.BU_FI.PAYLATER_MAU_SEGMENT` WHERE month_trans = '2025-02-01' GROUP BY 1 ORDER BY 1 | I79: 5 row 01. <=1M 328968 02. 1-3M 211902 03. 3-5M 151661 04. 5-10M 217911 05. 10-20M 60549 | J79: 5 | K79: eval | L79: DA_Team | M79: 2025-03-11 | N79: VTS
A80: VTS007 | B80: User ở HCM thanh toán ở SME , tách theo active type, thang 3/2025 | C80: Ranking + Filter | D80: Simple | E80: momovn-prod.BU_FI.PAYLATER_MAU_SEGMENT | F80: agent_id, spending_sps, sl_trans_sps, most_city_a60, mau_type, month_trans | G80: SME = SME OFFLINE, tương ứng cột spending_sps / sl_trans_sps. User có dùng SME: sl_trans_sps > 0. Location dùng most_city_a60 ( most_city_a60 = 'Hồ Chí Minh'. active_type = mau_type (1.New, 2.Retain, 3.Reactive). | H80: SELECT mau_type, COUNT(DISTINCT agent_id) AS user_count, SUM(spending_sps) AS total_spending_sme, SUM(sl_trans_sps) AS total_trans_sme FROM `momovn-prod.BU_FI.PAYLATER_MAU_SEGMENT` WHERE month_trans = '2025-03-01' AND sl_trans_sps > 0 and most_city_a60 = 'Hồ Chí Minh' GROUP BY 1 ORDER BY 1 | I80: 3 row: mau_type user_count total_spending_sme total_trans_sme 1.New 6223 11052796573.0 14814 2.Retain 126213 182967382561.0 430887 3.Reactive 9713 14737209346.0 23693 | J80: 3 | K80: dev | L80: DA_Team | M80: 2025-03-11 | N80: VTS
A81: VTS008 | B81: Top 10% user PayLater chiếm bao nhiêu % GMV? thang 12/2025 | C81: Window + Complex | D81: Moderate | E81: momovn-prod.BU_FI.PAYLATER_MAU_SEGMENT | F81: agent_id, spending_vts, month_trans | G81: Dùng NTILE(10) hoặc PERCENT_RANK() để xác định top 10% user theo spending_vts. GMV = SUM(spending_vts). Tính % GMV của top 10% so với tổng GMV | H81: WITH user_ranked AS ( SELECT agent_id, spending_vts, NTILE(10) OVER (ORDER BY spending_vts DESC) AS decile FROM `momovn-prod.BU_FI.PAYLATER_MAU_SEGMENT` WHERE month_trans = '2025-12-01' ) SELECT COUNT(DISTINCT CASE WHEN decile = 1 THEN agent_id END) AS top10pct_users, COUNT(DISTINCT agent_id) AS total_users, SUM(CASE WHEN decile = 1 THEN spending_vts ELSE 0 END) AS top10pct_gmv, SUM(spending_vts) AS total_gmv, SAFE_DIVIDE( SUM(CASE WHEN decile = 1 THEN spending_vts ELSE 0 END), SUM(spending_vts) ) AS top10pct_gmv_share FROM user_ranked | I81: 1 row, "top10pct_users": "143661", "total_users": "1436606", "top10pct_gmv": "1133211080525.0", "total_gmv": "2367319098181.0", "top10pct_gmv_share": "0.478" | J81: 1 | K81: eval | L81: DA_Team | M81: 2025-03-11 | N81: VTS
A82: VTS009 | B82: So sánh tỷ lệ retain giữa user có dùng promo và không dùng promo trong tháng 11/2025 | C82: Conditional Logic | D82: Moderate | E82: momovn-prod.BU_FI.PAYLATER_MAU_SEGMENT | F82: is_retain_next_month, is_using_promo, agent_id, month_trans | G82: is_using_promo = 1 là có dùng promo. Retention rate = SAFE_DIVIDE(SUM(is_retain_next_month), COUNT(DISTINCT agent_id)). GROUP BY is_using_promo | H82: SELECT is_using_promo, COUNT(DISTINCT agent_id) AS users, SAFE_DIVIDE(SUM(is_retain_next_month), COUNT(DISTINCT agent_id)) AS retention_rate FROM `momovn-prod.BU_FI.PAYLATER_MAU_SEGMENT` WHERE month_trans = '2025-11-01' GROUP BY is_using_promo | I82: 2 rows, promo vs non-promo với retention rate: [{ "is_using_promo": "0", "users": "1115184", "retention_rate": "0.843" }, { "is_using_promo": "1", "users": "262734", "retention_rate": "0.830" }] | J82: 2 | K82: eval | L82: DA_Team | M82: 2025-03-11 | N82: VTS
A83: VTS010 | B83: User thanh toán VTS bao nhiêu dịch vụ ? Phân bổ user theo số lượng dịch vụ tháng 12/2025 | C83: Conditional Logic | D83: Moderate | E83: momovn-prod.BU_FI.PAYLATER_MAU_SEGMENT, | F83: agent_id, cnt_usecase, month_trans | G83: cnt_usecase là số distinct usecase mỗi user dùng trong tháng. Tạo range: 1 usecase, 2 usecase, 3+ usecase, CASE WHEN để bucket rồi COUNT DISTINCT agent_id | H83: SELECT CASE WHEN cnt_usecase <= 1 THEN '1 usecase' WHEN cnt_usecase = 2 THEN '2 usecases' WHEN cnt_usecase >= 3 THEN '3+ usecases' END AS usecase_range, COUNT(DISTINCT agent_id) AS user_count FROM `momovn-prod.BU_FI.PAYLATER_MAU_SEGMENT` WHERE month_trans = '2025-12-01' GROUP BY 1 ORDER BY 1 | I83: 3 row; [{ "usecase_range": "1 usecase", "user_count": "514981" }, { "usecase_range": "2 usecases", "user_count": "347842" }, { "usecase_range": "3+ usecases", "user_count": "573783" }] | J83: 3 | K83: eval | L83: DA_Team | M83: 2025-03-11 | N83: VTS
A84: VTS011 | B84: User có first usecase là airtime/data thì second usecase tập trung vào usecase nào? thang 1/2026 | C84: Window + Complex | D84: Moderate | E84: PAYLATER_ALL_TRANS | F84: user_id, core_id, service_category, created_millis, result_code, trans_type | G84: Cần xác định thứ tự usecase theo thời gian cho mỗi user. Dùng ROW_NUMBER() PARTITION BY user_id ORDER BY created_millis để rank transaction. First usecase = service_category của transaction đầu tiên. Lọc user có first usecase là AIRTIME hoặc DATA. Second usecase = service_category của transaction thứ 2 (khác service_category đầu). Filter: result_code = 0, trans_type IN ('pay_pl','pay_ins','send_pl') | H84: WITH trans_ranked AS ( SELECT user_id, service_category, created_millis, ROW_NUMBER() OVER (PARTITION BY user_id ORDER BY created_millis) AS rn FROM `momovn-prod.BU_FI.PAYLATER_ALL_TRANS` WHERE result_code = 0 AND trans_type IN ('pay_pl','pay_ins','send_pl') AND created_date BETWEEN '2026-01-01' AND '2026-01-31' ), first_uc AS ( SELECT user_id, service_category AS first_usecase FROM trans_ranked WHERE rn = 1 AND UPPER(service_category) IN ('AIRTIME', 'DATA') ), second_uc AS ( SELECT t.user_id, t.service_category AS second_usecase FROM trans_ranked t JOIN first_uc f ON t.user_id = f.user_id WHERE t.rn > 1 AND t.service_category != f.first_usecase QUALIFY ROW_NUMBER() OVER (PARTITION BY t.user_id ORDER BY t.created_millis) = 1 ) SELECT s.second_usecase, COUNT(DISTINCT s.user_id) AS user_count FROM second_uc s GROUP BY s.second_usecase ORDER BY user_count DESC | I84: 17 row: second_usecase user_count UTILITIES 41579 MARKETPLACE 32971 APPLICATION STORE 27654 LOGISTICS 23827 SME OFFLINE 18693 RETAIL 16532 CINEMA 4557 GAME 4215 DIGITAL CONTENT 3666 FNB 2690 OTT 2586 PUBLIC SERVICE 2249 OTA 1835 MEDIUM SIZE POS MC 1130 ADS PAYMENT 780 INSURANCE 684 MONEY MARKET FUNDS 130 | J84: 17 | K84: eval | L84: DA_Team | M84: 2025-03-11 | N84: VTS
A85: VTS012 | B85: User active đầu tháng có retain cao hơn user active cuối tháng không? 11/2025 | C85: Conditional Logic | D85: Moderate | E85: momovn-prod.BU_FI.PAYLATER_MAU_SEGMENT | F85: agent_id, date_trans, month_trans, is_retain_next_month | G85: date_trans là ngày giao dịch đầu tiên trong tháng. Đầu tháng: EXTRACT(DAY FROM date_trans) <= 15. Cuối tháng: EXTRACT(DAY FROM date_trans) > 15. So sánh SAFE_DIVIDE(SUM(is_retain_next_month), COUNT(DISTINCT agent_id)) giữa 2 nhóm | H85: SELECT CASE WHEN EXTRACT(DAY FROM date_trans) <= 15 THEN 'early_month' ELSE 'late_month' END AS activation_period, COUNT(DISTINCT agent_id) AS user_count, SAFE_DIVIDE(SUM(is_retain_next_month), COUNT(DISTINCT agent_id)) AS retention_rate FROM `momovn-prod.BU_FI.PAYLATER_MAU_SEGMENT` WHERE month_trans = '2025-11-01' GROUP BY 1 ORDER BY 1 | I85: 2 rows (early_month, late_month) với retention_rate activation_period user_count retention_rate early_month 1148487 0.868 late_month 229431 0.706 | J85: 2 | K85: eval | L85: DA_Team | M85: 2025-03-11 | N85: VTS
... A88: VTS015 | B88: User có đc tăng limit ở tháng 9/2025 thì tăng spending bn %? quan sat sau 3 tháng | C88: Window + Complex | D88: Complex | E88: momovn-prod.BU_FI.PAYLATER_MAU_SEGMENT | F88: agent_id, credit_limit, spending_vts, month_trans | G88: Xác định user được tăng limit: so sánh credit_limit tháng N vs tháng N-1 bằng LAG(). Nếu credit_limit tăng → so sánh spending_vts trước/sau. | H88: WITH user_monthly AS ( SELECT agent_id, month_trans, credit_limit, spending_vts FROM `momovn-prod.BU_FI.PAYLATER_MAU_SEGMENT` WHERE month_trans BETWEEN '2025-08-01' AND '2026-01-01' ), limit_increased AS ( SELECT a.agent_id, a.spending_vts AS spending_before, t1.spending_vts AS spending_t1, t2.spending_vts AS spending_t2, t3.spending_vts AS spending_t3 FROM user_monthly a JOIN user_monthly b ON a.agent_id = b.agent_id AND a.month_trans = '2025-08-01' AND b.month_trans = '2025-09-01' AND b.credit_limit > a.credit_limit LEFT JOIN user_monthly t1 ON a.agent_id = t1.agent_id AND t1.month_trans = '2025-10-01' LEFT JOIN user_monthly t2 ON a.agent_id = t2.agent_id AND t2.month_trans = '2025-11-01' LEFT JOIN user_monthly t3 ON a.agent_id = t3.agent_id AND t3.month_trans = '2025-12-01' ) SELECT COUNT(DISTINCT agent_id) AS users, SAFE_DIVIDE(AVG(spending_t1) - AVG(spending_before), AVG(spending_before)) AS spending_change_t1_oct, SAFE_DIVIDE(AVG(spending_t2) - AVG(spending_before), AVG(spending_before)) AS spending_change_t2_nov, SAFE_DIVIDE(AVG(spending_t3) - AVG(spending_before), AVG(spending_before)) AS spending_change_t3_dec FROM limit_increased | I88: 1 row; users spending_change_t1_oct spending_change_t2_nov spending_change_t3_dec 75503 0.39954237241173335 0.30689196073441921 0.360572284623127181 | J88: 1 | K88: eval | L88: DA_Team | M88: 2025-03-11 | N88: VTS
A89: VTS016 | B89: New MAU đang tăng từ gift nào? | C89: Multi-step | D89: Complex | E89: PAYLATER_MAU_SEGMENT | F89: agent_id, mau_type, first_trans_gift_list, first_trans_gift_type, month_trans | G89: first_trans_gift_list là REPEATED STRING (array gift IDs). Cần UNNEST để tách từng gift ID ra. New MAU = mau_type='1.New'. 'Đang tăng' = so sánh MoM. Agent phải biết dùng UNNEST cho REPEATED field trong BigQuery. COUNT DISTINCT agent_id theo gift_id, so sánh MoM xem gift nào đang drive new user tăng | H89: WITH new_gift AS ( SELECT month_trans, gift_id, COUNT(DISTINCT agent_id) AS new_users FROM `momovn-prod.BU_FI.PAYLATER_MAU_SEGMENT`, UNNEST(first_trans_gift_list) AS gift_id WHERE mau_type = '1.New' AND month_trans >= DATE_SUB((SELECT MAX(month_trans) FROM `momovn-prod.BU_FI.PAYLATER_MAU_SEGMENT`), INTERVAL 2 MONTH) GROUP BY 1, 2 ) SELECT *, LAG(new_users) OVER (PARTITION BY gift_id ORDER BY month_trans) AS prev_month_users, new_users - LAG(new_users) OVER (PARTITION BY gift_id ORDER BY month_trans) AS abs_change, SAFE_DIVIDE( new_users - LAG(new_users) OVER (PARTITION BY gift_id ORDER BY month_trans), LAG(new_users) OVER (PARTITION BY gift_id ORDER BY month_trans) ) AS mom_growth FROM new_gift QUALIFY LAG(new_users) OVER (PARTITION BY gift_id ORDER BY month_trans) IS NOT NULL ORDER BY abs_change DESC | I89: N rows, mỗi gift_id có MoM growth, sắp xếp theo abs_change giảm dần → gift nào drive tăng trưởng | J89: N | K89: eval | L89: DA_Team | M89: 2025-03-11 | N89: VTS
A90: VTS017 | B90: User churn bao lâu quay lại, có dùng promo k | C90: Multi-step | D90: Complex | E90: PAYLATER_MAU_SEGMENT | F90: agent_id, mau_type, first_trans_ispromo, is_using_promo, spending_vts, trans_vts, is_retain_next_month, month_trans | G90: User Reactive: mau_type = '3.Reactive'. Promo-driven: first_trans_ispromo = 1 (giao dịch đầu tiên quay lại có dùng promo). Organic return: first_trans_ispromo = 0. Cần kết hợp với thời gian absent (từ LAG). So sánh spending, trans, retention giữa 2 nhóm, tách theo absent duration | H90: WITH user_timeline AS ( SELECT agent_id, month_trans, mau_type, first_trans_ispromo, spending_vts, trans_vts, is_retain_next_month, LAG(month_trans) OVER (PARTITION BY agent_id ORDER BY month_trans) AS prev_active_month FROM `momovn-prod.BU_FI.PAYLATER_MAU_SEGMENT` ), reactive_detail AS ( SELECT *, DATE_DIFF(month_trans, prev_active_month, MONTH) AS months_absent, CASE WHEN first_trans_ispromo = 1 THEN 'promo_driven' ELSE 'organic_return' END AS return_type FROM user_timeline WHERE mau_type = '3.Reactive' AND prev_active_month IS NOT NULL AND month_trans BETWEEN '2025-10-01' AND '2026-01-01' ) SELECT CASE WHEN months_absent <= 3 THEN 'short_absence (1-2m)' WHEN months_absent <= 7 THEN 'medium_absence (3-6m)' ELSE 'long_absence (>6m)' END AS absence_group, return_type, COUNT(DISTINCT agent_id) AS users, AVG(spending_vts) AS avg_spending, AVG(trans_vts) AS avg_trans, SAFE_DIVIDE(SUM(is_retain_next_month), COUNT(DISTINCT agent_id)) AS retention_rate FROM reactive_detail GROUP BY 1, 2 ORDER BY 1, 2 | I90: ~6 rows (3 absence groups × 2 return types) với spending + retention | J90: 6 | K90: eval | L90: DA_Team | M90: 2025-03-11 | N90: VTS
A91: VTS018 | B91: Retention rate tháng này như nào? | C91: Multi-step | D91: Complex | E91: PAYLATER_MAU_SEGMENT, PAYLATER_ALL_TRANS | F91: agent_id, is_retain_next_month, month_trans, user_id, created_date, result_code, trans_type | G91: Agent cần hiểu 'tháng này như nào' = so sánh MTD (month-to-date). Retention rate tháng hiện tại chưa kết thúc → cần dùng proxy: tính % user tháng trước có giao dịch MTD tháng này (từ ALL_TRANS). So sánh running rate này với cùng thời điểm MTD tháng trước đó. Ví dụ: đang ngày 15 tháng 1/2026 → tính % user tháng 12 đã active trong 1-15/1 → compare với % user tháng 11 đã active trong 1-15/12. Nếu agent chỉ trả is_retain_next_month tháng trước = chưa đủ vì đó là full-month, không phải running rate | H91: -- Giả sử đang ở ngày 15/1/2026 -- Running retention tháng 1: % user tháng 12 đã có giao dịch trong 1-15/1 WITH dec_users AS ( SELECT DISTINCT agent_id FROM `momovn-prod.BU_FI.PAYLATER_MAU_SEGMENT` WHERE month_trans = '2025-12-01' ), jan_mtd_active AS ( SELECT DISTINCT user_id FROM `momovn-prod.BU_FI.PAYLATER_ALL_TRANS` WHERE result_code = 0 AND trans_type IN ('pay_pl','pay_ins','send_pl') AND created_date BETWEEN '2026-01-01' AND '2026-01-15' ), -- So sánh: running retention tháng 12 tại cùng thời điểm (1-15/12) nov_users AS ( SELECT DISTINCT agent_id FROM `momovn-prod.BU_FI.PAYLATER_MAU_SEGMENT` WHERE month_trans = '2025-11-01' ), dec_mtd_active AS ( SELECT DISTINCT user_id FROM `momovn-prod.BU_FI.PAYLATER_ALL_TRANS` WHERE result_code = 0 AND trans_type IN ('pay_pl','pay_ins','send_pl') AND created_date BETWEEN '2025-12-01' AND '2025-12-15' ) SELECT 'Jan 2026 MTD (1-15)' AS period, COUNT(DISTINCT d.agent_id) AS prev_month_users, COUNT(DISTINCT j.user_id) AS retained_mtd, SAFE_DIVIDE(COUNT(DISTINCT j.user_id), COUNT(DISTINCT d.agent_id)) AS running_retention FROM dec_users d LEFT JOIN jan_mtd_active j ON d.agent_id = j.user_id UNION ALL SELECT 'Dec 2025 MTD (1-15)', COUNT(DISTINCT n.agent_id), COUNT(DISTINCT dm.user_id), SAFE_DIVIDE(COUNT(DISTINCT dm.user_id), COUNT(DISTINCT n.agent_id)) FROM nov_users n LEFT JOIN dec_mtd_active dm ON n.agent_id = dm.user_id | I91: 2 rows: MTD running retention vs Last month running retention (apples-to-apples) | J91: 2 | K91: eval | L91: DA_Team | M91: 2025-03-11 | N91: VTS
A92: VTS019 | B92: Cho t xem tình hình VTS tháng rồi | C92: Ambiguous | D92: Ambiguous | E92: momovn-prod.BU_FI.PAYLATER_MAU_SEGMENT | F92: agent_id, spending_vts, trans_vts, mau_type, month_trans | G92: Câu hỏi mơ hồ: 'tình hình' không rõ muốn xem gì (MAU, spending, retention?). 'Tháng rồi' không rõ tháng nào. Agent đúng khi hỏi lại clarify | H92: -- Agent nên hỏi lại để clarify. -- Nếu assume: growth rate of MAU + growth rate of spending tháng + gap retention rate | I92: Agent nên hỏi lại. Nếu trả lời: 3 rows | J92: 3 | K92: ambiguous | L92: DA_Team | M92: 2025-03-11 | N92: VTS
A93: VTS020 | B93: Promo có hiệu quả không? | C93: Ambiguous | D93: Ambiguous | E93: momovn-prod.BU_FI.PAYLATER_MAU_SEGMENT | F93: is_using_promo, promo_amt, spending_vts, trans_vts, is_retain_next_month, agent_id, month_trans | G93: Mơ hồ nhiều chiều: 'hiệu quả' = tăng spending? tăng retention? tăng frequency? ROI? Timeframe nào? Agent nên hỏi lại: hiệu quả theo góc nhìn nào, khoảng thời gian nào | H93: -- Agent nên hỏi lại. -- Nếu assume: so sánh spending + retention giữa promo vs non-promo user tháng gần nhất, -- promo ở first trans hay trong tháng | I93: Agent nên hỏi lại. Nếu trả lời: 2 rows (promo vs non-promo) | J93: 2 | K93: ambiguous | L93: DA_Team | M93: 2025-03-11 | N93: VTS
A94: INS01 | B94: Có bao nhiêu user đã mua BHSK+ và đã từng gia hạn BHYT trước đó ? | C94: JOIN | D94: Ambiguous | E94: INS_CRITICAL_ILLNESS_V2, INS_PUBLIC_HEALTH | F94: trans_date, user_payment | G94: xSell các sản phẩm bảo hiểm trong lĩnh vực sức khỏe | I94: Agent nên hỏi các gói sản phẩm tương tác để segmentation 1 cách hiệu quả nhất | K94: ambiguous | L94: DA_Team | M94: 2025-03-11 | N94: InsurTech
A95: INS02 | B95: So sánh doanh thu ngày thường vs cuối tuần vs ngày lễ — thời điểm nào khách hàng có xu hướng mua bảo hiểm nhiều nhất? | C95: Date/Time | D95: Simple | E95: INS_CRITICAL_ILLNESS_V2, INS_PUBLIC_HEALTH, INS_DIS_ALL_TRANS, INS_COL_ALL_TRANS | F95: trans_date, user_payment, id, amount | G95: User payment behavior | I95: Agent nên hỏi sản phẩm tương tác để segmentation 1 cách hiệu quả nhất | K95: ambiguous | L95: DA_Team | M95: 2025-03-11 | N95: InsurTech
A96: INS03 | B96: Những giao dịch đã thanh toán thành công nhưng status hợp đồng không thành công — có bao nhiêu case như vậy và giá trị bao nhiêu | C96: Conditional Logic | D96: Simple | E96: INS_DIS_ALL_TRANS, INS_ACTIVE_POLICY | F96: user, user_payment, staus, billid | G96: Transaction detail | K96: ambiguous | L96: DA_Team | M96: 2025-03-11 | N96: InsurTech
A97: INS04 | B97: Users có traffic vào luồng sản phẩn và ra đơn với first-source/last source nào ? Tốn bao nhiêu phút ? | C97: Multi-step | D97: Complex | E97: EVENT_INSURTECH, INS_DIS_ALL_TRANS_REVENUE, INS_CRITICAL_ILLNESS_V2, INS_PUBLIC_HEALTH | F97: date, datetime, trans_datetime, user, product, time, service_name | G97: Transaction Journey | K97: eval | L97: DA_Team | M97: 2025-03-11 | N97: InsurTech
A98: INS05 | B98: User vào luồng sản phẩm bao lâu, từ đâu, tới end-point nào, rớt ở step nào | C98: Aggregation | D98: Moderate | E98: EVENT_INSURTECH | F98: date, datetime, user, momo_session_id_v2, key, value, event_name, service_name, screen_name, button_name, icon_name, component_name,block_name, tab_name, field_name | G98: Funnel Event Tracking | K98: eval | L98: DA_Team | M98: 2025-03-11 | N98: InsurTech
A99: INS06 | B99: Phân tích AiO các giao dịch bảo hiểm bundle của luồng OTA (Máy bay/Xe Khách) | C99: Conditional Logic | D99: Ambiguous | E99: FI_PI_BUNDLE_INS, INS_OTA_AIRLINE_BUNDLE, INS_DIS_ALL_TRANS_REVENUE | F99: trans_datetime, merchant, user_payment, ins_service, amount_bundle, amount_vexe, amount_ota, departure_time, arrival_time, days_to_trans, revenue | G99: Product Transactions Analysis | I99: Agent nên hỏi lại quy tắc sản phẩm, điểm khởi hành và nơi đến, thời gian chuyến đi, merchant, metrics muốn theo dõi | K99: ambiguous | L99: DA_Team | M99: 2025-03-11 | N99: InsurTech
A100: INS07 | B100: Lượng truy vấn, kết quả và tần suất truy vấn Bảo Hiểm Y Tế trên MoMo | C100: Date/Time | D100: Simple | E100: INS_PUBLIC_HEALTH_RAW | F100: created_datetime, request_id, user, billid, result_code | G100: Truy vấn thông tin thẻ bảo hiểm y tế | K100: ambiguous | L100: DA_Team | M100: 2025-03-11 | N100: InsurTech
A101: INS08 | B101: Phân bổ ticket size theo merchant, money_source, sản phẩm của các dịch vụ kênh bán bảo hiểm | C101: Ambiguous | D101: Simple | E101: INS_DIS_ALL_TRANS_REVENUE | F101: trans_date, merchant, sp, sp_detail, money_source, amount/id | G101: Transaction detail | K101: ambiguous | L101: DA_Team | M101: 2025-03-11 | N101: InsurTech
A102: INS09 | B102: Số new/retain của từng sản phẩm ở từng khoảng thời gian khác nhau | C102: Ambiguous | D102: Simple | E102: INS_DIS_ALL_TRANS_REVENUE / INS_PUBLIC_HEALTH / INS_CRITICAL_ILLNESS_V2 | F102: trans_date, sp, sp_detail, user_payment | G102: User retention | K102: ambiguous | L102: DA_Team | M102: 2025-03-11 | N102: InsurTech
A103: INS10 | B103: Tổng số lượng giao dịch organic và có sử dụng voucher mỗi ngày | C103: Ambiguous | D103: Simple | E103: INS_DIS_ALL_TRANS_REVENUE | F103: trans_date, id , typeid | G103: Transaction detail | I103: Mỗi ngày từ 8-10% | K103: ambiguous | L103: DA_Team | M103: 2025-03-11 | N103: InsurTech
A104: INS11 | B104: Tỷ trọng loại hình giao dịch mỗi ngày | C104: Ambiguous | D104: Simple | E104: INS_DIS_ALL_TRANS_REVENUE | F104: trans_date, payment_channel, id | G104: Transaction detail | I104: Mỗi ngày tầm 3-4000 giao dịch, 2-30 giao dịch auto debit/web | K104: ambiguous | L104: DA_Team | M104: 2025-03-11 | N104: InsurTech
A105: INS12 | B105: Tỷ trọng thanh toán hộ của luồng Thu Hộ Bảo Hiểm Nhân Thọ | C105: Ambiguous | D105: Simple | E105: INS_COL_ALL_TRANS | F105: trans_date, user_payment, id, billid, proxy_purchase | G105: Transaction detail | I105: Tỉ lệ nearly the same, 51-49 | K105: ambiguous | L105: DA_Team | M105: 2025-03-11 | N105: InsurTech
A106: INS13 | B106: Tỷ trọng PAYMENT/REPAYMENT của BHYT mỗi ngày thế nào | C106: Ambiguous | D106: Simple | E106: INS_PUBLIC_HEALTH | F106: trans_date, id, flag_repayment | G106: Transaction detail | I106: Mỗi ngày 3-400 đơn PAYMENT, 80-100 REPAYMENT | K106: ambiguous | L106: DA_Team | M106: 2025-03-11 | N106: InsurTech
A117: BANK001 | B117: Thống kê số lượng giao dịch rút tiền theo từng bank_code trong tháng 12/2025 | C117: Aggregation | D117: Simple | E117: BANK_CO | F117: bank_code, date | G117: Filter date BETWEEN '2025-12-01' AND '2025-12-31'. GROUP BY bank_code ORDER BY count DESC. | I117: 33 rows
A118: BANK002 | B118: Liệt kê tất cả giao dịch rút tiền thành công có amount > 5,000,000 trong ngày 2025-12-01 | C118: Conditional Logic | D118: Simple | E118: BANK_CO | F118: status_final, amount, date, tid, user, bank_code | G118: status_final = 2 AND amount > 5000000 AND date = '2025-12-01'. | I118: 19,717 rows
A119: BANK003 | B119: Tổng số tiền chuyển tiền W2B trong tháng 01/2026, chỉ tính giao dịch thành công | C119: Aggregation | D119: Simple | E119: BANK_W2B_RAW | F119: amount, bank_code, status_final | G119: SUM(amount) WHERE bank_code not in ('MoMo BE') and status_final = 2 AND date between '2026-01-01' and '2026-01-31' | I119: 26060872518689
A120: BANK004 | B120: Tỷ lệ phần trăm giao dịch W2B theo từng channel (VietQR vs Other) trong toàn bộ dataset | C120: Aggregation | D120: Simple | E120: BANK_W2B_RAW | F120: channel | G120: COUNT(*) GROUP BY channel. Tính % = count / total * 100.
...

Sheet Agent_A_Results
A1: ID | B1: Question (ref) | C1: Generated SQL | D1: Execution Status | E1: Query Result (summary) | F1: Result Row Count | G1: Execution Time (ms) | H1: Tables Used | I1: Columns Used | J1: Agent Confidence Score | K1: Retries / Self-corrections | L1: Error Message (if any) | M1: Notes
A2: =#REF! -> #REF! | B2: =#REF! -> #REF!
A3: =#REF! -> #REF! | B3: =#REF! -> #REF!
A4: =#REF! -> #REF! | B4: =#REF! -> #REF!
A5: =#REF! -> #REF! | B5: =#REF! -> #REF!
A6: =#REF! -> #REF! | B6: =#REF! -> #REF!
A7: =Gold_Dataset!A2 -> Q1 | B7: =Gold_Dataset!B2 -> Trong 30 ngay truoc giai ngan, user thuong access bao nhieu lan? Phan bo theo bucket.
A8: =Gold_Dataset!A3 -> Q2 | B8: =Gold_Dataset!B3 -> Tính last touchpoint user giải ngân tháng 2
A9: =Gold_Dataset!A4 -> Q3 | B9: =Gold_Dataset!B4 -> Tinh last touchpoint ma user giai ngan Vay Nhanh thang 2 chia theo final segment user
A10: =Gold_Dataset!A5 -> Q4 | B10: =Gold_Dataset!B5 -> So sanh so lan access va so ngay access truoc giai ngan giua NEWLOAN, RELOAN, REPEATED?
A11: =Gold_Dataset!A6 -> Q5 | B11: =Gold_Dataset!B6 -> Cohort liquidation theo thang: ty le reloan trong 30/60/90 ngay sau khi tat toan?
A12: =Gold_Dataset!A7 -> Q6 | B12: =Gold_Dataset!B7 -> Ti le duoc duyet (disburse/submit) chia theo segment, lender, credit score range, thang (Jul 2025 - Feb 2026)?
A13: =Gold_Dataset!A8 -> Q7 | B13: =Gold_Dataset!B8 -> Tong gia tri giai ngan va gia tri trung binh moi khoan Vay Nhanh thang 2/2026?
A14: =Gold_Dataset!A9 -> Q8 | B14: =Gold_Dataset!B9 -> So sanh giai ngan Vay Nhanh thang 1 va thang 2/2026?
A15: =Gold_Dataset!A10 -> Q9 | B15: =Gold_Dataset!B10 -> Phan bo so lan giai ngan cua user Vay Nhanh thang 2/2026?
A16: =Gold_Dataset!A11 -> Q10 | B16: =Gold_Dataset!B11 -> Top 10 ly do tu choi don vay Vay Nhanh thang 2/2026?
A17: =Gold_Dataset!A12 -> Q11 | B17: =Gold_Dataset!B12 -> So luong user duy nhat giai ngan Vay Nhanh thang 2/2026 va trung binh moi user vay bao nhieu khoan?
A18: =Gold_Dataset!A13 -> Q12 | B18: =Gold_Dataset!B13 -> Phan bo ky han (tenor) cac khoan vay Vay Nhanh thang 2/2026?
... A25: =Gold_Dataset!A20 -> Q19 | B25: =Gold_Dataset!B20 -> DPD30 cac khoan vay theo vintage va lender (chi dung LOAN_INFO, khong dung bang vintage)?
A26: =#REF! -> #REF! | B26: =#REF! -> #REF!
A27: =#REF! -> #REF! | B27: =#REF! -> #REF!
A28: =#REF! -> #REF! | B28: =#REF! -> #REF!
A29: =#REF! -> #REF! | B29: =#REF! -> #REF!
A30: =#REF! -> #REF! | B30: =#REF! -> #REF!
A31: =#REF! -> #REF! | B31: =#REF! -> #REF!
A32: =#REF! -> #REF! | B32: =#REF! -> #REF!
A33: =Gold_Dataset!A21 | B33: =Gold_Dataset!B21
A34: =Gold_Dataset!A22 -> TTT001 | B34: =Gold_Dataset!B22 -> AUM tháng 1 bao nhiêu?
A35: =Gold_Dataset!A23 -> TTT002 | B35: =Gold_Dataset!B23 -> Có bao nhiêu người đang dùng TTT vậy?
A36: =Gold_Dataset!A24 -> TTT003 | B36: =Gold_Dataset!B24 -> Tháng rồi người ta gửi vô TTT tổng bao nhiêu tiền?
A37: =Gold_Dataset!A25 -> TTT004 | B37: =Gold_Dataset!B25 -> MoMo đang trả lãi cho TTT mỗi tháng bao nhiêu vậy? Có đáng lo không?
A38: =Gold_Dataset!A26 -> TTT005 | B38: =Gold_Dataset!B26 -> Tháng 1 so với tháng 2 thì TTT đang lên hay xuống?
A39: =Gold_Dataset!A27 -> TTT006 | B39: =Gold_Dataset!B27 -> Vùng nào đang dùng TTT nhiều nhất? Top 5 cho t
A40: =Gold_Dataset!A28 -> TTT007 | B40: =Gold_Dataset!B28 -> Tiền rút ra nhiều hơn tiền gửi vào không? Tháng 2
A41: =Gold_Dataset!A29 -> TTT008 | B41: =Gold_Dataset!B29 -> Nhóm tuổi nào gửi tiết kiệm TTT nhiều nhất?
A42: =Gold_Dataset!A30 -> TTT009 | B42: =Gold_Dataset!B30 -> Bao nhiêu % user TTT đang dùng Túi+?
A43: =Gold_Dataset!A31 -> TTT010 | B43: =Gold_Dataset!B31 -> Người dùng rút tiền từ TTT chủ yếu qua kênh nào?
A44: =Gold_Dataset!A32 -> TTT011 | B44: =Gold_Dataset!B32 -> User mới tháng này so tháng trước tăng hay giảm? Giảm bao nhiêu?
... A59: =Gold_Dataset!A47 -> TTT026 | B59: =Gold_Dataset!B47 -> so du trung binh cua user ttt la bao nhieu?
A60: =Gold_Dataset!A48 -> TTT027 | B60: =Gold_Dataset!B48 -> tui+ dang co bao nhieu nguoi? tang hay giam so thang truoc? | C60: SELECT t1.IS_MP, COUNT(DISTINCT (cast(REGEXP_EXTRACT(t1.USER_ID, r'\d+') as string))) AS total_plus_users FROM momovn-prod.BU_FI.mart_ttt_daily_user_record AS t1 WHERE t1.GRASS_DATE BETWEEN '2026-02-01' AND '2026-02-28' AND t1.PLUS_TYPE NOT IN ('0.Churn', 'Non TTT+') GROUP BY t1.IS_MP | D60: SUCCESS | F60: 2 | H60: momovn-prod.BU_FI.mart_ttt_daily_user_record | I60: IS_MP,USER_ID
A61: =Gold_Dataset!A49 -> TTT028 | B61: =Gold_Dataset!B49 -> user nao dang giu nhieu tien nhat trong ttt? top 10
A62: =Gold_Dataset!A50 -> TTT029 | B62: =Gold_Dataset!B50 -> tai sao thang nay user nap nhieu tien hon binh thuong?
A63: =Gold_Dataset!A51 -> TTT030 | B63: =Gold_Dataset!B51 -> user tui+ rut tien ve ngan hang (napas) thang roi bao nhieu? co tang khong?
A64: =Gold_Dataset!A52 -> TTT031 | B64: =Gold_Dataset!B52 -> tinh hinh kinh doanh ttt 6 thang qua
A65: =Gold_Dataset!A53 -> TTT032 | B65: =Gold_Dataset!B53 -> nhom so du nao dong gop nhieu nhat vao tong AUM?
A66: =Gold_Dataset!A54 -> TTT033 | B66: =Gold_Dataset!B54 -> user tui+ duoc cashback bao nhieu roi? co dang khong?
A67: =Gold_Dataset!A55 -> TTT034 | B67: =Gold_Dataset!B55 -> user nap tu dong (auto invest) co bao nhieu nguoi? nap trung binh bao nhieu?
A68: =Gold_Dataset!A56 -> TTT035 | B68: =Gold_Dataset!B56 -> user co so du tren 50 trieu chiem bao nhieu % tong? ho la ai?
A69: =Gold_Dataset!A57 -> TTT036 | B69: =Gold_Dataset!B57 -> cuoi tuan user co rut tien nhieu hon ngay thuong khong?
A70: =Gold_Dataset!A58 -> TTT037 | B70: =Gold_Dataset!B58 -> user ttt duoc nhan lai bao nhieu 1 ngay? phan bo theo nhom so du ra sao?
A71: =Gold_Dataset!A59 -> TTT038 | B71: =Gold_Dataset!B59 -> user reactive thang 2 quay lai voi bao nhieu tien? co giu lai duoc khong?
A72: =Gold_Dataset!A60 -> TTT039 | B72: =Gold_Dataset!B60 -> user nap qua p2p vs nap thuong, nhom nao nhieu hon?
... A233: =Gold_Dataset!A221 | B233: =Gold_Dataset!B221

Sheet Evaluation_Scores
A1: ID | B1: Difficulty | C1: Category | D1: A: Valid SQL | E1: A: Exact Result Match | F1: A: Partial Credit | G1: A: Schema Linking | H1: A: Efficiency Score | I1: B: Valid SQL | J1: B: Exact Result Match | K1: B: Partial Credit | L1: B: Schema Linking | M1: B: Efficiency Score | N1: Winner (EX) | O1: Winner (Overall) | P1: LLM Judge Score | Q1: Notes
A2: =#REF! -> #REF! | B2: =#REF! -> #REF! | C2: =#REF! -> #REF! | D2: =IF(Agent_A_Results!D2="SUCCESS",1,0) -> 0 | E2: 1 | I2: =IF(Agent_B_Results!D2="SUCCESS",1,0) -> 0 | J2: 0 | N2: =IF(AND(E2="",J2=""),"",IF(E2>J2,"A",IF(J2>E2,"B","Tie"))) -> A | O2: A
A3: =#REF! -> #REF! | B3: =#REF! -> #REF! | C3: =#REF! -> #REF! | D3: =IF(Agent_A_Results!D3="SUCCESS",1,0) -> 0 | I3: =IF(Agent_B_Results!D3="SUCCESS",1,0) -> 0 | N3: =IF(AND(E3="",J3=""),"",IF(E3>J3,"A",IF(J3>E3,"B","Tie")))
A4: =#REF! -> #REF! | B4: =#REF! -> #REF! | C4: =#REF! -> #REF! | D4: =IF(Agent_A_Results!D4="SUCCESS",1,0) -> 0 | I4: =IF(Agent_B_Results!D4="SUCCESS",1,0) -> 0 | N4: =IF(AND(E4="",J4=""),"",IF(E4>J4,"A",IF(J4>E4,"B","Tie")))
A5: =#REF! -> #REF! | B5: =#REF! -> #REF! | C5: =#REF! -> #REF! | D5: =IF(Agent_A_Results!D5="SUCCESS",1,0) -> 0 | I5: =IF(Agent_B_Results!D5="SUCCESS",1,0) -> 0 | N5: =IF(AND(E5="",J5=""),"",IF(E5>J5,"A",IF(J5>E5,"B","Tie")))
A6: =#REF! -> #REF! | B6: =#REF! -> #REF! | C6: =#REF! -> #REF! | D6: =IF(Agent_A_Results!D6="SUCCESS",1,0) -> 0 | I6: =IF(Agent_B_Results!D6="SUCCESS",1,0) -> 0 | N6: =IF(AND(E6="",J6=""),"",IF(E6>J6,"A",IF(J6>E6,"B","Tie")))
A7: =Gold_Dataset!A2 -> Q1 | B7: =Gold_Dataset!D2 -> Moderate | C7: =Gold_Dataset!C2 -> Subquery | D7: =IF(Agent_A_Results!D7="SUCCESS",1,0) -> 0 | I7: =IF(Agent_B_Results!D7="SUCCESS",1,0) -> 0 | N7: =IF(AND(E7="",J7=""),"",IF(E7>J7,"A",IF(J7>E7,"B","Tie")))
A8: =Gold_Dataset!A3 -> Q2 | B8: =Gold_Dataset!D3 -> Complex | C8: =Gold_Dataset!C3 -> Window + Complex | D8: =IF(Agent_A_Results!D8="SUCCESS",1,0) -> 0 | I8: =IF(Agent_B_Results!D8="SUCCESS",1,0) -> 0 | N8: =IF(AND(E8="",J8=""),"",IF(E8>J8,"A",IF(J8>E8,"B","Tie")))
A9: =Gold_Dataset!A4 -> Q3 | B9: =Gold_Dataset!D4 -> Complex | C9: =Gold_Dataset!C4 -> Window + Complex | D9: =IF(Agent_A_Results!D9="SUCCESS",1,0) -> 0 | I9: =IF(Agent_B_Results!D9="SUCCESS",1,0) -> 0 | N9: =IF(AND(E9="",J9=""),"",IF(E9>J9,"A",IF(J9>E9,"B","Tie")))
A10: =Gold_Dataset!A5 -> Q4 | B10: =Gold_Dataset!D5 -> Moderate | C10: =Gold_Dataset!C5 -> JOIN | D10: =IF(Agent_A_Results!D10="SUCCESS",1,0) -> 0 | I10: =IF(Agent_B_Results!D10="SUCCESS",1,0) -> 0 | N10: =IF(AND(E10="",J10=""),"",IF(E10>J10,"A",IF(J10>E10,"B","Tie")))
A11: =Gold_Dataset!A6 -> Q5 | B11: =Gold_Dataset!D6 -> Moderate | C11: =Gold_Dataset!C6 -> Multi-step | D11: =IF(Agent_A_Results!D11="SUCCESS",1,0) -> 0 | I11: =IF(Agent_B_Results!D11="SUCCESS",1,0) -> 0 | N11: =IF(AND(E11="",J11=""),"",IF(E11>J11,"A",IF(J11>E11,"B","Tie")))
A12: =Gold_Dataset!A7 -> Q6 | B12: =Gold_Dataset!D7 -> Moderate | C12: =Gold_Dataset!C7 -> Subquery | D12: =IF(Agent_A_Results!D12="SUCCESS",1,0) -> 0 | I12: =IF(Agent_B_Results!D12="SUCCESS",1,0) -> 0 | N12: =IF(AND(E12="",J12=""),"",IF(E12>J12,"A",IF(J12>E12,"B","Tie")))
A13: =Gold_Dataset!A8 -> Q7 | B13: =Gold_Dataset!D8 -> Simple | C13: =Gold_Dataset!C8 -> Aggregation | D13: =IF(Agent_A_Results!D13="SUCCESS",1,0) -> 0 | I13: =IF(Agent_B_Results!D13="SUCCESS",1,0) -> 0 | N13: =IF(AND(E13="",J13=""),"",IF(E13>J13,"A",IF(J13>E13,"B","Tie")))
A14: =Gold_Dataset!A9 -> Q8 | B14: =Gold_Dataset!D9 -> Simple | C14: =Gold_Dataset!C9 -> Aggregation | D14: =IF(Agent_A_Results!D14="SUCCESS",1,0) -> 0 | I14: =IF(Agent_B_Results!D14="SUCCESS",1,0) -> 0 | N14: =IF(AND(E14="",J14=""),"",IF(E14>J14,"A",IF(J14>E14,"B","Tie")))
A15: =Gold_Dataset!A10 -> Q9 | B15: =Gold_Dataset!D10 -> Simple | C15: =Gold_Dataset!C10 -> Aggregation | D15: =IF(Agent_A_Results!D15="SUCCESS",1,0) -> 0 | I15: =IF(Agent_B_Results!D15="SUCCESS",1,0) -> 0 | N15: =IF(AND(E15="",J15=""),"",IF(E15>J15,"A",IF(J15>E15,"B","Tie")))
A16: =Gold_Dataset!A11 -> Q10 | B16: =Gold_Dataset!D11 -> Simple | C16: =Gold_Dataset!C11 -> Aggregation | D16: =IF(Agent_A_Results!D16="SUCCESS",1,0) -> 0 | I16: =IF(Agent_B_Results!D16="SUCCESS",1,0) -> 0 | N16: =IF(AND(E16="",J16=""),"",IF(E16>J16,"A",IF(J16>E16,"B","Tie")))
A17: =Gold_Dataset!A12 -> Q11 | B17: =Gold_Dataset!D12 -> Simple | C17: =Gold_Dataset!C12 -> Aggregation | D17: =IF(Agent_A_Results!D17="SUCCESS",1,0) -> 0 | I17: =IF(Agent_B_Results!D17="SUCCESS",1,0) -> 0 | N17: =IF(AND(E17="",J17=""),"",IF(E17>J17,"A",IF(J17>E17,"B","Tie")))
A18: =Gold_Dataset!A13 -> Q12 | B18: =Gold_Dataset!D13 -> Simple | C18: =Gold_Dataset!C13 -> Aggregation | D18: =IF(Agent_A_Results!D18="SUCCESS",1,0) -> 0 | I18: =IF(Agent_B_Results!D18="SUCCESS",1,0) -> 0 | N18: =IF(AND(E18="",J18=""),"",IF(E18>J18,"A",IF(J18>E18,"B","Tie")))
... A25: =Gold_Dataset!A20 -> Q19 | B25: =Gold_Dataset!D20 -> Ambiguous | C25: =Gold_Dataset!C20 -> Ambiguous | D25: =IF(Agent_A_Results!D25="SUCCESS",1,0) -> 0 | I25: =IF(Agent_B_Results!D25="SUCCESS",1,0) -> 0 | N25: =IF(AND(E25="",J25=""),"",IF(E25>J25,"A",IF(J25>E25,"B","Tie")))
A26: =#REF! -> #REF! | B26: =#REF! -> #REF! | C26: =#REF! -> #REF! | D26: =IF(Agent_A_Results!D26="SUCCESS",1,0) -> 0 | I26: =IF(Agent_B_Results!D26="SUCCESS",1,0) -> 0 | N26: =IF(AND(E26="",J26=""),"",IF(E26>J26,"A",IF(J26>E26,"B","Tie")))
A27: =#REF! -> #REF! | B27: =#REF! -> #REF! | C27: =#REF! -> #REF! | D27: =IF(Agent_A_Results!D27="SUCCESS",1,0) -> 0 | I27: =IF(Agent_B_Results!D27="SUCCESS",1,0) -> 0 | N27: =IF(AND(E27="",J27=""),"",IF(E27>J27,"A",IF(J27>E27,"B","Tie")))
A28: =#REF! -> #REF! | B28: =#REF! -> #REF! | C28: =#REF! -> #REF! | D28: =IF(Agent_A_Results!D28="SUCCESS",1,0) -> 0 | I28: =IF(Agent_B_Results!D28="SUCCESS",1,0) -> 0 | N28: =IF(AND(E28="",J28=""),"",IF(E28>J28,"A",IF(J28>E28,"B","Tie")))
A29: =#REF! -> #REF! | B29: =#REF! -> #REF! | C29: =#REF! -> #REF! | D29: =IF(Agent_A_Results!D29="SUCCESS",1,0) -> 0 | I29: =IF(Agent_B_Results!D29="SUCCESS",1,0) -> 0 | N29: =IF(AND(E29="",J29=""),"",IF(E29>J29,"A",IF(J29>E29,"B","Tie")))
A30: =#REF! -> #REF! | B30: =#REF! -> #REF! | C30: =#REF! -> #REF! | D30: =IF(Agent_A_Results!D30="SUCCESS",1,0) -> 0 | I30: =IF(Agent_B_Results!D30="SUCCESS",1,0) -> 0 | N30: =IF(AND(E30="",J30=""),"",IF(E30>J30,"A",IF(J30>E30,"B","Tie")))
A31: =#REF! -> #REF! | B31: =#REF! -> #REF! | C31: =#REF! -> #REF! | D31: =IF(Agent_A_Results!D31="SUCCESS",1,0) -> 0 | I31: =IF(Agent_B_Results!D31="SUCCESS",1,0) -> 0 | N31: =IF(AND(E31="",J31=""),"",IF(E31>J31,"A",IF(J31>E31,"B","Tie")))
A32: =#REF! -> #REF! | B32: =#REF! -> #REF! | C32: =#REF! -> #REF! | D32: =IF(Agent_A_Results!D32="SUCCESS",1,0) -> 0 | I32: =IF(Agent_B_Results!D32="SUCCESS",1,0) -> 0 | N32: =IF(AND(E32="",J32=""),"",IF(E32>J32,"A",IF(J32>E32,"B","Tie")))
A33: =Gold_Dataset!A21 | B33: =Gold_Dataset!D21 | C33: =Gold_Dataset!C21 | D33: =IF(Agent_A_Results!D33="SUCCESS",1,0) -> 0 | I33: =IF(Agent_B_Results!D33="SUCCESS",1,0) -> 0 | N33: =IF(AND(E33="",J33=""),"",IF(E33>J33,"A",IF(J33>E33,"B","Tie")))
A34: =Gold_Dataset!A22 -> TTT001 | B34: =Gold_Dataset!D22 -> Simple | C34: =Gold_Dataset!C22 -> Aggregation | D34: =IF(Agent_A_Results!D34="SUCCESS",1,0) -> 0 | I34: =IF(Agent_B_Results!D34="SUCCESS",1,0) -> 0 | N34: =IF(AND(E34="",J34=""),"",IF(E34>J34,"A",IF(J34>E34,"B","Tie")))
A35: =Gold_Dataset!A23 -> TTT002 | B35: =Gold_Dataset!D23 -> Ambiguous | C35: =Gold_Dataset!C23 -> Ambiguous | D35: =IF(Agent_A_Results!D35="SUCCESS",1,0) -> 0 | I35: =IF(Agent_B_Results!D35="SUCCESS",1,0) -> 0 | N35: =IF(AND(E35="",J35=""),"",IF(E35>J35,"A",IF(J35>E35,"B","Tie")))
A36: =Gold_Dataset!A24 -> TTT003 | B36: =Gold_Dataset!D24 -> Moderate | C36: =Gold_Dataset!C24 -> Aggregation | D36: =IF(Agent_A_Results!D36="SUCCESS",1,0) -> 0 | I36: =IF(Agent_B_Results!D36="SUCCESS",1,0) -> 0 | N36: =IF(AND(E36="",J36=""),"",IF(E36>J36,"A",IF(J36>E36,"B","Tie")))
A37: =Gold_Dataset!A25 -> TTT004 | B37: =Gold_Dataset!D25 -> Simple | C37: =Gold_Dataset!C25 -> Aggregation | D37: =IF(Agent_A_Results!D37="SUCCESS",1,0) -> 0 | I37: =IF(Agent_B_Results!D37="SUCCESS",1,0) -> 0 | N37: =IF(AND(E37="",J37=""),"",IF(E37>J37,"A",IF(J37>E37,"B","Tie")))
A38: =Gold_Dataset!A26 -> TTT005 | B38: =Gold_Dataset!D26 -> Ambiguous | C38: =Gold_Dataset!C26 -> Multi-step | D38: =IF(Agent_A_Results!D38="SUCCESS",1,0) -> 0 | I38: =IF(Agent_B_Results!D38="SUCCESS",1,0) -> 0 | N38: =IF(AND(E38="",J38=""),"",IF(E38>J38,"A",IF(J38>E38,"B","Tie")))
A39: =Gold_Dataset!A27 -> TTT006 | B39: =Gold_Dataset!D27 -> Moderate | C39: =Gold_Dataset!C27 -> Ranking + Filter | D39: =IF(Agent_A_Results!D39="SUCCESS",1,0) -> 0 | I39: =IF(Agent_B_Results!D39="SUCCESS",1,0) -> 0 | N39: =IF(AND(E39="",J39=""),"",IF(E39>J39,"A",IF(J39>E39,"B","Tie")))
A40: =Gold_Dataset!A28 -> TTT007 | B40: =Gold_Dataset!D28 -> Complex | C40: =Gold_Dataset!C28 -> Multi-step | D40: =IF(Agent_A_Results!D40="SUCCESS",1,0) -> 0 | I40: =IF(Agent_B_Results!D40="SUCCESS",1,0) -> 0 | N40: =IF(AND(E40="",J40=""),"",IF(E40>J40,"A",IF(J40>E40,"B","Tie")))
A41: =Gold_Dataset!A29 -> TTT008 | B41: =Gold_Dataset!D29 -> Moderate | C41: =Gold_Dataset!C29 -> Aggregation | D41: =IF(Agent_A_Results!D41="SUCCESS",1,0) -> 0 | I41: =IF(Agent_B_Results!D41="SUCCESS",1,0) -> 0 | N41: =IF(AND(E41="",J41=""),"",IF(E41>J41,"A",IF(J41>E41,"B","Tie")))
A42: =Gold_Dataset!A30 -> TTT009 | B42: =Gold_Dataset!D30 -> Moderate | C42: =Gold_Dataset!C30 -> Conditional Logic | D42: =IF(Agent_A_Results!D42="SUCCESS",1,0) -> 0 | I42: =IF(Agent_B_Results!D42="SUCCESS",1,0) -> 0 | N42: =IF(AND(E42="",J42=""),"",IF(E42>J42,"A",IF(J42>E42,"B","Tie")))
A43: =Gold_Dataset!A31 -> TTT010 | B43: =Gold_Dataset!D31 -> Moderate | C43: =Gold_Dataset!C31 -> Ranking + Filter | D43: =IF(Agent_A_Results!D43="SUCCESS",1,0) -> 0 | I43: =IF(Agent_B_Results!D43="SUCCESS",1,0) -> 0 | N43: =IF(AND(E43="",J43=""),"",IF(E43>J43,"A",IF(J43>E43,"B","Tie")))
A44: =Gold_Dataset!A32 -> TTT011 | B44: =Gold_Dataset!D32 -> Moderate | C44: =Gold_Dataset!C32 -> Date/Time | D44: =IF(Agent_A_Results!D44="SUCCESS",1,0) -> 0 | I44: =IF(Agent_B_Results!D44="SUCCESS",1,0) -> 0 | N44: =IF(AND(E44="",J44=""),"",IF(E44>J44,"A",IF(J44>E44,"B","Tie")))
... A54: =Gold_Dataset!A42 -> TTT021 | B54: =Gold_Dataset!D42 -> Complex | C54: =Gold_Dataset!C42 -> Window + Complex | D54: =IF(Agent_A_Results!D54="SUCCESS",1,0) -> 0 | I54: =IF(Agent_B_Results!D54="SUCCESS",1,0) -> 0 | N54: =IF(AND(E54="",J54=""),"",IF(E54>J54,"A",IF(J54>E54,"B","Tie")))

Sheet Agent_B_Results
A1: ID | B1: Question (ref) | C1: Generated SQL | D1: Execution Status | E1: Query Result (summary) | F1: Result Row Count | G1: Execution Time (ms) | H1: Tables Used | I1: Columns Used | J1: Agent Confidence Score | K1: Retries / Self-corrections | L1: Error Message (if any) | M1: Notes
A2: =#REF! -> #REF! | B2: =#REF! -> #REF!
A3: =#REF! -> #REF! | B3: =#REF! -> #REF!
A4: =#REF! -> #REF! | B4: =#REF! -> #REF!
A5: =#REF! -> #REF! | B5: =#REF! -> #REF!
A6: =#REF! -> #REF! | B6: =#REF! -> #REF!
A7: =Gold_Dataset!A2 -> Q1 | B7: =Gold_Dataset!B2 -> Trong 30 ngay truoc giai ngan, user thuong access bao nhieu lan? Phan bo theo bucket.
A8: =Gold_Dataset!A3 -> Q2 | B8: =Gold_Dataset!B3 -> Tính last touchpoint user giải ngân tháng 2
A9: =Gold_Dataset!A4 -> Q3 | B9: =Gold_Dataset!B4 -> Tinh last touchpoint ma user giai ngan Vay Nhanh thang 2 chia theo final segment user
A10: =Gold_Dataset!A5 -> Q4 | B10: =Gold_Dataset!B5 -> So sanh so lan access va so ngay access truoc giai ngan giua NEWLOAN, RELOAN, REPEATED?
A11: =Gold_Dataset!A6 -> Q5 | B11: =Gold_Dataset!B6 -> Cohort liquidation theo thang: ty le reloan trong 30/60/90 ngay sau khi tat toan?
A12: =Gold_Dataset!A7 -> Q6 | B12: =Gold_Dataset!B7 -> Ti le duoc duyet (disburse/submit) chia theo segment, lender, credit score range, thang (Jul 2025 - Feb 2026)?
A13: =Gold_Dataset!A8 -> Q7 | B13: =Gold_Dataset!B8 -> Tong gia tri giai ngan va gia tri trung binh moi khoan Vay Nhanh thang 2/2026?
A14: =Gold_Dataset!A9 -> Q8 | B14: =Gold_Dataset!B9 -> So sanh giai ngan Vay Nhanh thang 1 va thang 2/2026?
A15: =Gold_Dataset!A10 -> Q9 | B15: =Gold_Dataset!B10 -> Phan bo so lan giai ngan cua user Vay Nhanh thang 2/2026?
A16: =Gold_Dataset!A11 -> Q10 | B16: =Gold_Dataset!B11 -> Top 10 ly do tu choi don vay Vay Nhanh thang 2/2026?
A17: =Gold_Dataset!A12 -> Q11 | B17: =Gold_Dataset!B12 -> So luong user duy nhat giai ngan Vay Nhanh thang 2/2026 va trung binh moi user vay bao nhieu khoan?
A18: =Gold_Dataset!A13 -> Q12 | B18: =Gold_Dataset!B13 -> Phan bo ky han (tenor) cac khoan vay Vay Nhanh thang 2/2026?
... A25: =Gold_Dataset!A20 -> Q19 | B25: =Gold_Dataset!B20 -> DPD30 cac khoan vay theo vintage va lender (chi dung LOAN_INFO, khong dung bang vintage)?
A26: =#REF! -> #REF! | B26: =#REF! -> #REF!
A27: =#REF! -> #REF! | B27: =#REF! -> #REF!
A28: =#REF! -> #REF! | B28: =#REF! -> #REF!
A29: =#REF! -> #REF! | B29: =#REF! -> #REF!
A30: =#REF! -> #REF! | B30: =#REF! -> #REF!
A31: =#REF! -> #REF! | B31: =#REF! -> #REF!
A32: =#REF! -> #REF! | B32: =#REF! -> #REF!
A33: =Gold_Dataset!A21 | B33: =Gold_Dataset!B21
A34: =Gold_Dataset!A22 -> TTT001 | B34: =Gold_Dataset!B22 -> AUM tháng 1 bao nhiêu?
A35: =Gold_Dataset!A23 -> TTT002 | B35: =Gold_Dataset!B23 -> Có bao nhiêu người đang dùng TTT vậy?
A36: =Gold_Dataset!A24 -> TTT003 | B36: =Gold_Dataset!B24 -> Tháng rồi người ta gửi vô TTT tổng bao nhiêu tiền?
A37: =Gold_Dataset!A25 -> TTT004 | B37: =Gold_Dataset!B25 -> MoMo đang trả lãi cho TTT mỗi tháng bao nhiêu vậy? Có đáng lo không?
A38: =Gold_Dataset!A26 -> TTT005 | B38: =Gold_Dataset!B26 -> Tháng 1 so với tháng 2 thì TTT đang lên hay xuống?
A39: =Gold_Dataset!A27 -> TTT006 | B39: =Gold_Dataset!B27 -> Vùng nào đang dùng TTT nhiều nhất? Top 5 cho t
A40: =Gold_Dataset!A28 -> TTT007 | B40: =Gold_Dataset!B28 -> Tiền rút ra nhiều hơn tiền gửi vào không? Tháng 2
A41: =Gold_Dataset!A29 -> TTT008 | B41: =Gold_Dataset!B29 -> Nhóm tuổi nào gửi tiết kiệm TTT nhiều nhất?
A42: =Gold_Dataset!A30 -> TTT009 | B42: =Gold_Dataset!B30 -> Bao nhiêu % user TTT đang dùng Túi+?
A43: =Gold_Dataset!A31 -> TTT010 | B43: =Gold_Dataset!B31 -> Người dùng rút tiền từ TTT chủ yếu qua kênh nào?
A44: =Gold_Dataset!A32 -> TTT011 | B44: =Gold_Dataset!B32 -> User mới tháng này so tháng trước tăng hay giảm? Giảm bao nhiêu?
... A54: =Gold_Dataset!A42 -> TTT021 | B54: =Gold_Dataset!B42 -> user ttt giu tien bao lau truoc khi rut ra het?

Sheet Head_to_Head
A1: MCNEMAR'S CONTINGENCY TABLE
C3: Agent B Correct | D3: Agent B Wrong
B4: Agent A Correct | C4: =COUNTIFS(Evaluation_Scores!E:E,1,Evaluation_Scores!J:J,1) -> 0 | D4: =COUNTIFS(Evaluation_Scores!E:E,1,Evaluation_Scores!J:J,0) -> 1
B5: Agent A Wrong | C5: =COUNTIFS(Evaluation_Scores!E:E,0,Evaluation_Scores!J:J,1) -> 0 | D5: =COUNTIFS(Evaluation_Scores!E:E,0,Evaluation_Scores!J:J,0) -> 0
A7: McNemar Statistic (χ²) | C7: =IF((D4+C5)=0,"N/A",(D4-C5)^2/(D4+C5)) -> 1
A8: Critical value (α=0.05, df=1) | C8: 3.841
A9: Significant? | C9: =IF(C7="N/A","N/A",IF(C7>C8,"YES - Significant","NO - Not significant")) -> NO - Not significant
A12: BREAKDOWN BY DIFFICULTY
A13: Difficulty | B13: N | C13: Agent A EX Acc | D13: Agent B EX Acc | E13: Δ (B - A) | F13: Winner
A14: Simple | B14: =COUNTIF(Evaluation_Scores!B:B,"Simple") -> 11 | C14: =IFERROR(COUNTIFS(Evaluation_Scores!B:B,"Simple",Evaluation_Scores!E:E,1)/COUNTIF(Evaluation_Scores!B:B,"Simple"),"-") -> 0 | D14: =IFERROR(COUNTIFS(Evaluation_Scores!B:B,"Simple",Evaluation_Scores!J:J,1)/COUNTIF(Evaluation_Scores!B:B,"Simple"),"-") -> 0 | E14: =IFERROR(D14-C14,"-") -> 0 | F14: =IF(E14="-","",IF(E14>0.001,"B",IF(E14<-0.001,"A","Tie"))) -> Tie
A15: Moderate | B15: =COUNTIF(Evaluation_Scores!B:B,"Moderate") -> 13 | C15: =IFERROR(COUNTIFS(Evaluation_Scores!B:B,"Moderate",Evaluation_Scores!E:E,1)/COUNTIF(Evaluation_Scores!B:B,"Moderate"),"-") -> 0 | D15: =IFERROR(COUNTIFS(Evaluation_Scores!B:B,"Moderate",Evaluation_Scores!J:J,1)/COUNTIF(Evaluation_Scores!B:B,"Moderate"),"-") -> 0 | E15: =IFERROR(D15-C15,"-") -> 0 | F15: =IF(E15="-","",IF(E15>0.001,"B",IF(E15<-0.001,"A","Tie"))) -> Tie
A16: Complex | B16: =COUNTIF(Evaluation_Scores!B:B,"Complex") -> 12 | C16: =IFERROR(COUNTIFS(Evaluation_Scores!B:B,"Complex",Evaluation_Scores!E:E,1)/COUNTIF(Evaluation_Scores!B:B,"Complex"),"-") -> 0 | D16: =IFERROR(COUNTIFS(Evaluation_Scores!B:B,"Complex",Evaluation_Scores!J:J,1)/COUNTIF(Evaluation_Scores!B:B,"Complex"),"-") -> 0 | E16: =IFERROR(D16-C16,"-") -> 0 | F16: =IF(E16="-","",IF(E16>0.001,"B",IF(E16<-0.001,"A","Tie"))) -> Tie
A17: Ambiguous | B17: =COUNTIF(Evaluation_Scores!B:B,"Ambiguous") -> 4 | C17: =IFERROR(COUNTIFS(Evaluation_Scores!B:B,"Ambiguous",Evaluation_Scores!E:E,1)/COUNTIF(Evaluation_Scores!B:B,"Ambiguous"),"-") -> 0 | D17: =IFERROR(COUNTIFS(Evaluation_Scores!B:B,"Ambiguous",Evaluation_Scores!J:J,1)/COUNTIF(Evaluation_Scores!B:B,"Ambiguous"),"-") -> 0 | E17: =IFERROR(D17-C17,"-") -> 0 | F17: =IF(E17="-","",IF(E17>0.001,"B",IF(E17<-0.001,"A","Tie"))) -> Tie
A20: BREAKDOWN BY CATEGORY
A21: Difficulty | B21: N | C21: Agent A EX Acc | D21: Agent B EX Acc | E21: Δ (B - A) | F21: Winner
A22: Aggregation | B22: =COUNTIF(Evaluation_Scores!C:C,"Aggregation") -> 14 | C22: =IFERROR(COUNTIFS(Evaluation_Scores!C:C,"Aggregation",Evaluation_Scores!E:E,1)/COUNTIF(Evaluation_Scores!C:C,"Aggregation"),"-") -> 0 | D22: =IFERROR(COUNTIFS(Evaluation_Scores!C:C,"Aggregation",Evaluation_Scores!J:J,1)/COUNTIF(Evaluation_Scores!C:C,"Aggregation"),"-") -> 0 | E22: =IFERROR(D22-C22,"-") -> 0 | F22: =IF(E22="-","",IF(E22>0.001,"B",IF(E22<-0.001,"A","Tie"))) -> Tie
A23: Ranking + Filter | B23: =COUNTIF(Evaluation_Scores!C:C,"Ranking + Filter") -> 3 | C23: =IFERROR(COUNTIFS(Evaluation_Scores!C:C,"Ranking + Filter",Evaluation_Scores!E:E,1)/COUNTIF(Evaluation_Scores!C:C,"Ranking + Filter"),"-") -> 0 | D23: =IFERROR(COUNTIFS(Evaluation_Scores!C:C,"Ranking + Filter",Evaluation_Scores!J:J,1)/COUNTIF(Evaluation_Scores!C:C,"Ranking + Filter"),"-") -> 0 | E23: =IFERROR(D23-C23,"-") -> 0 | F23: =IF(E23="-","",IF(E23>0.001,"B",IF(E23<-0.001,"A","Tie"))) -> Tie
A24: JOIN | B24: =COUNTIF(Evaluation_Scores!C:C,"JOIN") -> 2 | C24: =IFERROR(COUNTIFS(Evaluation_Scores!C:C,"JOIN",Evaluation_Scores!E:E,1)/COUNTIF(Evaluation_Scores!C:C,"JOIN"),"-") -> 0 | D24: =IFERROR(COUNTIFS(Evaluation_Scores!C:C,"JOIN",Evaluation_Scores!J:J,1)/COUNTIF(Evaluation_Scores!C:C,"JOIN"),"-") -> 0 | E24: =IFERROR(D24-C24,"-") -> 0 | F24: =IF(E24="-","",IF(E24>0.001,"B",IF(E24<-0.001,"A","Tie"))) -> Tie
A25: Window + Complex | B25: =COUNTIF(Evaluation_Scores!C:C,"Window + Complex") -> 4 | C25: =IFERROR(COUNTIFS(Evaluation_Scores!C:C,"Window + Complex",Evaluation_Scores!E:E,1)/COUNTIF(Evaluation_Scores!C:C,"Window + Complex"),"-") -> 0 | D25: =IFERROR(COUNTIFS(Evaluation_Scores!C:C,"Window + Complex",Evaluation_Scores!J:J,1)/COUNTIF(Evaluation_Scores!C:C,"Window + Complex"),"-") -> 0 | E25: =IFERROR(D25-C25,"-") -> 0 | F25: =IF(E25="-","",IF(E25>0.001,"B",IF(E25<-0.001,"A","Tie"))) -> Tie
A26: Subquery | B26: =COUNTIF(Evaluation_Scores!C:C,"Subquery") -> 6 | C26: =IFERROR(COUNTIFS(Evaluation_Scores!C:C,"Subquery",Evaluation_Scores!E:E,1)/COUNTIF(Evaluation_Scores!C:C,"Subquery"),"-") -> 0 | D26: =IFERROR(COUNTIFS(Evaluation_Scores!C:C,"Subquery",Evaluation_Scores!J:J,1)/COUNTIF(Evaluation_Scores!C:C,"Subquery"),"-") -> 0 | E26: =IFERROR(D26-C26,"-") -> 0 | F26: =IF(E26="-","",IF(E26>0.001,"B",IF(E26<-0.001,"A","Tie"))) -> Tie
A27: Date/Time | B27: =COUNTIF(Evaluation_Scores!C:C,"Date/Time") -> 3 | C27: =IFERROR(COUNTIFS(Evaluation_Scores!C:C,"Date/Time",Evaluation_Scores!E:E,1)/COUNTIF(Evaluation_Scores!C:C,"Date/Time"),"-") -> 0 | D27: =IFERROR(COUNTIFS(Evaluation_Scores!C:C,"Date/Time",Evaluation_Scores!J:J,1)/COUNTIF(Evaluation_Scores!C:C,"Date/Time"),"-") -> 0 | E27: =IFERROR(D27-C27,"-") -> 0 | F27: =IF(E27="-","",IF(E27>0.001,"B",IF(E27<-0.001,"A","Tie"))) -> Tie
A28: Conditional Logic | B28: =COUNTIF(Evaluation_Scores!C:C,"Conditional Logic") -> 1 | C28: =IFERROR(COUNTIFS(Evaluation_Scores!C:C,"Conditional Logic",Evaluation_Scores!E:E,1)/COUNTIF(Evaluation_Scores!C:C,"Conditional Logic"),"-") -> 0 | D28: =IFERROR(COUNTIFS(Evaluation_Scores!C:C,"Conditional Logic",Evaluation_Scores!J:J,1)/COUNTIF(Evaluation_Scores!C:C,"Conditional Logic"),"-") -> 0 | E28: =IFERROR(D28-C28,"-") -> 0 | F28: =IF(E28="-","",IF(E28>0.001,"B",IF(E28<-0.001,"A","Tie"))) -> Tie
A29: Multi-step | B29: =COUNTIF(Evaluation_Scores!C:C,"Multi-step") -> 4 | C29: =IFERROR(COUNTIFS(Evaluation_Scores!C:C,"Multi-step",Evaluation_Scores!E:E,1)/COUNTIF(Evaluation_Scores!C:C,"Multi-step"),"-") -> 0 | D29: =IFERROR(COUNTIFS(Evaluation_Scores!C:C,"Multi-step",Evaluation_Scores!J:J,1)/COUNTIF(Evaluation_Scores!C:C,"Multi-step"),"-") -> 0 | E29: =IFERROR(D29-C29,"-") -> 0 | F29: =IF(E29="-","",IF(E29>0.001,"B",IF(E29<-0.001,"A","Tie"))) -> Tie

Sheet Error_Analysis
A1: ID | B1: Agent | C1: Error Category | D1: Error Subcategory | E1: Description | F1: Root Cause | G1: Severity | H1: Reproducible? | I1: Fix Priority | J1: Suggested Fix

Sheet Summary_Dashboard
A1: EVALUATION SUMMARY DASHBOARD
A3: OVERALL METRICS
A4: Metric | B4: Agent A | C4: Agent B | D4: Δ (B - A) | E4: Winner
A5: Total Questions | B5: =COUNTA(Evaluation_Scores!A:A)-1 -> 52 | C5: =COUNTA(Evaluation_Scores!A:A)-1 -> 52 | D5: =IFERROR(C5-B5,"-") -> 0 | E5: =IF(ISNUMBER(D5),IF(D5>0.001,"B ✓",IF(D5<-0.001,"A ✓","Tie")),"-") -> Tie
A6: Valid SQL Rate | B6: =IFERROR(COUNTIF(Evaluation_Scores!D:D,1)/(COUNTA(Evaluation_Scores!A:A)-1),"-") -> 0 | C6: =IFERROR(COUNTIF(Evaluation_Scores!I:I,1)/(COUNTA(Evaluation_Scores!A:A)-1),"-") -> 0 | D6: =IFERROR(C6-B6,"-") -> 0 | E6: =IF(ISNUMBER(D6),IF(D6>0.001,"B ✓",IF(D6<-0.001,"A ✓","Tie")),"-") -> Tie
A7: Execution Accuracy (EX) | B7: =IFERROR(COUNTIF(Evaluation_Scores!E:E,1)/(COUNTA(Evaluation_Scores!A:A)-1),"-") -> 0.019230769 | C7: =IFERROR(COUNTIF(Evaluation_Scores!J:J,1)/(COUNTA(Evaluation_Scores!A:A)-1),"-") -> 0 | D7: =IFERROR(C7-B7,"-") -> -0.019230769 | E7: =IF(ISNUMBER(D7),IF(D7>0.001,"B ✓",IF(D7<-0.001,"A ✓","Tie")),"-") -> A ✓
A8: Avg Partial Credit | B8: =IFERROR(AVERAGE(Evaluation_Scores!F:F),"-") -> - | C8: =IFERROR(AVERAGE(Evaluation_Scores!K:K),"-") -> - | D8: =IFERROR(C8-B8,"-") -> - | E8: =IF(ISNUMBER(D8),IF(D8>0.001,"B ✓",IF(D8<-0.001,"A ✓","Tie")),"-") -> -
A9: Schema Linking Acc | B9: =IFERROR(AVERAGE(Evaluation_Scores!G:G),"-") -> - | C9: =IFERROR(AVERAGE(Evaluation_Scores!L:L),"-") -> - | D9: =IFERROR(C9-B9,"-") -> - | E9: =IF(ISNUMBER(D9),IF(D9>0.001,"B ✓",IF(D9<-0.001,"A ✓","Tie")),"-") -> -
A10: Avg Efficiency | B10: =IFERROR(AVERAGE(Evaluation_Scores!H:H),"-") -> - | C10: =IFERROR(AVERAGE(Evaluation_Scores!M:M),"-") -> - | D10: =IFERROR(C10-B10,"-") -> - | E10: =IF(ISNUMBER(D10),IF(D10>0.001,"B ✓",IF(D10<-0.001,"A ✓","Tie")),"-") -> -
A11: Hallucination Rate | B11: =IFERROR(COUNTIF(Agent_A_Results!D:D,"HALLUCINATION")/(COUNTA(Evaluation_Scores!A:A)-1),"-") -> 0 | C11: =IFERROR(COUNTIF(Agent_B_Results!D:D,"HALLUCINATION")/(COUNTA(Evaluation_Scores!A:A)-1),"-") -> 0 | D11: =IFERROR(C11-B11,"-") -> 0 | E11: =IF(ISNUMBER(D11),IF(D11>0.001,"B ✓",IF(D11<-0.001,"A ✓","Tie")),"-") -> Tie
A12: Avg Latency (ms) | B12: =IFERROR(AVERAGE(Agent_A_Results!G:G),"-") -> - | C12: =IFERROR(AVERAGE(Agent_B_Results!G:G),"-") -> - | D12: =IFERROR(C12-B12,"-") -> - | E12: =IF(ISNUMBER(D12),IF(D12>0.001,"B ✓",IF(D12<-0.001,"A ✓","Tie")),"-") -> -
A14: STATISTICAL SIGNIFICANCE
A15: McNemar χ² | B15: =Head_to_Head!C7 -> 1
A16: Significant (p<0.05)? | B16: =Head_to_Head!C9 -> NO - Not significant
A18: HEAD-TO-HEAD WIN/LOSS
A19: Both Correct | B19: =Head_to_Head!C4 -> 0
A20: A wins (A correct, B wrong) | B20: =Head_to_Head!D4 -> 1
A21: B wins (B correct, A wrong) | B21: =Head_to_Head!C5 -> 0
A22: Both Wrong | B22: =Head_to_Head!D5 -> 0
